Workbook

Sheet Summary Of Financials
C5: SUMMARY OF FINANCIALS
C6: DESCRIPTION | D6: YEAR 1 | E6: YEAR 2 | F6: YEAR 3 | G6: YEAR 4 | H6: YEAR 5 | I6: YEAR 6 | J6: YEAR 7 | K6: YEAR 8 | L6: YEAR 9 | M6: YEAR 10 | N6: TOTAL
C7: Projected Revenue Generation | D7: ='Income Statement'!K14 -> 30653209512 | E7: ='Income Statement'!N14 -> 6.437174e+10 | F7: ='Income Statement'!Q14 -> 1.2378754e+11 | G7: ='Income Statement'!T14 -> 1.7330256e+11 | H7: ='Income Statement'!W14 -> 2.2745961e+11 | I7: ='Income Statement'!Z14 -> 3.3883259e+11 | J7: ='Income Statement'!AC14 -> 2.5077422e+11 | K7: ='Income Statement'!AF14 -> 2.6331293e+11 | L7: ='Income Statement'!AI14 -> 2.7647857e+11 | M7: ='Income Statement'!AL14 -> 3.903025e+11 | N7: =SUM(D7:M7) -> 2.1392755e+12
C8: Less: Direct Cost | D8: ='Income Statement'!K29 -> 2.7379561e+10 | E8: ='Income Statement'!N29 -> 4.1652759e+10 | F8: ='Income Statement'!Q29 -> 6.3578396e+10 | G8: ='Income Statement'!T29 -> 8.7696597e+10 | H8: ='Income Statement'!W29 -> 1.1422662e+11 | I8: ='Income Statement'!Z29 -> 1.148064e+11 | J8: ='Income Statement'!AC29 -> 1.1544416e+11 | K8: ='Income Statement'!AF29 -> 1.161457e+11 | L8: ='Income Statement'!AI29 -> 1.1691739e+11 | M8: ='Income Statement'!AL29 -> 1.1776625e+11 | N8: =SUM(D8:M8) -> 9.1561385e+11
C9: Gross Profit | D9: ='Income Statement'!K31 -> 3.2736482e+09 | E9: ='Income Statement'!N31 -> 2.2718981e+10 | F9: ='Income Statement'!Q31 -> 6.0209145e+10 | G9: ='Income Statement'!T31 -> 8.5605961e+10 | H9: ='Income Statement'!W31 -> 1.1323299e+11 | I9: ='Income Statement'!Z31 -> 2.2402619e+11 | J9: ='Income Statement'!AC31 -> 1.3533005e+11 | K9: ='Income Statement'!AF31 -> 1.4716723e+11 | L9: ='Income Statement'!AI31 -> 1.5956118e+11 | M9: ='Income Statement'!AL31 -> 2.7253625e+11 | N9: =SUM(D9:M9) -> 1.2236616e+12
C10: Operating and Maintenance Cost | D10: ='Income Statement'!K63 -> 5.2767062e+09 | E10: ='Income Statement'!N63 -> 8.1710879e+09 | F10: ='Income Statement'!Q63 -> 1.5090476e+10 | G10: ='Income Statement'!T63 -> 2.4188114e+10 | H10: ='Income Statement'!W63 -> 3.5248346e+10 | I10: ='Income Statement'!Z63 -> 5.1893013e+10 | J10: ='Income Statement'!AC63 -> 4.6102183e+10 | K10: ='Income Statement'!AF63 -> 3.7756276e+10 | L10: ='Income Statement'!AI63 -> 3.0804392e+10 | M10: ='Income Statement'!AL63 -> 2.886227e+10 | N10: =SUM(D10:M10) -> 2.8339286e+11
C11: Net Earnings before Tax | D11: ='Income Statement'!K64 -> -2.003058e+09 | E11: ='Income Statement'!N64 -> 1.4547893e+10 | F11: ='Income Statement'!Q64 -> 4.5118669e+10 | G11: ='Income Statement'!T64 -> 6.1417847e+10 | H11: ='Income Statement'!W64 -> 7.7984643e+10 | I11: ='Income Statement'!Z64 -> 1.7213317e+11 | J11: ='Income Statement'!AC64 -> 8.922787e+10 | K11: ='Income Statement'!AF64 -> 1.0941095e+11 | L11: ='Income Statement'!AI64 -> 1.2875679e+11 | M11: ='Income Statement'!AL64 -> 2.4367398e+11 | N11: =SUM(D11:M11) -> 9.4026875e+11
C12: Less: Tax | D12: ='Income Statement'!K70 -> 0 | E12: ='Income Statement'!N70 -> 4.8008048e+09 | F12: ='Income Statement'!Q70 -> 1.4889161e+10 | G12: ='Income Statement'!T70 -> 2.0267889e+10 | H12: ='Income Statement'!W70 -> 2.5734932e+10 | I12: ='Income Statement'!Z70 -> 5.6803947e+10 | J12: ='Income Statement'!AC70 -> 2.9445197e+10 | K12: ='Income Statement'!AF70 -> 3.6105613e+10 | L12: ='Income Statement'!AI70 -> 4.248974e+10 | M12: ='Income Statement'!AL70 -> 8.0412413e+10 | N12: =SUM(D12:M12) -> 3.109497e+11
C13: Less: Repayment Expense - Long term facility | I13: ='[1]Income Statement'!Z67 -> 1.8717388e+11 | J13: ='[1]Income Statement'!AC67 -> 1.9278909e+11 | K13: ='[1]Income Statement'!AF67 -> 1.9857277e+11 | L13: ='[1]Income Statement'!AI67 -> 2.0452995e+11 | M13: ='[1]Income Statement'!AL67 -> 2.1066585e+11 | N13: =SUM(D13:M13) -> 9.9373153e+11
C14: Net Earnings after Tax | D14: ='Income Statement'!K71 -> -2.003058e+09 | E14: ='Income Statement'!N71 -> 9.7470885e+09 | F14: ='Income Statement'!Q71 -> 3.0229508e+10 | G14: ='Income Statement'!T71 -> 4.1149957e+10 | H14: ='Income Statement'!W71 -> 5.2249711e+10 | I14: ='Income Statement'!Z71 -> 1.1532923e+11 | J14: ='Income Statement'!AC71 -> 5.9782673e+10 | K14: ='Income Statement'!AF71 -> 7.3305336e+10 | L14: ='Income Statement'!AI71 -> 8.6267048e+10 | M14: ='Income Statement'!AL67 -> 2.4367398e+11 | N14: =SUM(D14:M14) -> 7.0973147e+11
C15: Discounted Factor | D15: 0.909 | E15: 0.826 | F15: 0.751 | G15: 0.683 | H15: 0.621 | I15: 0.564 | J15: 0.513 | K15: 0.467 | L15: 0.424 | M15: 0.386
C16: Present Value | D16: =D15*D14 -> -1.8207797e+09 | E16: =E15*E14 -> 8.0510951e+09 | F16: =F15*F14 -> 2.2702361e+10 | G16: =G15*G14 -> 2.8105421e+10 | H16: =H15*H14 -> 3.244707e+10 | I16: =I15*I14 -> 6.5045683e+10 | J16: =J15*J14 -> 3.0668511e+10 | K16: =K15*K14 -> 3.4233592e+10 | ... M16: =M15*M14 -> 9.4058155e+10 | N16: =SUM(D16:M16) -> 3.5006834e+11
C18: Projected Total Income | D18: =D7 -> 30653209512 | E18: =E7 -> 6.437174e+10 | F18: =F7 -> 1.2378754e+11 | G18: =G7 -> 1.7330256e+11 | H18: =H7 -> 2.2745961e+11 | I18: =I7 -> 3.3883259e+11 | J18: =J7 -> 2.5077422e+11 | K18: =K7 -> 2.6331293e+11 | ... M18: =M7 -> 3.903025e+11 | N18: =SUM(D18:M18) -> 2.1392755e+12
C19: Total Investment | D19: ='Facility Repayment Plan'!C29 -> 1.6145783e+11 | E19: ='Facility Repayment Plan'!D29 -> 1.7760361e+11 | F19: ='Facility Repayment Plan'!E29 -> 1.9536397e+11 | G19: ='Facility Repayment Plan'!F29 -> 2.1490037e+11 | H19: ='Facility Repayment Plan'!G29 -> 2.3639041e+11 | N19: =SUM(D19:M19) -> 9.857162e+11
C20: Repayment Plan | D20: ='[1]Facility Repayment Plan'!C30 -> 0 | E20: ='[1]Facility Repayment Plan'!D30 -> 0 | F20: ='[1]Facility Repayment Plan'!E30 -> 0 | G20: ='[1]Facility Repayment Plan'!F30 -> 0 | H20: ='[1]Facility Repayment Plan'!G30 -> 0 | I20: =I13 -> 1.8717388e+11 | J20: =J13 -> 1.9278909e+11 | K20: =K13 -> 1.9857277e+11 | L20: =L13 -> 2.0452995e+11 | M20: =M13 -> 2.1066585e+11 | N20: =SUM(D20:M20) -> 9.9373153e+11

Sheet Summary Of Financials $
C5: SUMMARY OF FINANCIALS $
C6: DESCRIPTION | D6: YEAR 1 | E6: YEAR 2 | F6: YEAR 3 | G6: YEAR 4 | H6: YEAR 5 | I6: YEAR 6 | J6: YEAR 7 | K6: YEAR 8 | L6: YEAR 9 | M6: YEAR 10 | N6: TOTAL
C7: Projected Revenue Generation | D7: =('Income Statement'!K14)/952.639 -> 32177152 | E7: =('Income Statement'!N14)/1047.9029 -> 61429108 | F7: =('Income Statement'!Q14)/1152.69319 -> 1.0738984e+08 | G7: =('Income Statement'!T14)/1267.962509 -> 1.3667798e+08 | H7: =('Income Statement'!W14)/1394.7587599 -> 1.6308168e+08 | I7: =('Income Statement'!Z14)/1534.23463589 -> 2.2084796e+08 | J7: =('Income Statement'!AC14)/1687.658099479 -> 1.4859302e+08 | K7: =('Income Statement'!AF14)/1856.4239094269 -> 1.4183879e+08 | L7: =('Income Statement'!AI14)/2042.06630036959 -> 1.3539158e+08 | M7: =('Income Statement'!AL14)/2246.27293040655 -> 1.737556e+08 | N7: =SUM(D7:M7) -> 1.3211827e+09
C8: Less: Direct Cost | D8: =('Income Statement'!K29)/952.639 -> 28740752 | E8: =('Income Statement'!N29)/1047.9029 -> 39748682 | F8: =('Income Statement'!Q29)/1152.69319 -> 55156391 | G8: =('Income Statement'!T29)/1267.962509 -> 69163399 | H8: =('Income Statement'!W29)/1394.7587599 -> 81897043 | I8: =('Income Statement'!Z29)/1534.23463589 -> 74829755 | J8: =('Income Statement'!AC29)/1687.658099479 -> 68404947 | K8: =('Income Statement'!AF29)/1856.4239094269 -> 62564213 | L8: =('Income Statement'!AI29)/2042.06630036959 -> 57254455 | M8: =('Income Statement'!AL29)/2246.27293040655 -> 52427402 | N8: =SUM(D8:M8) -> 5.9018704e+08
C9: Gross Profit | D9: =('Income Statement'!K31)/952.639 -> 3436399.5 | E9: =('Income Statement'!N31)/1047.9029 -> 21680426 | F9: =('Income Statement'!Q31)/1152.69319 -> 52233453 | G9: =('Income Statement'!T31)/1267.962509 -> 67514584 | H9: =('Income Statement'!W31)/1394.7587599 -> 81184641 | I9: =('Income Statement'!Z31)/1534.23463589 -> 1.460182e+08 | J9: =('Income Statement'!AC31)/1687.658099479 -> 80188074 | K9: =('Income Statement'!AF31)/1856.4239094269 -> 79274580 | L9: =('Income Statement'!AI31)/2042.06630036959 -> 78137120 | M9: =('Income Statement'!AL31)/2246.27293040655 -> 1.213282e+08 | N9: =SUM(D9:M9) -> 7.3099568e+08
C10: Operating and Maintenance Cost | D10: =('Income Statement'!K63)/952.639 -> 5539040.7 | E10: =('Income Statement'!N63)/1047.9029 -> 7797562 | F10: =('Income Statement'!Q63)/1152.69319 -> 13091494 | G10: =('Income Statement'!T63)/1267.962509 -> 19076364 | H10: =('Income Statement'!W63)/1394.7587599 -> 25272002 | I10: =('Income Statement'!Z63)/1534.23463589 -> 33823387 | J10: =('Income Statement'!AC63)/1687.658099479 -> 27317253 | K10: =('Income Statement'!AF63)/1856.4239094269 -> 20338176 | L10: =('Income Statement'!AI63)/2042.06630036959 -> 15084913 | M10: =('Income Statement'!AL63)/2246.27293040655 -> 12848960 | N10: =SUM(D10:M10) -> 1.8018915e+08
C11: Net Earnings before Tax | D11: =('Income Statement'!K64)/952.639 -> -2102641.2 | E11: =('Income Statement'!N64)/1047.9029 -> 13882864 | F11: =('Income Statement'!Q64)/1152.69319 -> 39141959 | G11: =('Income Statement'!T64)/1267.962509 -> 48438220 | H11: =('Income Statement'!W64)/1394.7587599 -> 55912639 | I11: =('Income Statement'!Z64)/1534.23463589 -> 1.1219482e+08 | J11: =('Income Statement'!AC64)/1687.658099479 -> 52870821 | K11: =('Income Statement'!AF64)/1856.4239094269 -> 58936404 | L11: =('Income Statement'!AI64)/2042.06630036959 -> 63052208 | M11: =('Income Statement'!AL64)/2246.27293040655 -> 1.0847924e+08 | N11: =SUM(D11:M11) -> 5.5080653e+08
C12: Less: Tax | D12: =('Income Statement'!K70)/952.639 -> 0 | E12: =('Income Statement'!N70)/1047.9029 -> 4581345.1 | F12: =('Income Statement'!Q70)/1152.69319 -> 12916846 | G12: =('Income Statement'!T70)/1267.962509 -> 15984613 | H12: =('Income Statement'!W70)/1394.7587599 -> 18451171 | I12: =('Income Statement'!Z70)/1534.23463589 -> 37024289 | J12: =('Income Statement'!AC70)/1687.658099479 -> 17447371 | K12: =('Income Statement'!AF70)/1856.4239094269 -> 19449013 | L12: =('Income Statement'!AI70)/2042.06630036959 -> 20807229 | M12: =('Income Statement'!AL70)/2246.27293040655 -> 35798149 | N12: =SUM(D12:M12) -> 1.8246003e+08
C13: Less: Repayment Expense - Long term facility | D13: 0 | E13: 0 | F13: 0 | G13: 0 | H13: 0 | I13: =D19 -> 169484800 | J13: =E19 -> 169484800 | K13: =F19 -> 169484800 | L13: =G19 -> 169484800 | M13: =H19 -> 169484800 | N13: =SUM(D13:M13) -> 847424000
C14: Net Earnings after Tax | D14: =('Income Statement'!K71)/952.639 -> -2102641.2 | E14: =('Income Statement'!N71)/1047.9029 -> 9301518.8 | F14: =('Income Statement'!Q71)/1152.69319 -> 26225112 | G14: =('Income Statement'!T71)/1267.962509 -> 32453607 | H14: =('Income Statement'!W71)/1394.7587599 -> 37461468 | I14: =('Income Statement'!Z71)/1534.23463589 -> 75170527 | J14: =('Income Statement'!AC71)/1687.658099479 -> 35423450 | K14: =('Income Statement'!AF71)/1856.4239094269 -> 39487391 | L14: =('Income Statement'!AI71)/2042.06630036959 -> 42244979 | M14: =('Income Statement'!AL67)/2246.27293040655 -> 1.0847924e+08 | N14: =SUM(D14:M14) -> 4.0414465e+08
C15: Discounted Factor | D15: 0.909 | E15: 0.826 | F15: 0.751 | G15: 0.683 | H15: 0.621 | I15: 0.564 | J15: 0.513 | K15: 0.467 | L15: 0.424 | M15: 0.386
C16: Present Value | D16: =(D15*D14)/952.639 -> -2006.3223 | E16: =(E15*E14)/1047.9029 -> 7331.8382 | F16: =(F15*F14)/1152.69319 -> 17086.125 | G16: =(G15*G14)/1267.962509 -> 17481.443 | H16: =(H15*H14)/1394.7587599 -> 16679.28 | I16: =(I15*I14)/1534.23463589 -> 27633.438 | J16: =(J15*J14)/1687.658099479 -> 10767.72 | K16: =(K15*K14)/1856.4239094269 -> 9933.4055 | L16: =(L15*L14)/2042.06630036959 -> 8771.4445 | M16: =(M15*M14)/2246.27293040655 -> 18641.095 | N16: =SUM(D16:M16) -> 132319.47
D17: 0 | E17: 0 | F17: 0 | G17: 0 | H17: 0 | I17: 0 | J17: 0 | K17: 0 | L17: 0 | M17: 0
C18: Projected Total Income | D18: =(D7)/952.639 -> 33776.857 | E18: =(E7)/1047.9029 -> 58620.992 | F18: =(F7)/1152.69319 -> 93164.291 | G18: =(G7)/1267.962509 -> 107793.39 | H18: =(H7)/1394.7587599 -> 116924.65 | I18: =(I7)/1534.23463589 -> 143946.66 | J18: =(J7)/1687.658099479 -> 88046.875 | K18: =(K7)/1856.4239094269 -> 76404.313 | L18: =(L7)/2042.06630036959 -> 66301.263 | M18: =(M7)/2246.27293040655 -> 77352.845 | N18: =SUM(D18:M18) -> 862332.15
C19: Total Investment | D19: =('Facility Repayment Plan'!C29)/952.639 -> 169484800 | E19: =('Facility Repayment Plan'!D29)/1047.9029 -> 169484800 | F19: =('Facility Repayment Plan'!E29)/1152.69319 -> 169484800 | G19: =('Facility Repayment Plan'!F29)/1267.962509 -> 169484800 | H19: =('Facility Repayment Plan'!G29)/1394.7587599 -> 169484800 | I19: 0 | J19: 0 | K19: 0 | L19: 0 | M19: 0 | N19: =SUM(D19:M19) -> 847424000
C20: Repayment Plan | D20: ='[1]Facility Repayment Plan'!C30 -> 0 | E20: ='[1]Facility Repayment Plan'!D30 -> 0 | F20: ='[1]Facility Repayment Plan'!E30 -> 0 | G20: ='[1]Facility Repayment Plan'!F30 -> 0 | H20: ='[1]Facility Repayment Plan'!G30 -> 0 | I20: =I13 -> 169484800 | J20: =J13 -> 169484800 | K20: =K13 -> 169484800 | L20: =L13 -> 169484800 | M20: =M13 -> 169484800 | N20: =SUM(D20:M20) -> 847424000

Sheet Parameters and Summary
F2: Year 1 | G2: Year 2 | H2: Year 3 | I2: Year 4 | J2: Year 5 | K2: Year 6 | L2: Year 7 | M2: Year 8 | N2: Year 9 | O2: Year 10
C3: Assumptions
C4: Transport Utility Operating Hours per day (hrs) | E4: 24
C5: Human Operating Hours per day/shift (hrs) | E5: 8
C6: Number of Shift per day | E6: 3
C8: Number of trips
C9: Taxi
C10: Peak | D10: 6am- 6pm | E10: 15
C11: Off peak | D11: 6pm- 9pm | E11: 3
C12: Overnight | D12: 9pm - 6am | E12: 1
C15: Bus
C16: Peak | D16: 6am- 6pm | E16: 7
C17: Off peak | D17: 6pm- 9pm | E17: 3
C18: Overnight | D18: 9pm - 6am | E18: 0
C21: Number of operating days per week | E21: 6
C22: Number of operating week per month | E22: 4
C23: Number of operating month per year | E23: 12
C24: Taxi Fare per trip (NGN) | E24: 1500 | F24: 1500 | G24: =F24*1.05 -> 1575 | H24: =G24*1.05 -> 1653.75 | I24: =H24*1.05 -> 1736.4375 | J24: =I24*1.05 -> 1823.2594 | K24: =J24*1.05 -> 1914.4223 | L24: =K24*1.05 -> 2010.1435 | M24: =L24*1.05 -> 2110.6506 | N24: =M24*1.05 -> 2216.1832 | O24: =N24*1.05 -> 2326.9923
C30: Number of PAX Per Trip- Taxi
C31: Peak | D31: 6am- 6pm | E31: 1
C32: Off peak | D32: 6pm- 9pm | E32: 1
C33: Overnight | D33: 9pm - 6am | E33: 1
C35: Number of PAX Per Trip- Bus
C36: Peak | D36: 6am- 6pm | E36: 37
C37: Off peak | D37: 6pm- 11pm | E37: 25
C38: Overnight | D38: 11pm - 6am | E38: 0
C41: Deployment Efficiency
C42: Taxi and Bus
C43: Location | D43: Peak | E43: Off-Peak | F43: Night
C44: Retail and Recreation (+56%) | D44: 1 | E44: 0.75 | F44: 0.1
C45: Supermarket and Pharmacy (+75%) | D45: =D44 -> 1 | E45: =E44 -> 0.75 | F45: =F44 -> 0.1
C46: Parks (+43%) | D46: =D45 -> 1 | E46: =E45 -> 0.75 | F46: =F45 -> 0.1
C47: Workplaces (+73%) | D47: =D46 -> 1 | E47: =E46 -> 0.75 | F47: =F46 -> 0.1
C48: Residential Areas (+19%) | D48: =D47 -> 1 | E48: =E47 -> 0.75 | F48: =F47 -> 0.1
C49: Public Transport (+33%) | D49: =D48 -> 1 | E49: =E48 -> 0.75 | F49: =F48 -> 0.1
C51: Bus
C52: Location | D52: Peak | E52: Off-Peak | F52: Night
C53: Retail and Recreation (+56%) | D53: 1 | E53: 0.75 | F53: 0
C54: Supermarket and Pharmacy (+75%) | D54: =D53 -> 1 | E54: =E53 -> 0.75 | F54: =F53 -> 0
C55: Parks (+43%) | D55: =D54 -> 1 | E55: =E54 -> 0.75 | F55: =F54 -> 0
C56: Workplaces (+73%) | D56: =D55 -> 1 | E56: =E55 -> 0.75 | F56: =F55 -> 0
C57: Residential Areas (+19%) | D57: =D56 -> 1 | E57: =E56 -> 0.75 | F57: =F56 -> 0
C58: Public Transport (+33%) | D58: =D57 -> 1 | E58: =E57 -> 0.75 | F58: =F57 -> 0
F60: 1 | G60: 2 | H60: 3 | I60: 4 | J60: 5 | K60: 6 | L60: 7 | M60: 8 | N60: 9 | O60: 10
C61: Bus Fare per trip (NGN) | E61: 500 | F61: 500 | G61: =F61*1.05 -> 525 | H61: =G61*1.05 -> 551.25 | I61: =H61*1.05 -> 578.8125 | J61: =I61*1.05 -> 607.75313 | K61: =J61*1.05 -> 638.14078 | L61: =K61*1.05 -> 670.04782 | M61: =L61*1.05 -> 703.55021 | N61: =M61*1.05 -> 738.72772 | O61: =N61*1.05 -> 775.66411
C65: Annual Growth Rate | E65: 0.1
C66: Investment Period (year) | E66: 5
C68: Depreciation ` | E68: 0.1
C70: Exchange Rate | E70: 952.639 | F70: 10% annual depreciation
C73: PAX Average Occupancy- Taxi
C74: Retail and Recreation (+56%) | E74: 1
C75: Supermarket and Pharmacy (+75%) | E75: 1
C76: Parks (+43%) | E76: 1
C77: Workplaces (+73%) | E77: 1
C78: Residential Areas (+19%) | E78: 1
C79: Public Transport (+33%) | E79: 1
C81: PAX Average Occupancy- BUS
C82: Retail and Recreation (+56%) | E82: 0.7
C83: Supermarket and Pharmacy (+75%) | E83: 0.686
C84: Parks (+43%) | E84: 0.6
C85: Workplaces (+73%) | E85: 0.72
C86: Residential Areas (+19%) | E86: 0.671
C87: Public Transport (+33%) | E87: 0.72
C91: Procurement
C92: Taxi | E92: 2000
C93: Bus | E93: 400

Sheet Exchange Rate growth 
D3: Year 1 | E3: Year 2 | F3: Year 3 | G3: Year 4 | H3: Year 5 | I3: Year 6 | J3: Year 7 | K3: Year 8 | L3: Year 9 | M3: Year 10
D4: NGN | E4: NGN | F4: NGN | G4: NGN | H4: NGN | I4: NGN | J4: NGN | K4: NGN | L4: NGN | M4: NGN
C5: Depreciation Factor | E5: 1.1 | F5: 1.1 | G5: 1.1 | H5: 1.1 | I5: 1.1 | J5: 1.1 | K5: 1.1 | L5: 1.1 | M5: 1.1
C6: Exchange | D6: ='Parameters and Summary'!E70 -> 952.639 | E6: =D6*E5 -> 1047.9029 | F6: =E6*F5 -> 1152.6932 | G6: =F6*G5 -> 1267.9625 | H6: =G6*H5 -> 1394.7588 | I6: =H6*I5 -> 1534.2346 | J6: =I6*J5 -> 1687.6581 | K6: =J6*K5 -> 1856.4239 | L6: =K6*L5 -> 2042.0663 | M6: =L6*M5 -> 2246.2729
D10: 952.639 | E10: 1047.9029 | F10: 1152.6932 | G10: 1267.9625 | H10: 1394.7588 | I10: 1534.2346 | J10: 1687.6581 | K10: 1856.4239 | L10: 2042.0663 | M10: 2246.2729
C14: Inflation | D14: 0.05 | E14: 0.05 | F14: 0.05 | G14: 0.05 | H14: 0.05 | I14: 0.05 | J14: 0.05 | K14: 0.05 | L14: 0.05 | M14: 0.05

Sheet Income Statement
C2: Projected Income Statement
C3: Enhancing Public Transportation in the FCT
E4: Cummulative | H4: 2023 | K4: 45657 | N4: 46022 | Q4: 46387 | T4: 46752 | W4: 47118 | Z4: 47483 | AC4: 47848 | AF4: 48213 | AI4: 48579 | AL4: 48944
H5: Construction/ Deployment Period | K5: 1 | N5: =K5+1 -> 2 | Q5: =N5+1 -> 3 | T5: =Q5+1 -> 4 | W5: =T5+1 -> 5 | Z5: =W5+1 -> 6 | AC5: =Z5+1 -> 7 | AF5: =AC5+1 -> 8 | AI5: =AF5+1 -> 9 | AL5: =AI5+1 -> 10
E6: NGN | F6: RATE | G6: USD | H6: NGN | I6: RATE | J6: USD | K6: NGN | L6: RATE | M6: USD | N6: NGN | O6: RATE | P6: USD | Q6: NGN | R6: RATE | S6: USD | T6: NGN | U6: RATE | V6: USD | W6: NGN | X6: RATE | Y6: USD | Z6: NGN | AA6: RATE | AB6: USD | AC6: NGN | AD6: RATE | AE6: USD | AF6: NGN | AG6: RATE | AH6: USD | AI6: NGN | AJ6: RATE | AK6: USD | AL6: NGN | AM6: RATE | AN6: USD
C7: REVENUE
C9: Transportation Fare
C10: Taxi | E10: =K10+N10+Q10+T10+W10+Z10+AC10+AF10+AI10+AL10 -> 7.8514975e+11 | F10: ='Parameters and Summary'!E70 -> 952.639 | G10: =E10/F10 -> 8.2418392e+08 | I10: =F10 -> 952.639 | J10: =H10/I10 -> 0 | K10: ='Revenue Schedule'!AE31 -> 14990400000 | L10: =I10 -> 952.639 | M10: =K10/L10 -> 15735656 | N10: ='Cashflow Statement'!Q16 -> 31479840000 | O10: ='Exchange Rate growth '!E6 -> 1047.9029 | P10: =N10/O10 -> 30040799 | Q10: ='Cashflow Statement'!T16 -> 49580748000 | R10: ='Exchange Rate growth '!F6 -> 1152.6932 | S10: =Q10/R10 -> 43012962 | T10: ='Cashflow Statement'!W16 -> 69413047200 | U10: ='Exchange Rate growth '!G6 -> 1267.9625 | V10: =T10/U10 -> 54743769 | W10: ='Cashflow Statement'!Z16 -> 91104624450 | X10: ='Exchange Rate growth '!H6 -> 1394.7588 | Y10: =W10/X10 -> 65319270 | Z10: ='Cashflow Statement'!AC16 -> 9.5659856e+10 | AA10: ='Exchange Rate growth '!I6 -> 1534.2346 | AB10: =Z10/AA10 -> 62350213 | AC10: ='Cashflow Statement'!AF16 -> 1.0044285e+11 | AD10: ='Exchange Rate growth '!J6 -> 1687.6581 | AE10: =AC10/AD10 -> 59516112 | AF10: ='Cashflow Statement'!AI16 -> 1.0546499e+11 | AG10: ='Exchange Rate growth '!K6 -> 1856.4239 | AH10: =AF10/AG10 -> 56810834 | AI10: ='Cashflow Statement'!AL16 -> 1.1073824e+11 | AJ10: ='Exchange Rate growth '!L6 -> 2042.0663 | AK10: =AI10/AJ10 -> 54228524 | AL10: ='Cashflow Statement'!AO16 -> 1.1627515e+11 | AM10: ='Exchange Rate growth '!M6 -> 2246.2729 | AN10: =AL10/AM10 -> 51763591
C11: Bus | E11: =K11+N11+Q11+T11+W11+Z11+AC11+AF11+AI11+AL11 -> 1.1541257e+12 | F11: =F10 -> 952.639 | G11: =E11/F11 -> 1.2115037e+09 | I11: =I10 -> 952.639 | K11: ='Revenue Schedule'!AE64 -> 15662809512 | L11: =L10 -> 952.639 | M11: =K11/L11 -> 16441495 | N11: ='Cashflow Statement'!Q17 -> 3.28919e+10 | O11: =O10 -> 1047.9029 | P11: =N11/O11 -> 31388309 | Q11: ='Cashflow Statement'!T17 -> 7.4206793e+10 | R11: =R10 -> 1152.6932 | S11: =Q11/R11 -> 64376882 | T11: ='Cashflow Statement'!W17 -> 1.0388951e+11 | U11: =U10 -> 1267.9625 | V11: =T11/U11 -> 81934213 | W11: ='Cashflow Statement'!Z17 -> 1.3635498e+11 | X11: =X10 -> 1394.7588 | Y11: =W11/X11 -> 97762413 | Z11: ='Cashflow Statement'!AC17 -> 1.4317273e+11 | AA11: =AA10 -> 1534.2346 | AB11: =Z11/AA11 -> 93318667 | AC11: ='Cashflow Statement'!AF17 -> 1.5033137e+11 | AD11: =AD10 -> 1687.6581 | AE11: =AC11/AD11 -> 89076910 | AF11: ='Cashflow Statement'!AI17 -> 1.5784794e+11 | AG11: =AG10 -> 1856.4239 | AH11: =AF11/AG11 -> 85027959 | AI11: ='Cashflow Statement'!AL17 -> 1.6574033e+11 | AJ11: =AJ10 -> 2042.0663 | AK11: =AI11/AJ11 -> 81163052 | AL11: ='Cashflow Statement'!AO17 -> 1.7402735e+11 | AM11: =AM10 -> 2246.2729 | AN11: =AL11/AM11 -> 77473822
C12: ='Cashflow Statement'!C20 -> Fleets Disposal | E12: =K12+N12+Q12+T12+W12+Z12+AC12+AF12+AI12+AL12 -> 100000000000 | F12: =F11 -> 952.639 | G12: =E12/F12 -> 1.0497156e+08 | I12: =I11 -> 952.639 | N12: ='Cashflow Statement'!Q20 -> 0 | Q12: ='Cashflow Statement'!T20 -> 0 | T12: ='Cashflow Statement'!W20 -> 0 | W12: ='Cashflow Statement'!Z20 -> 0 | Z12: ='Cashflow Statement'!AC20 -> 0 | AC12: ='Cashflow Statement'!AF20 -> 0 | AF12: ='Cashflow Statement'!AI20 -> 0 | AI12: ='Cashflow Statement'!AL20 -> 0 | AL12: ='Cashflow Statement'!AO20 -> 100000000000 | AM12: =AM11 -> 2246.2729 | AN12: =AL12/AM12 -> 44518188
C13: Bonds | E13: =K13+N13+Q13+T13+W13+Z13+AC13+AF13+AI13+AL13 -> 100000000000 | F13: =F12 -> 952.639 | G13: =E13/F13 -> 1.0497156e+08 | I13: =I12 -> 952.639 | N13: ='Cashflow Statement'!Q21 -> 0 | Q13: ='Cashflow Statement'!T21 -> 0 | T13: ='Cashflow Statement'!W21 -> 0 | W13: ='Cashflow Statement'!Z21 -> 0 | Z13: ='Cashflow Statement'!AC13 -> 100000000000 | AC13: ='Cashflow Statement'!AF21 -> 0 | AF13: ='Cashflow Statement'!AI21 -> 0 | AI13: ='Cashflow Statement'!AL21 -> 0 | AL13: ='Cashflow Statement'!AO21 -> 0 | AM13: =AM12 -> 2246.2729 | AN13: =AL13/AM13 -> 0
C14: TOTAL REVENUE | E14: =SUM(E10:E12) -> 2.0392755e+12 | G14: =SUM(G10:G12) -> 2.1406592e+09 | H14: =SUM(H10:H12) -> 0 | J14: =SUM(J10:J12) -> 0 | K14: =SUM(K10:K12) -> 30653209512 | M14: =SUM(M10:M12) -> 32177152 | N14: =SUM(N10:N12) -> 6.437174e+10 | P14: =SUM(P10:P12) -> 61429108 | Q14: =SUM(Q10:Q12) -> 1.2378754e+11 | S14: =SUM(S10:S12) -> 1.0738984e+08 | T14: =SUM(T10:T12) -> 1.7330256e+11 | V14: =SUM(V10:V12) -> 1.3667798e+08 | W14: =SUM(W10:W12) -> 2.2745961e+11 | Y14: =SUM(Y10:Y12) -> 1.6308168e+08 | Z14: =SUM(Z10:Z13) -> 3.3883259e+11 | AB14: =SUM(AB10:AB12) -> 1.5566888e+08 | AC14: =SUM(AC10:AC12) -> 2.5077422e+11 | AE14: =SUM(AE10:AE12) -> 1.4859302e+08 | AF14: =SUM(AF10:AF12) -> 2.6331293e+11 | AH14: =SUM(AH10:AH12) -> 1.4183879e+08 | AI14: =SUM(AI10:AI12) -> 2.7647857e+11 | AK14: =SUM(AK10:AK12) -> 1.3539158e+08 | AL14: =SUM(AL10:AL12) -> 3.903025e+11 | AN14: =SUM(AN10:AN12) -> 1.737556e+08
C17: Direct Cost
C19: Direct Labour/Wage Cost
C20: Drivers- Taxi | E20: =K20+N20+Q20+T20+W20+Z20+AC20+AF20+AI20+AL20 -> 5.3071624e+10 | F20: =F10 -> 952.639 | G20: =E20/F20 -> 55710110 | I20: =I10 -> 952.639 | J20: =H20/I20 -> 0 | K20: ='Cashflow Statement'!N38 -> 3330000000 | L20: =L10 -> 952.639 | M20: =K20/L20 -> 3495552.9 | N20: ='Cashflow Statement'!Q38 -> 3.663e+09 | O20: =O10 -> 1047.9029 | P20: =N20/O20 -> 3495552.9 | Q20: ='Cashflow Statement'!T38 -> 4.0293e+09 | R20: =R10 -> 1152.6932 | S20: =Q20/R20 -> 3495552.9 | T20: ='Cashflow Statement'!W38 -> 4.43223e+09 | U20: =U10 -> 1267.9625 | V20: =T20/U20 -> 3495552.9 | W20: ='Cashflow Statement'!Z38 -> 4.875453e+09 | X20: =X10 -> 1394.7588 | Y20: =W20/X20 -> 3495552.9 | Z20: ='Cashflow Statement'!AC38 -> 5.3629983e+09 | AA20: =AA10 -> 1534.2346 | AB20: =Z20/AA20 -> 3495552.9 | AC20: ='Cashflow Statement'!AF38 -> 5.8992981e+09 | AD20: =AD10 -> 1687.6581 | AE20: =AC20/AD20 -> 3495552.9 | AF20: ='Cashflow Statement'!AI38 -> 6.4892279e+09 | AG20: =AG10 -> 1856.4239 | AH20: =AF20/AG20 -> 3495552.9 | AI20: ='Cashflow Statement'!AL38 -> 7.1381507e+09 | AJ20: =AJ10 -> 2042.0663 | AK20: =AI20/AJ20 -> 3495552.9 | AL20: ='Cashflow Statement'!AO38 -> 7.8519658e+09 | AM20: =AM10 -> 2246.2729 | AN20: =AL20/AM20 -> 3495552.9
C21: Drivers- Bus | E21: =K21+N21+Q21+T21+W21+Z21+AC21+AF21+AI21+AL21 -> 1.0040577e+10 | F21: =F11 -> 952.639 | G21: =E21/F21 -> 10539751 | I21: =I11 -> 952.639 | J21: =H21/I21 -> 0 | K21: ='Cashflow Statement'!N39 -> 630000000 | L21: =L11 -> 952.639 | M21: =K21/L21 -> 661320.82 | N21: ='Cashflow Statement'!Q39 -> 693000000 | O21: =O11 -> 1047.9029 | P21: =N21/O21 -> 661320.82 | Q21: ='Cashflow Statement'!T39 -> 7.623e+08 | R21: =R11 -> 1152.6932 | S21: =Q21/R21 -> 661320.82 | T21: ='Cashflow Statement'!W39 -> 8.3853e+08 | U21: =U11 -> 1267.9625 | V21: =T21/U21 -> 661320.82 | W21: ='Cashflow Statement'!Z39 -> 9.22383e+08 | X21: =X11 -> 1394.7588 | Y21: =W21/X21 -> 661320.82 | Z21: ='Cashflow Statement'!AC39 -> 1.0146213e+09 | AA21: =AA11 -> 1534.2346 | AB21: =Z21/AA21 -> 661320.82 | AC21: ='Cashflow Statement'!AF39 -> 1.1160834e+09 | AD21: =AD11 -> 1687.6581 | AE21: =AC21/AD21 -> 661320.82 | AF21: ='Cashflow Statement'!AI39 -> 1.2276918e+09 | AG21: =AG11 -> 1856.4239 | AH21: =AF21/AG21 -> 661320.82 | AI21: ='Cashflow Statement'!AL39 -> 1.350461e+09 | AJ21: =AJ11 -> 2042.0663 | AK21: =AI21/AJ21 -> 661320.82 | AL21: ='Cashflow Statement'!AO39 -> 1.485507e+09 | AM21: =AM11 -> 2246.2729 | AN21: =AL21/AM21 -> 661320.82
C23: Repairs & Maintanance | E23: =K23+N23+Q23+T23+W23+Z23+AC23+AF23+AI23+AL23 -> 360000000 | F23: =F21 -> 952.639 | G23: =E23/F23 -> 377897.61 | I23: =I21 -> 952.639 | J23: =H23/I23 -> 0 | K23: ='Cashflow Statement'!N42 -> 360000000 | L23: =L21 -> 952.639 | M23: =K23/L23 -> 377897.61 | N23: ='Cashflow Statement'!Q42 -> 0 | O23: =O21 -> 1047.9029 | P23: =N23/O23 -> 0 | Q23: ='Cashflow Statement'!T42 -> 0 | R23: =R21 -> 1152.6932 | S23: =Q23/R23 -> 0 | T23: ='Cashflow Statement'!W42 -> 0 | U23: =U21 -> 1267.9625 | V23: =T23/U23 -> 0 | W23: ='Cashflow Statement'!Z42 -> 0 | X23: =X21 -> 1394.7588 | Y23: =W23/X23 -> 0 | Z23: ='Cashflow Statement'!AC42 -> 0 | AA23: =AA21 -> 1534.2346 | AB23: =Z23/AA23 -> 0 | AC23: ='Cashflow Statement'!AF42 -> 0 | AD23: =AD21 -> 1687.6581 | AE23: =AC23/AD23 -> 0 | AF23: ='Cashflow Statement'!AI42 -> 0 | AG23: =AG21 -> 1856.4239 | AH23: =AF23/AG23 -> 0 | AI23: ='Cashflow Statement'!AL42 -> 0 | AJ23: =AJ21 -> 2042.0663 | AK23: =AI23/AJ23 -> 0 | AL23: ='Cashflow Statement'!AO42 -> 0 | AM23: =AM21 -> 2246.2729 | AN23: =AL23/AM23 -> 0
C24: Energy and Power | E24: =K24+N24+Q24+T24+W24+Z24+AC24+AF24+AI24+AL24 -> 5299200000 | F24: =F23 -> 952.639 | G24: =E24/F24 -> 5562652.8 | I24: =I23 -> 952.639 | J24: =H24/I24 -> 0 | K24: ='Cashflow Statement'!N43 -> 5299200000 | L24: =L23 -> 952.639 | M24: =K24/L24 -> 5562652.8 | N24: ='Cashflow Statement'!Q43 -> 0 | O24: =O23 -> 1047.9029 | P24: =N24/O24 -> 0 | Q24: ='Cashflow Statement'!T43 -> 0 | R24: =R23 -> 1152.6932 | S24: =Q24/R24 -> 0 | T24: ='Cashflow Statement'!W43 -> 0 | U24: =U23 -> 1267.9625 | V24: =T24/U24 -> 0 | W24: ='Cashflow Statement'!Z43 -> 0 | X24: =X23 -> 1394.7588 | Y24: =W24/X24 -> 0 | Z24: ='Cashflow Statement'!AC43 -> 0 | AA24: =AA23 -> 1534.2346 | AB24: =Z24/AA24 -> 0 | AC24: ='Cashflow Statement'!AF43 -> 0 | AD24: =AD23 -> 1687.6581 | AE24: =AC24/AD24 -> 0 | AF24: ='Cashflow Statement'!AI43 -> 0 | AG24: =AG23 -> 1856.4239 | AH24: =AF24/AG24 -> 0 | AI24: ='Cashflow Statement'!AL43 -> 0 | AJ24: =AJ23 -> 2042.0663 | AK24: =AI24/AJ24 -> 0 | AL24: ='Cashflow Statement'!AO43 -> 0 | AM24: =AM23 -> 2246.2729 | AN24: =AL24/AM24 -> 0
C26: Depreciation & Amortisation- Fleets | E26: =K26+N26+Q26+T26+W26+Z26+AC26+AF26+AI26+AL26 -> 7.6985677e+11 | F26: =F24 -> 952.639 | G26: =E26/F26 -> 8.0813064e+08 | I26: =I24 -> 952.639 | J26: =H26/I26 -> 0 | K26: =CAPEX!C14 -> 1.6145783e+10 | L26: =L24 -> 952.639 | M26: =K26/L26 -> 16948480 | N26: =CAPEX!D14 -> 3.3906144e+10 | O26: =O24 -> 1047.9029 | P26: =N26/O26 -> 32356189 | Q26: =CAPEX!E14 -> 5.3442542e+10 | R26: =R24 -> 1152.6932 | S26: =Q26/R26 -> 46363197 | T26: =CAPEX!F14 -> 7.4932579e+10 | U26: =U24 -> 1267.9625 | V26: =T26/U26 -> 59096841 | W26: =CAPEX!G14 -> 9.857162e+10 | X26: =X24 -> 1394.7588 | Y26: =W26/X26 -> 70672881 | Z26: =CAPEX!H14 -> 9.857162e+10 | AA26: =AA24 -> 1534.2346 | AB26: =Z26/AA26 -> 64248074 | AC26: =CAPEX!I14 -> 9.857162e+10 | AD26: =AD24 -> 1687.6581 | AE26: =AC26/AD26 -> 58407340 | AF26: =CAPEX!J14 -> 9.857162e+10 | AG26: =AG24 -> 1856.4239 | AH26: =AF26/AG26 -> 53097582 | AI26: =CAPEX!K14 -> 9.857162e+10 | AJ26: =AJ24 -> 2042.0663 | AK26: =AI26/AJ26 -> 48270529 | AL26: =CAPEX!L14 -> 9.857162e+10 | AM26: =AM24 -> 2246.2729 | AN26: =AL26/AM26 -> 43882299
C27: Fleets Insurance | E27: =K27+N27+Q27+T27+W27+Z27+AC27+AF27+AI27+AL27 -> 7.6985677e+10 | F27: =F23 -> 952.639 | G27: =E27/F27 -> 80813064 | I27: =I23 -> 952.639 | J27: =H27/I27 -> 0 | K27: ='Cashflow Statement'!N46 -> 1.6145783e+09 | L27: =L23 -> 952.639 | M27: =K27/L27 -> 1694848 | N27: ='Cashflow Statement'!Q46 -> 3.3906144e+09 | O27: =O23 -> 1047.9029 | P27: =N27/O27 -> 3235618.9 | Q27: ='Cashflow Statement'!T46 -> 5.3442542e+09 | R27: =R23 -> 1152.6932 | S27: =Q27/R27 -> 4636319.7 | T27: ='Cashflow Statement'!W46 -> 7.4932579e+09 | U27: =U23 -> 1267.9625 | V27: =T27/U27 -> 5909684.1 | W27: ='Cashflow Statement'!Z46 -> 9.857162e+09 | X27: =X23 -> 1394.7588 | Y27: =W27/X27 -> 7067288.1 | Z27: ='Cashflow Statement'!AC46 -> 9.857162e+09 | AA27: =AA23 -> 1534.2346 | AB27: =Z27/AA27 -> 6424807.4 | AC27: ='Cashflow Statement'!AF46 -> 9.857162e+09 | AD27: =AD23 -> 1687.6581 | AE27: =AC27/AD27 -> 5840734 | AF27: ='Cashflow Statement'!AI46 -> 9.857162e+09 | AG27: =AG23 -> 1856.4239 | AH27: =AF27/AG27 -> 5309758.2 | AI27: ='Cashflow Statement'!AL46 -> 9.857162e+09 | AJ27: =AJ23 -> 2042.0663 | AK27: =AI27/AJ27 -> 4827052.9 | AL27: ='Cashflow Statement'!AO46 -> 9.857162e+09 | AM27: =AM23 -> 2246.2729 | AN27: =AL27/AM27 -> 4388229.9
C29: Total Direct Cost | E29: =SUM(E17:E28) -> 9.1561385e+11 | G29: =SUM(G17:G28) -> 9.6113412e+08 | H29: =SUM(H17:H28) -> 0 | J29: =SUM(J17:J28) -> 0 | K29: =SUM(K17:K28) -> 2.7379561e+10 | M29: =SUM(M17:M28) -> 28740752 | N29: =SUM(N17:N28) -> 4.1652759e+10 | P29: =SUM(P17:P28) -> 39748682 | Q29: =SUM(Q17:Q28) -> 6.3578396e+10 | S29: =SUM(S17:S28) -> 55156391 | T29: =SUM(T17:T28) -> 8.7696597e+10 | V29: =SUM(V17:V28) -> 69163399 | W29: =SUM(W17:W28) -> 1.1422662e+11 | Y29: =SUM(Y17:Y28) -> 81897043 | Z29: =SUM(Z17:Z28) -> 1.148064e+11 | AB29: =SUM(AB17:AB28) -> 74829755 | AC29: =SUM(AC17:AC28) -> 1.1544416e+11 | AE29: =SUM(AE17:AE28) -> 68404947 | AF29: =SUM(AF17:AF28) -> 1.161457e+11 | AH29: =SUM(AH17:AH28) -> 62564213 | AI29: =SUM(AI17:AI28) -> 1.1691739e+11 | AK29: =SUM(AK17:AK28) -> 57254455 | AL29: =SUM(AL17:AL28) -> 1.1776625e+11 | AN29: =SUM(AN17:AN28) -> 52427402
C31: Gross Profit | E31: =K31+N31+Q31+T31+W31+Z31+AC31+AF31+AI31+AL31 -> 1.2236616e+12 | G31: =G14-G29 -> 1.1795251e+09 | H31: =H14-H29 -> 0 | J31: =J14-J29 -> 0 | K31: =K14-K29 -> 3.2736482e+09 | M31: =M14-M29 -> 3436399.5 | N31: =N14-N29 -> 2.2718981e+10 | P31: =P14-P29 -> 21680426 | Q31: =Q14-Q29 -> 6.0209145e+10 | S31: =S14-S29 -> 52233453 | T31: =T14-T29 -> 8.5605961e+10 | V31: =V14-V29 -> 67514584 | W31: =W14-W29 -> 1.1323299e+11 | Y31: =Y14-Y29 -> 81184641 | Z31: =Z14-Z29 -> 2.2402619e+11 | AB31: =AB14-AB29 -> 80839125 | AC31: =AC14-AC29 -> 1.3533005e+11 | AE31: =AE14-AE29 -> 80188074 | AF31: =AF14-AF29 -> 1.4716723e+11 | AH31: =AH14-AH29 -> 79274580 | AI31: =AI14-AI29 -> 1.5956118e+11 | AK31: =AK14-AK29 -> 78137120 | AL31: =AL14-AL29 -> 2.7253625e+11 | AN31: =AN14-AN29 -> 1.213282e+08
C33: Operating & Maintenance Cost
C34: Personnel costs | E34: =K34+N34+Q34+T34+W34+Z34+AC34+AF34+AI34+AL34 -> 9.3712057e+09 | F34: =F10 -> 952.639 | G34: =E34/F34 -> 9837100.6 | I34: =I10 -> 952.639 | J34: =H34/I34 -> 0 | K34: ='Cashflow Statement'!N51 -> 588000000 | L34: =L10 -> 952.639 | M34: =K34/L34 -> 617232.76 | N34: ='Cashflow Statement'!Q51 -> 646800000 | O34: =O10 -> 1047.9029 | P34: =N34/O34 -> 617232.76 | Q34: ='Cashflow Statement'!T51 -> 711480000 | R34: =R10 -> 1152.6932 | S34: =Q34/R34 -> 617232.76 | T34: ='Cashflow Statement'!W51 -> 7.82628e+08 | U34: =U10 -> 1267.9625 | V34: =T34/U34 -> 617232.76 | W34: ='Cashflow Statement'!Z51 -> 8.608908e+08 | X34: =X10 -> 1394.7588 | Y34: =W34/X34 -> 617232.76 | Z34: ='Cashflow Statement'!AC51 -> 9.4697988e+08 | AA34: =AA10 -> 1534.2346 | AB34: =Z34/AA34 -> 617232.76 | AC34: ='Cashflow Statement'!AF51 -> 1.0416779e+09 | AD34: =AD10 -> 1687.6581 | AE34: =AC34/AD34 -> 617232.76 | AF34: ='Cashflow Statement'!AI51 -> 1.1458457e+09 | AG34: =AG10 -> 1856.4239 | AH34: =AF34/AG34 -> 617232.76 | AI34: ='Cashflow Statement'!AL51 -> 1.2604302e+09 | AJ34: =AJ10 -> 2042.0663 | AK34: =AI34/AJ34 -> 617232.76 | AL34: ='Cashflow Statement'!AO51 -> 1.3864732e+09 | AM34: =AM10 -> 2246.2729 | AN34: =AL34/AM34 -> 617232.76
N35: ='Cashflow Statement'!Q52 -> 0 | Q35: ='Cashflow Statement'!T52 -> 0 | T35: ='Cashflow Statement'!W52 -> 0 | W35: ='Cashflow Statement'!Z52 -> 0 | Z35: ='Cashflow Statement'!AC52 -> 0 | AC35: ='Cashflow Statement'!AF52 -> 0 | AF35: ='Cashflow Statement'!AI52 -> 0 | AI35: ='Cashflow Statement'!AL52 -> 0 | AL35: ='Cashflow Statement'!AO52 -> 0
C36: Other operating costs | N36: ='Cashflow Statement'!Q53 -> 0 | Q36: ='Cashflow Statement'!T53 -> 0 | T36: ='Cashflow Statement'!W53 -> 0 | W36: ='Cashflow Statement'!Z53 -> 0 | Z36: ='Cashflow Statement'!AC53 -> 0 | AC36: ='Cashflow Statement'!AF53 -> 0 | AF36: ='Cashflow Statement'!AI53 -> 0 | AI36: ='Cashflow Statement'!AL53 -> 0 | AL36: ='Cashflow Statement'!AO53 -> 0
C37: Admin Assets Insurance | D37: ='Cashflow Statement'!G54 -> 1.1 | E37: =K37+N37+Q37+T37+W37+Z37+AC37+AF37+AI37+AL37 -> 5500000 | F37: =F34 -> 952.639 | G37: =E37/F37 -> 5773.4357 | I37: =I34 -> 952.639 | J37: =H37/I37 -> 0 | K37: ='Cashflow Statement'!N54 -> 550000 | L37: =L34 -> 952.639 | M37: =K37/L37 -> 577.34357 | N37: ='Cashflow Statement'!Q54 -> 550000 | O37: =O34 -> 1047.9029 | P37: =N37/O37 -> 524.85779 | Q37: ='Cashflow Statement'!T54 -> 550000 | R37: =R34 -> 1152.6932 | S37: =Q37/R37 -> 477.14345 | T37: ='Cashflow Statement'!W54 -> 550000 | U37: =U34 -> 1267.9625 | V37: =T37/U37 -> 433.76677 | W37: ='Cashflow Statement'!Z54 -> 550000 | X37: =X34 -> 1394.7588 | Y37: =W37/X37 -> 394.33343 | Z37: ='Cashflow Statement'!AC54 -> 550000 | AA37: =AA34 -> 1534.2346 | AB37: =Z37/AA37 -> 358.48493 | AC37: ='Cashflow Statement'!AF54 -> 550000 | AD37: =AD34 -> 1687.6581 | AE37: =AC37/AD37 -> 325.89539 | AF37: ='Cashflow Statement'!AI54 -> 550000 | AG37: =AG34 -> 1856.4239 | AH37: =AF37/AG37 -> 296.26854 | AI37: ='Cashflow Statement'!AL54 -> 550000 | AJ37: =AJ34 -> 2042.0663 | AK37: =AI37/AJ37 -> 269.33504 | AL37: ='Cashflow Statement'!AO54 -> 550000 | AM37: =AM34 -> 2246.2729 | AN37: =AL37/AM37 -> 244.85003
C38: Marketing Expenses and Public Relation | D38: ='Cashflow Statement'!G55 -> 1.1 | E38: =K38+N38+Q38+T38+W38+Z38+AC38+AF38+AI38+AL38 -> 7.686641e+10 | F38: =F37 -> 952.639 | G38: =E38/F38 -> 80687869 | I38: =I37 -> 952.639 | J38: =H38/I38 -> 0 | K38: ='Cashflow Statement'!N55 -> 6.2196419e+08 | L38: =L37 -> 952.639 | M38: =K38/L38 -> 652885.5 | N38: ='Cashflow Statement'!Q55 -> 1.5792993e+09 | O38: =O37 -> 1047.9029 | P38: =N38/O38 -> 1507104.6 | Q38: ='Cashflow Statement'!T55 -> 3.7378076e+09 | R38: =R37 -> 1152.6932 | S38: =Q38/R38 -> 3242673.5 | T38: ='Cashflow Statement'!W55 -> 6.5985525e+09 | U38: =U37 -> 1267.9625 | V38: =T38/U38 -> 5204059.6 | W38: ='Cashflow Statement'!Z55 -> 1.0095914e+10 | X38: =X37 -> 1394.7588 | Y38: =W38/X38 -> 7238466.1 | Z38: ='Cashflow Statement'!AC55 -> 1.5428676e+10 | AA38: =AA37 -> 1534.2346 | AB38: =Z38/AA38 -> 10056269 | AC38: ='Cashflow Statement'!AF55 -> 1.3340302e+10 | AD38: =AD37 -> 1687.6581 | AE38: =AC38/AD38 -> 7904623.6 | AF38: ='Cashflow Statement'!AI55 -> 1.0432785e+10 | AG38: =AG37 -> 1856.4239 | AH38: =AF38/AG38 -> 5619828.9 | AI38: ='Cashflow Statement'!AL55 -> 7.944351e+09 | AJ38: =AJ37 -> 2042.0663 | AK38: =AI38/AJ38 -> 3890349.2 | AL38: ='Cashflow Statement'!AO55 -> 7.0867588e+09 | AM38: =AM37 -> 2246.2729 | AN38: =AL38/AM38 -> 3154896.6
C39: Pension Contribution | D39: ='Cashflow Statement'!G56 -> 1.1 | E39: =K39+N39+Q39+T39+W39+Z39+AC39+AF39+AI39+AL39 -> 5.7986726e+09 | F39: =F38 -> 952.639 | G39: =E39/F39 -> 6086956.9 | I39: =I38 -> 952.639 | J39: =H39/I39 -> 0 | K39: ='Cashflow Statement'!N56 -> 363840000 | L39: =L38 -> 952.639 | M39: =K39/L39 -> 381928.52 | N39: ='Cashflow Statement'!Q56 -> 400224000 | O39: =O38 -> 1047.9029 | P39: =N39/O39 -> 381928.52 | Q39: ='Cashflow Statement'!T56 -> 4.402464e+08 | R39: =R38 -> 1152.6932 | S39: =Q39/R39 -> 381928.52 | T39: ='Cashflow Statement'!W56 -> 4.8427104e+08 | U39: =U38 -> 1267.9625 | V39: =T39/U39 -> 381928.52 | W39: ='Cashflow Statement'!Z56 -> 5.3269814e+08 | X39: =X38 -> 1394.7588 | Y39: =W39/X39 -> 381928.52 | Z39: ='Cashflow Statement'!AC56 -> 5.8596796e+08 | AA39: =AA38 -> 1534.2346 | AB39: =Z39/AA39 -> 381928.52 | AC39: ='Cashflow Statement'!AF56 -> 6.4456475e+08 | AD39: =AD38 -> 1687.6581 | AE39: =AC39/AD39 -> 381928.52 | AF39: ='Cashflow Statement'!AI56 -> 7.0902123e+08 | AG39: =AG38 -> 1856.4239 | AH39: =AF39/AG39 -> 381928.52 | AI39: ='Cashflow Statement'!AL56 -> 7.7992335e+08 | AJ39: =AJ38 -> 2042.0663 | AK39: =AI39/AJ39 -> 381928.52 | AL39: ='Cashflow Statement'!AO56 -> 8.5791569e+08 | AM39: =AM38 -> 2246.2729 | AN39: =AL39/AM39 -> 381928.52
C40: Group Life | D40: ='Cashflow Statement'!G57 -> 1.1 | E40: =K40+N40+Q40+T40+W40+Z40+AC40+AF40+AI40+AL40 -> 7.2483407e+08 | F40: =F39 -> 952.639 | G40: =E40/F40 -> 760869.62 | I40: =I39 -> 952.639 | J40: =H40/I40 -> 0 | K40: ='Cashflow Statement'!N57 -> 45480000 | L40: =L39 -> 952.639 | M40: =K40/L40 -> 47741.065 | N40: ='Cashflow Statement'!Q57 -> 50028000 | O40: =O39 -> 1047.9029 | P40: =N40/O40 -> 47741.065 | Q40: ='Cashflow Statement'!T57 -> 55030800 | R40: =R39 -> 1152.6932 | S40: =Q40/R40 -> 47741.065 | T40: ='Cashflow Statement'!W57 -> 60533880 | U40: =U39 -> 1267.9625 | V40: =T40/U40 -> 47741.065 | W40: ='Cashflow Statement'!Z57 -> 66587268 | X40: =X39 -> 1394.7588 | Y40: =W40/X40 -> 47741.065 | Z40: ='Cashflow Statement'!AC57 -> 73245995 | AA40: =AA39 -> 1534.2346 | AB40: =Z40/AA40 -> 47741.065 | AC40: ='Cashflow Statement'!AF57 -> 80570594 | AD40: =AD39 -> 1687.6581 | AE40: =AC40/AD40 -> 47741.065 | AF40: ='Cashflow Statement'!AI57 -> 88627654 | AG40: =AG39 -> 1856.4239 | AH40: =AF40/AG40 -> 47741.065 | AI40: ='Cashflow Statement'!AL57 -> 97490419 | AJ40: =AJ39 -> 2042.0663 | AK40: =AI40/AJ40 -> 47741.065 | AL40: ='Cashflow Statement'!AO57 -> 1.0723946e+08 | AM40: =AM39 -> 2246.2729 | AN40: =AL40/AM40 -> 47741.065
C41: NSITF | D41: ='Cashflow Statement'!G58 -> 1.1 | E41: =K41+N41+Q41+T41+W41+Z41+AC41+AF41+AI41+AL41 -> 7.2483407e+08 | F41: =F39 -> 952.639 | G41: =E41/F41 -> 760869.62 | I41: =I39 -> 952.639 | J41: =H41/I41 -> 0 | K41: ='Cashflow Statement'!N58 -> 45480000 | L41: =L39 -> 952.639 | M41: =K41/L41 -> 47741.065 | N41: ='Cashflow Statement'!Q58 -> 50028000 | O41: =O39 -> 1047.9029 | P41: =N41/O41 -> 47741.065 | Q41: ='Cashflow Statement'!T58 -> 55030800 | R41: =R39 -> 1152.6932 | S41: =Q41/R41 -> 47741.065 | T41: ='Cashflow Statement'!W58 -> 60533880 | U41: =U39 -> 1267.9625 | V41: =T41/U41 -> 47741.065 | W41: ='Cashflow Statement'!Z58 -> 66587268 | X41: =X39 -> 1394.7588 | Y41: =W41/X41 -> 47741.065 | Z41: ='Cashflow Statement'!AC58 -> 73245995 | AA41: =AA39 -> 1534.2346 | AB41: =Z41/AA41 -> 47741.065 | AC41: ='Cashflow Statement'!AF58 -> 80570594 | AD41: =AD39 -> 1687.6581 | AE41: =AC41/AD41 -> 47741.065 | AF41: ='Cashflow Statement'!AI58 -> 88627654 | AG41: =AG39 -> 1856.4239 | AH41: =AF41/AG41 -> 47741.065 | AI41: ='Cashflow Statement'!AL58 -> 97490419 | AJ41: =AJ39 -> 2042.0663 | AK41: =AI41/AJ41 -> 47741.065 | AL41: ='Cashflow Statement'!AO58 -> 1.0723946e+08 | AM41: =AM39 -> 2246.2729 | AN41: =AL41/AM41 -> 47741.065
C42: NHIS | D42: ='Cashflow Statement'!G59 -> 1.1 | E42: =K42+N42+Q42+T42+W42+Z42+AC42+AF42+AI42+AL42 -> 1.8120852e+09 | F42: =F39 -> 952.639 | G42: =E42/F42 -> 1902174 | I42: =I39 -> 952.639 | J42: =H42/I42 -> 0 | K42: ='Cashflow Statement'!N59 -> 113700000 | L42: =L39 -> 952.639 | M42: =K42/L42 -> 119352.66 | N42: ='Cashflow Statement'!Q59 -> 125070000 | O42: =O39 -> 1047.9029 | P42: =N42/O42 -> 119352.66 | Q42: ='Cashflow Statement'!T59 -> 1.37577e+08 | R42: =R39 -> 1152.6932 | S42: =Q42/R42 -> 119352.66 | T42: ='Cashflow Statement'!W59 -> 1.513347e+08 | U42: =U39 -> 1267.9625 | V42: =T42/U42 -> 119352.66 | W42: ='Cashflow Statement'!Z59 -> 1.6646817e+08 | X42: =X39 -> 1394.7588 | Y42: =W42/X42 -> 119352.66 | Z42: ='Cashflow Statement'!AC59 -> 1.8311499e+08 | AA42: =AA39 -> 1534.2346 | AB42: =Z42/AA42 -> 119352.66 | AC42: ='Cashflow Statement'!AF59 -> 2.0142649e+08 | AD42: =AD39 -> 1687.6581 | AE42: =AC42/AD42 -> 119352.66 | AF42: ='Cashflow Statement'!AI59 -> 2.2156913e+08 | AG42: =AG39 -> 1856.4239 | AH42: =AF42/AG42 -> 119352.66 | AI42: ='Cashflow Statement'!AL59 -> 2.4372605e+08 | AJ42: =AJ39 -> 2042.0663 | AK42: =AI42/AJ42 -> 119352.66 | AL42: ='Cashflow Statement'!AO59 -> 2.6809865e+08 | AM42: =AM39 -> 2246.2729 | AN42: =AL42/AM42 -> 119352.66
C43: Board Expenses | D43: ='Cashflow Statement'!G60 -> 1.1 | E43: =K43+N43+Q43+T43+W43+Z43+AC43+AF43+AI43+AL43 -> 1.5937425e+10 | F43: =F39 -> 952.639 | G43: =E43/F43 -> 16729763 | I43: =I39 -> 952.639 | J43: =H43/I43 -> 0 | K43: ='Cashflow Statement'!N60 -> 1000000000 | L43: =L39 -> 952.639 | M43: =K43/L43 -> 1049715.6 | N43: ='Cashflow Statement'!Q60 -> 1100000000 | O43: =O39 -> 1047.9029 | P43: =N43/O43 -> 1049715.6 | Q43: ='Cashflow Statement'!T60 -> 1210000000 | R43: =R39 -> 1152.6932 | S43: =Q43/R43 -> 1049715.6 | T43: ='Cashflow Statement'!W60 -> 1331000000 | U43: =U39 -> 1267.9625 | V43: =T43/U43 -> 1049715.6 | W43: ='Cashflow Statement'!Z60 -> 1464100000 | X43: =X39 -> 1394.7588 | Y43: =W43/X43 -> 1049715.6 | Z43: ='Cashflow Statement'!AC60 -> 1.61051e+09 | AA43: =AA39 -> 1534.2346 | AB43: =Z43/AA43 -> 1049715.6 | AC43: ='Cashflow Statement'!AF60 -> 1.771561e+09 | AD43: =AD39 -> 1687.6581 | AE43: =AC43/AD43 -> 1049715.6 | AF43: ='Cashflow Statement'!AI60 -> 1.9487171e+09 | AG43: =AG39 -> 1856.4239 | AH43: =AF43/AG43 -> 1049715.6 | AI43: ='Cashflow Statement'!AL60 -> 2.1435888e+09 | AJ43: =AJ39 -> 2042.0663 | AK43: =AI43/AJ43 -> 1049715.6 | AL43: ='Cashflow Statement'!AO60 -> 2.3579477e+09 | AM43: =AM39 -> 2246.2729 | AN43: =AL43/AM43 -> 1049715.6
C44: Printing & Stationary | D44: ='Cashflow Statement'!G61 -> 1.1 | E44: =K44+N44+Q44+T44+W44+Z44+AC44+AF44+AI44+AL44 -> 1.5937425e+08 | F44: =F43 -> 952.639 | G44: =E44/F44 -> 167297.63 | I44: =I43 -> 952.639 | J44: =H44/I44 -> 0 | K44: ='Cashflow Statement'!N61 -> 10000000 | L44: =L43 -> 952.639 | M44: =K44/L44 -> 10497.156 | N44: ='Cashflow Statement'!Q61 -> 11000000 | O44: =O43 -> 1047.9029 | P44: =N44/O44 -> 10497.156 | Q44: ='Cashflow Statement'!T61 -> 12100000 | R44: =R43 -> 1152.6932 | S44: =Q44/R44 -> 10497.156 | T44: ='Cashflow Statement'!W61 -> 13310000 | U44: =U43 -> 1267.9625 | V44: =T44/U44 -> 10497.156 | W44: ='Cashflow Statement'!Z61 -> 14641000 | X44: =X43 -> 1394.7588 | Y44: =W44/X44 -> 10497.156 | Z44: ='Cashflow Statement'!AC61 -> 16105100 | AA44: =AA43 -> 1534.2346 | AB44: =Z44/AA44 -> 10497.156 | AC44: ='Cashflow Statement'!AF61 -> 17715610 | AD44: =AD43 -> 1687.6581 | AE44: =AC44/AD44 -> 10497.156 | AF44: ='Cashflow Statement'!AI61 -> 19487171 | AG44: =AG43 -> 1856.4239 | AH44: =AF44/AG44 -> 10497.156 | AI44: ='Cashflow Statement'!AL61 -> 21435888 | AJ44: =AJ43 -> 2042.0663 | AK44: =AI44/AJ44 -> 10497.156 | AL44: ='Cashflow Statement'!AO61 -> 23579477 | AM44: =AM43 -> 2246.2729 | AN44: =AL44/AM44 -> 10497.156
C45: Vehicle Maintenance | D45: ='Cashflow Statement'!G62 -> 1.1 | E45: =K45+N45+Q45+T45+W45+Z45+AC45+AF45+AI45+AL45 -> 264960000 | F45: =F44 -> 952.639 | G45: =E45/F45 -> 278132.64 | I45: =I44 -> 952.639 | J45: =H45/I45 -> 0 | K45: ='Cashflow Statement'!N62 -> 264960000 | L45: =L44 -> 952.639 | M45: =K45/L45 -> 278132.64 | N45: ='Cashflow Statement'!Q62 -> 0 | O45: =O44 -> 1047.9029 | P45: =N45/O45 -> 0 | Q45: ='Cashflow Statement'!T62 -> 0 | R45: =R44 -> 1152.6932 | S45: =Q45/R45 -> 0 | T45: ='Cashflow Statement'!W62 -> 0 | U45: =U44 -> 1267.9625 | V45: =T45/U45 -> 0 | W45: ='Cashflow Statement'!Z62 -> 0 | X45: =X44 -> 1394.7588 | Y45: =W45/X45 -> 0 | Z45: ='Cashflow Statement'!AC62 -> 0 | AA45: =AA44 -> 1534.2346 | AB45: =Z45/AA45 -> 0 | AC45: ='Cashflow Statement'!AF62 -> 0 | AD45: =AD44 -> 1687.6581 | AE45: =AC45/AD45 -> 0 | AF45: ='Cashflow Statement'!AI62 -> 0 | AG45: =AG44 -> 1856.4239 | AH45: =AF45/AG45 -> 0 | AI45: ='Cashflow Statement'!AL62 -> 0 | AJ45: =AJ44 -> 2042.0663 | AK45: =AI45/AJ45 -> 0 | AL45: ='Cashflow Statement'!AO62 -> 0 | AM45: =AM44 -> 2246.2729 | AN45: =AL45/AM45 -> 0
C46: Rent | D46: ='Cashflow Statement'!G63 -> 1.1 | E46: =K46+N46+Q46+T46+W46+Z46+AC46+AF46+AI46+AL46 -> 7.9687123e+08 | F46: =F45 -> 952.639 | G46: =E46/F46 -> 836488.15 | I46: =I45 -> 952.639 | J46: =H46/I46 -> 0 | K46: ='Cashflow Statement'!N63 -> 50000000 | L46: =L45 -> 952.639 | M46: =K46/L46 -> 52485.779 | N46: ='Cashflow Statement'!Q63 -> 55000000 | O46: =O45 -> 1047.9029 | P46: =N46/O46 -> 52485.779 | Q46: ='Cashflow Statement'!T63 -> 60500000 | R46: =R45 -> 1152.6932 | S46: =Q46/R46 -> 52485.779 | T46: ='Cashflow Statement'!W63 -> 66550000 | U46: =U45 -> 1267.9625 | V46: =T46/U46 -> 52485.779 | W46: ='Cashflow Statement'!Z63 -> 73205000 | X46: =X45 -> 1394.7588 | Y46: =W46/X46 -> 52485.779 | Z46: ='Cashflow Statement'!AC63 -> 80525500 | AA46: =AA45 -> 1534.2346 | AB46: =Z46/AA46 -> 52485.779 | AC46: ='Cashflow Statement'!AF63 -> 88578050 | AD46: =AD45 -> 1687.6581 | AE46: =AC46/AD46 -> 52485.779 | AF46: ='Cashflow Statement'!AI63 -> 97435855 | AG46: =AG45 -> 1856.4239 | AH46: =AF46/AG46 -> 52485.779 | AI46: ='Cashflow Statement'!AL63 -> 1.0717944e+08 | AJ46: =AJ45 -> 2042.0663 | AK46: =AI46/AJ46 -> 52485.779 | AL46: ='Cashflow Statement'!AO63 -> 1.1789738e+08 | AM46: =AM45 -> 2246.2729 | AN46: =AL46/AM46 -> 52485.779
C47: Maintenance - Buildings | D47: ='Cashflow Statement'!G64 -> 1.1 | E47: =K47+N47+Q47+T47+W47+Z47+AC47+AF47+AI47+AL47 -> 1.5937425e+08 | F47: =F45 -> 952.639 | G47: =E47/F47 -> 167297.63 | I47: =I45 -> 952.639 | J47: =H47/I47 -> 0 | K47: ='Cashflow Statement'!N64 -> 10000000 | L47: =L45 -> 952.639 | M47: =K47/L47 -> 10497.156 | N47: ='Cashflow Statement'!Q64 -> 11000000 | O47: =O45 -> 1047.9029 | P47: =N47/O47 -> 10497.156 | Q47: ='Cashflow Statement'!T64 -> 12100000 | R47: =R45 -> 1152.6932 | S47: =Q47/R47 -> 10497.156 | T47: ='Cashflow Statement'!W64 -> 13310000 | U47: =U45 -> 1267.9625 | V47: =T47/U47 -> 10497.156 | W47: ='Cashflow Statement'!Z64 -> 14641000 | X47: =X45 -> 1394.7588 | Y47: =W47/X47 -> 10497.156 | Z47: ='Cashflow Statement'!AC64 -> 16105100 | AA47: =AA45 -> 1534.2346 | AB47: =Z47/AA47 -> 10497.156 | AC47: ='Cashflow Statement'!AF64 -> 17715610 | AD47: =AD45 -> 1687.6581 | AE47: =AC47/AD47 -> 10497.156 | AF47: ='Cashflow Statement'!AI64 -> 19487171 | AG47: =AG45 -> 1856.4239 | AH47: =AF47/AG47 -> 10497.156 | AI47: ='Cashflow Statement'!AL64 -> 21435888 | AJ47: =AJ45 -> 2042.0663 | AK47: =AI47/AJ47 -> 10497.156 | AL47: ='Cashflow Statement'!AO64 -> 23579477 | AM47: =AM45 -> 2246.2729 | AN47: =AL47/AM47 -> 10497.156
C48: Maintenance - Equipment | D48: ='Cashflow Statement'!G65 -> 1.1 | E48: =K48+N48+Q48+T48+W48+Z48+AC48+AF48+AI48+AL48 -> 8765583.5 | F48: =F47 -> 952.639 | G48: =E48/F48 -> 9201.3696 | I48: =I47 -> 952.639 | J48: =H48/I48 -> 0 | K48: ='Cashflow Statement'!N65 -> 550000 | L48: =L47 -> 952.639 | M48: =K48/L48 -> 577.34357 | N48: ='Cashflow Statement'!Q65 -> 605000 | O48: =O47 -> 1047.9029 | P48: =N48/O48 -> 577.34357 | Q48: ='Cashflow Statement'!T65 -> 665500 | R48: =R47 -> 1152.6932 | S48: =Q48/R48 -> 577.34357 | T48: ='Cashflow Statement'!W65 -> 732050 | U48: =U47 -> 1267.9625 | V48: =T48/U48 -> 577.34357 | W48: ='Cashflow Statement'!Z65 -> 805255 | X48: =X47 -> 1394.7588 | Y48: =W48/X48 -> 577.34357 | Z48: ='Cashflow Statement'!AC65 -> 885780.5 | AA48: =AA47 -> 1534.2346 | AB48: =Z48/AA48 -> 577.34357 | AC48: ='Cashflow Statement'!AF65 -> 974358.55 | AD48: =AD47 -> 1687.6581 | AE48: =AC48/AD48 -> 577.34357 | AF48: ='Cashflow Statement'!AI65 -> 1071794.4 | AG48: =AG47 -> 1856.4239 | AH48: =AF48/AG48 -> 577.34357 | AI48: ='Cashflow Statement'!AL65 -> 1178973.8 | AJ48: =AJ47 -> 2042.0663 | AK48: =AI48/AJ48 -> 577.34357 | AL48: ='Cashflow Statement'!AO65 -> 1296871.2 | AM48: =AM47 -> 2246.2729 | AN48: =AL48/AM48 -> 577.34357
C49: Postage & Communication | D49: ='Cashflow Statement'!G66 -> 1.1 | E49: =K49+N49+Q49+T49+W49+Z49+AC49+AF49+AI49+AL49 -> 1.4496681e+09 | F49: =F48 -> 952.639 | G49: =E49/F49 -> 1521739.2 | I49: =I48 -> 952.639 | J49: =H49/I49 -> 0 | K49: ='Cashflow Statement'!N66 -> 90960000 | L49: =L48 -> 952.639 | M49: =K49/L49 -> 95482.129 | N49: ='Cashflow Statement'!Q66 -> 1.00056e+08 | O49: =O48 -> 1047.9029 | P49: =N49/O49 -> 95482.129 | Q49: ='Cashflow Statement'!T66 -> 1.100616e+08 | R49: =R48 -> 1152.6932 | S49: =Q49/R49 -> 95482.129 | T49: ='Cashflow Statement'!W66 -> 1.2106776e+08 | U49: =U48 -> 1267.9625 | V49: =T49/U49 -> 95482.129 | W49: ='Cashflow Statement'!Z66 -> 1.3317454e+08 | X49: =X48 -> 1394.7588 | Y49: =W49/X49 -> 95482.129 | Z49: ='Cashflow Statement'!AC66 -> 1.4649199e+08 | AA49: =AA48 -> 1534.2346 | AB49: =Z49/AA49 -> 95482.129 | AC49: ='Cashflow Statement'!AF66 -> 1.6114119e+08 | AD49: =AD48 -> 1687.6581 | AE49: =AC49/AD49 -> 95482.129 | AF49: ='Cashflow Statement'!AI66 -> 1.7725531e+08 | AG49: =AG48 -> 1856.4239 | AH49: =AF49/AG49 -> 95482.129 | AI49: ='Cashflow Statement'!AL66 -> 1.9498084e+08 | AJ49: =AJ48 -> 2042.0663 | AK49: =AI49/AJ49 -> 95482.129 | AL49: ='Cashflow Statement'!AO66 -> 2.1447892e+08 | AM49: =AM48 -> 2246.2729 | AN49: =AL49/AM49 -> 95482.129
C50: Human Capital Development (ITF Inclusive) | D50: ='Cashflow Statement'!G67 -> 1.1 | E50: =K50+N50+Q50+T50+W50+Z50+AC50+AF50+AI50+AL50 -> 1.4496681e+09 | F50: =F49 -> 952.639 | G50: =E50/F50 -> 1521739.2 | I50: =I49 -> 952.639 | J50: =H50/I50 -> 0 | K50: ='Cashflow Statement'!N67 -> 90960000 | L50: =L49 -> 952.639 | M50: =K50/L50 -> 95482.129 | N50: ='Cashflow Statement'!Q67 -> 1.00056e+08 | O50: =O49 -> 1047.9029 | P50: =N50/O50 -> 95482.129 | Q50: ='Cashflow Statement'!T67 -> 1.100616e+08 | R50: =R49 -> 1152.6932 | S50: =Q50/R50 -> 95482.129 | T50: ='Cashflow Statement'!W67 -> 1.2106776e+08 | U50: =U49 -> 1267.9625 | V50: =T50/U50 -> 95482.129 | W50: ='Cashflow Statement'!Z67 -> 1.3317454e+08 | X50: =X49 -> 1394.7588 | Y50: =W50/X50 -> 95482.129 | Z50: ='Cashflow Statement'!AC67 -> 1.4649199e+08 | AA50: =AA49 -> 1534.2346 | AB50: =Z50/AA50 -> 95482.129 | AC50: ='Cashflow Statement'!AF67 -> 1.6114119e+08 | AD50: =AD49 -> 1687.6581 | AE50: =AC50/AD50 -> 95482.129 | AF50: ='Cashflow Statement'!AI67 -> 1.7725531e+08 | AG50: =AG49 -> 1856.4239 | AH50: =AF50/AG50 -> 95482.129 | AI50: ='Cashflow Statement'!AL67 -> 1.9498084e+08 | AJ50: =AJ49 -> 2042.0663 | AK50: =AI50/AJ50 -> 95482.129 | AL50: ='Cashflow Statement'!AO67 -> 2.1447892e+08 | AM50: =AM49 -> 2246.2729 | AN50: =AL50/AM50 -> 95482.129
C51: Government Rates | D51: ='Cashflow Statement'!G68 -> 1.1 | E51: =K51+N51+Q51+T51+W51+Z51+AC51+AF51+AI51+AL51 -> 7.686641e+10 | F51: =F50 -> 952.639 | G51: =E51/F51 -> 80687869 | I51: =I50 -> 952.639 | J51: =H51/I51 -> 0 | K51: ='Cashflow Statement'!N68 -> 6.2196419e+08 | L51: =L50 -> 952.639 | M51: =K51/L51 -> 652885.5 | N51: ='Cashflow Statement'!Q68 -> 1.5792993e+09 | O51: =O50 -> 1047.9029 | P51: =N51/O51 -> 1507104.6 | Q51: ='Cashflow Statement'!T68 -> 3.7378076e+09 | R51: =R50 -> 1152.6932 | S51: =Q51/R51 -> 3242673.5 | T51: ='Cashflow Statement'!W68 -> 6.5985525e+09 | U51: =U50 -> 1267.9625 | V51: =T51/U51 -> 5204059.6 | W51: ='Cashflow Statement'!Z68 -> 1.0095914e+10 | X51: =X50 -> 1394.7588 | Y51: =W51/X51 -> 7238466.1 | Z51: ='Cashflow Statement'!AC68 -> 1.5428676e+10 | AA51: =AA50 -> 1534.2346 | AB51: =Z51/AA51 -> 10056269 | AC51: ='Cashflow Statement'!AF68 -> 1.3340302e+10 | AD51: =AD50 -> 1687.6581 | AE51: =AC51/AD51 -> 7904623.6 | AF51: ='Cashflow Statement'!AI68 -> 1.0432785e+10 | AG51: =AG50 -> 1856.4239 | AH51: =AF51/AG51 -> 5619828.9 | AI51: ='Cashflow Statement'!AL68 -> 7.944351e+09 | AJ51: =AJ50 -> 2042.0663 | AK51: =AI51/AJ51 -> 3890349.2 | AL51: ='Cashflow Statement'!AO68 -> 7.0867588e+09 | AM51: =AM50 -> 2246.2729 | AN51: =AL51/AM51 -> 3154896.6
C52: Travelling Expenses | D52: ='Cashflow Statement'!G69 -> 1.1 | E52: =K52+N52+Q52+T52+W52+Z52+AC52+AF52+AI52+AL52 -> 1.9216603e+10 | F52: =F51 -> 952.639 | G52: =E52/F52 -> 20171967 | I52: =I51 -> 952.639 | J52: =H52/I52 -> 0 | K52: ='Cashflow Statement'!N69 -> 1.5549105e+08 | L52: =L51 -> 952.639 | M52: =K52/L52 -> 163221.38 | N52: ='Cashflow Statement'!Q69 -> 3.9482483e+08 | O52: =O51 -> 1047.9029 | P52: =N52/O52 -> 376776.15 | Q52: ='Cashflow Statement'!T69 -> 9.344519e+08 | R52: =R51 -> 1152.6932 | S52: =Q52/R52 -> 810668.36 | T52: ='Cashflow Statement'!W69 -> 1.6496381e+09 | U52: =U51 -> 1267.9625 | V52: =T52/U52 -> 1301014.9 | W52: ='Cashflow Statement'!Z69 -> 2.5239785e+09 | X52: =X51 -> 1394.7588 | Y52: =W52/X52 -> 1809616.5 | Z52: ='Cashflow Statement'!AC69 -> 3.857169e+09 | AA52: =AA51 -> 1534.2346 | AB52: =Z52/AA52 -> 2514067.2 | AC52: ='Cashflow Statement'!AF69 -> 3.3350755e+09 | AD52: =AD51 -> 1687.6581 | AE52: =AC52/AD52 -> 1976155.9 | AF52: ='Cashflow Statement'!AI69 -> 2.6081962e+09 | AG52: =AG51 -> 1856.4239 | AH52: =AF52/AG52 -> 1404957.2 | AI52: ='Cashflow Statement'!AL69 -> 1.9860877e+09 | AJ52: =AJ51 -> 2042.0663 | AK52: =AI52/AJ52 -> 972587.3 | AL52: ='Cashflow Statement'!AO69 -> 1.7716897e+09 | AM52: =AM51 -> 2246.2729 | AN52: =AL52/AM52 -> 788724.15
C53: Audit Fees | D53: ='Cashflow Statement'!G70 -> 1.1 | E53: =K53+N53+Q53+T53+W53+Z53+AC53+AF53+AI53+AL53 -> 8.7655835e+08 | F53: =F52 -> 952.639 | G53: =E53/F53 -> 920136.96 | I53: =I52 -> 952.639 | J53: =H53/I53 -> 0 | K53: ='Cashflow Statement'!N70 -> 55000000 | L53: =L52 -> 952.639 | M53: =K53/L53 -> 57734.357 | N53: ='Cashflow Statement'!Q70 -> 60500000 | O53: =O52 -> 1047.9029 | P53: =N53/O53 -> 57734.357 | Q53: ='Cashflow Statement'!T70 -> 66550000 | R53: =R52 -> 1152.6932 | S53: =Q53/R53 -> 57734.357 | T53: ='Cashflow Statement'!W70 -> 73205000 | U53: =U52 -> 1267.9625 | V53: =T53/U53 -> 57734.357 | W53: ='Cashflow Statement'!Z70 -> 80525500 | X53: =X52 -> 1394.7588 | Y53: =W53/X53 -> 57734.357 | Z53: ='Cashflow Statement'!AC70 -> 88578050 | AA53: =AA52 -> 1534.2346 | AB53: =Z53/AA53 -> 57734.357 | AC53: ='Cashflow Statement'!AF70 -> 97435855 | AD53: =AD52 -> 1687.6581 | AE53: =AC53/AD53 -> 57734.357 | AF53: ='Cashflow Statement'!AI70 -> 1.0717944e+08 | AG53: =AG52 -> 1856.4239 | AH53: =AF53/AG53 -> 57734.357 | AI53: ='Cashflow Statement'!AL70 -> 1.1789738e+08 | AJ53: =AJ52 -> 2042.0663 | AK53: =AI53/AJ53 -> 57734.357 | AL53: ='Cashflow Statement'!AO70 -> 1.2968712e+08 | AM53: =AM52 -> 2246.2729 | AN53: =AL53/AM53 -> 57734.357
C54: Legal & Secretarial Expenses | D54: ='Cashflow Statement'!G71 -> 1.1 | E54: =K54+N54+Q54+T54+W54+Z54+AC54+AF54+AI54+AL54 -> 3.9843562e+08 | F54: =F53 -> 952.639 | G54: =E54/F54 -> 418244.07 | I54: =I53 -> 952.639 | J54: =H54/I54 -> 0 | K54: ='Cashflow Statement'!N71 -> 25000000 | L54: =L53 -> 952.639 | M54: =K54/L54 -> 26242.889 | N54: ='Cashflow Statement'!Q71 -> 27500000 | O54: =O53 -> 1047.9029 | P54: =N54/O54 -> 26242.889 | Q54: ='Cashflow Statement'!T71 -> 30250000 | R54: =R53 -> 1152.6932 | S54: =Q54/R54 -> 26242.889 | T54: ='Cashflow Statement'!W71 -> 33275000 | U54: =U53 -> 1267.9625 | V54: =T54/U54 -> 26242.889 | W54: ='Cashflow Statement'!Z71 -> 36602500 | X54: =X53 -> 1394.7588 | Y54: =W54/X54 -> 26242.889 | Z54: ='Cashflow Statement'!AC71 -> 40262750 | AA54: =AA53 -> 1534.2346 | AB54: =Z54/AA54 -> 26242.889 | AC54: ='Cashflow Statement'!AF71 -> 44289025 | AD54: =AD53 -> 1687.6581 | AE54: =AC54/AD54 -> 26242.889 | AF54: ='Cashflow Statement'!AI71 -> 48717928 | AG54: =AG53 -> 1856.4239 | AH54: =AF54/AG54 -> 26242.889 | AI54: ='Cashflow Statement'!AL71 -> 53589720 | AJ54: =AJ53 -> 2042.0663 | AK54: =AI54/AJ54 -> 26242.889 | AL54: ='Cashflow Statement'!AO71 -> 58948692 | AM54: =AM53 -> 2246.2729 | AN54: =AL54/AM54 -> 26242.889
C55: Consultancies & Other Professional Fees | D55: ='Cashflow Statement'!G72 -> 1.1 | E55: =K55+N55+Q55+T55+W55+Z55+AC55+AF55+AI55+AL55 -> 5.7649808e+10 | F55: =F54 -> 952.639 | G55: =E55/F55 -> 60515901 | I55: =I54 -> 952.639 | J55: =H55/I55 -> 0 | K55: ='Cashflow Statement'!N72 -> 4.6647314e+08 | L55: =L54 -> 952.639 | M55: =K55/L55 -> 489664.13 | N55: ='Cashflow Statement'!Q72 -> 1.1844745e+09 | O55: =O54 -> 1047.9029 | P55: =N55/O55 -> 1130328.5 | Q55: ='Cashflow Statement'!T72 -> 2.8033557e+09 | R55: =R54 -> 1152.6932 | S55: =Q55/R55 -> 2432005.1 | T55: ='Cashflow Statement'!W72 -> 4.9489144e+09 | U55: =U54 -> 1267.9625 | V55: =T55/U55 -> 3903044.7 | W55: ='Cashflow Statement'!Z72 -> 7.5719355e+09 | X55: =X54 -> 1394.7588 | Y55: =W55/X55 -> 5428849.6 | Z55: ='Cashflow Statement'!AC72 -> 1.1571507e+10 | AA55: =AA54 -> 1534.2346 | AB55: =Z55/AA55 -> 7542201.7 | AC55: ='Cashflow Statement'!AF72 -> 1.0005227e+10 | AD55: =AD54 -> 1687.6581 | AE55: =AC55/AD55 -> 5928467.7 | AF55: ='Cashflow Statement'!AI72 -> 7.8245885e+09 | AG55: =AG54 -> 1856.4239 | AH55: =AF55/AG55 -> 4214871.6 | AI55: ='Cashflow Statement'!AL72 -> 5.9582632e+09 | AJ55: =AJ54 -> 2042.0663 | AK55: =AI55/AJ55 -> 2917761.9 | AL55: ='Cashflow Statement'!AO72 -> 5.3150691e+09 | AM55: =AM54 -> 2246.2729 | AN55: =AL55/AM55 -> 2366172.5
C56: Staff Medical Expenses | D56: ='Cashflow Statement'!G73 -> 1.1 | E56: =K56+N56+Q56+T56+W56+Z56+AC56+AF56+AI56+AL56 -> 7.2483407e+09 | F56: =F55 -> 952.639 | G56: =E56/F56 -> 7608696.2 | I56: =I55 -> 952.639 | J56: =H56/I56 -> 0 | K56: ='Cashflow Statement'!N73 -> 454800000 | L56: =L55 -> 952.639 | M56: =K56/L56 -> 477410.65 | N56: ='Cashflow Statement'!Q73 -> 500280000 | O56: =O55 -> 1047.9029 | P56: =N56/O56 -> 477410.65 | Q56: ='Cashflow Statement'!T73 -> 5.50308e+08 | R56: =R55 -> 1152.6932 | S56: =Q56/R56 -> 477410.65 | T56: ='Cashflow Statement'!W73 -> 6.053388e+08 | U56: =U55 -> 1267.9625 | V56: =T56/U56 -> 477410.65 | W56: ='Cashflow Statement'!Z73 -> 6.6587268e+08 | X56: =X55 -> 1394.7588 | Y56: =W56/X56 -> 477410.65 | Z56: ='Cashflow Statement'!AC73 -> 7.3245995e+08 | AA56: =AA55 -> 1534.2346 | AB56: =Z56/AA56 -> 477410.65 | AC56: ='Cashflow Statement'!AF73 -> 8.0570594e+08 | AD56: =AD55 -> 1687.6581 | AE56: =AC56/AD56 -> 477410.65 | AF56: ='Cashflow Statement'!AI73 -> 8.8627654e+08 | AG56: =AG55 -> 1856.4239 | AH56: =AF56/AG56 -> 477410.65 | AI56: ='Cashflow Statement'!AL73 -> 9.7490419e+08 | AJ56: =AJ55 -> 2042.0663 | AK56: =AI56/AJ56 -> 477410.65 | AL56: ='Cashflow Statement'!AO73 -> 1.0723946e+09 | AM56: =AM55 -> 2246.2729 | AN56: =AL56/AM56 -> 477410.65
C58: Depreciation & Amortisation- Admin Assets | E58: =K58+N58+Q58+T58+W58+Z58+AC58+AF58+AI58+AL58 -> 55000000 | F58: =F54 -> 952.639 | G58: =E58/F58 -> 57734.357 | I58: =I54 -> 952.639 | J58: =H58/I58 -> 0 | K58: =CAPEX!C36 -> 5500000 | L58: =L54 -> 952.639 | M58: =K58/L58 -> 5773.4357 | N58: =CAPEX!D36 -> 5500000 | O58: =O54 -> 1047.9029 | P58: =N58/O58 -> 5248.5779 | Q58: =CAPEX!E36 -> 5500000 | R58: =R54 -> 1152.6932 | S58: =Q58/R58 -> 4771.4345 | T58: =CAPEX!F36 -> 5500000 | U58: =U54 -> 1267.9625 | V58: =T58/U58 -> 4337.6677 | W58: =CAPEX!G36 -> 5500000 | X58: =X54 -> 1394.7588 | Y58: =W58/X58 -> 3943.3343 | Z58: =CAPEX!H36 -> 5500000 | AA58: =AA54 -> 1534.2346 | AB58: =Z58/AA58 -> 3584.8493 | AC58: =CAPEX!I36 -> 5500000 | AD58: =AD54 -> 1687.6581 | AE58: =AC58/AD58 -> 3258.9539 | AF58: =CAPEX!J36 -> 5500000 | AG58: =AG54 -> 1856.4239 | AH58: =AF58/AG58 -> 2962.6854 | AI58: =CAPEX!K36 -> 5500000 | AJ58: =AJ54 -> 2042.0663 | AK58: =AI58/AJ58 -> 2693.3504 | AL58: =CAPEX!L36 -> 5500000 | AM58: =AM54 -> 2246.2729 | AN58: =AL58/AM58 -> 2448.5003
C60: Stamp Duties etc | E60: =K60+N60+Q60+T60+W60+Z60+AC60+AF60+AI60+AL60 -> 4.2354288e+09 | F60: =F51 -> 952.639 | G60: =E60/F60 -> 4445995.6 | I60: =I51 -> 952.639 | J60: =H60/I60 -> 0 | K60: ='Cashflow Statement'!N77 -> 1.6308951e+08 | L60: =L51 -> 952.639 | M60: =K60/L60 -> 171197.6 | N60: ='Cashflow Statement'!Q77 -> 1.5723209e+08 | O60: =O51 -> 1047.9029 | P60: =N60/O60 -> 150044.53 | Q60: ='Cashflow Statement'!T77 -> 2.4911789e+08 | R60: =R51 -> 1152.6932 | S60: =Q60/R60 -> 216118.12 | T60: ='Cashflow Statement'!W77 -> 3.6478383e+08 | U60: =U51 -> 1267.9625 | V60: =T60/U60 -> 287692.92 | W60: ='Cashflow Statement'!Z77 -> 5.0253264e+08 | X60: =X51 -> 1394.7588 | Y60: =W60/X60 -> 360300.76 | Z60: ='Cashflow Statement'!AC77 -> 6.7262331e+08 | AA60: =AA51 -> 1534.2346 | AB60: =Z60/AA60 -> 438409.68 | AC60: ='Cashflow Statement'!AF77 -> 6.2109068e+08 | AD60: =AD51 -> 1687.6581 | AE60: =AC60/AD60 -> 368019.26 | AF60: ='Cashflow Statement'!AI77 -> 5.4609561e+08 | AG60: =AG51 -> 1856.4239 | AH60: =AF60/AG60 -> 294165.36 | AI60: ='Cashflow Statement'!AL77 -> 4.8489609e+08 | AJ60: =AJ51 -> 2042.0663 | AK60: =AI60/AJ60 -> 237453.65 | AL60: ='Cashflow Statement'!AO77 -> 4.7396717e+08 | AM60: =AM51 -> 2246.2729 | AN60: =AL60/AM60 -> 211001.59
C62: Bank Charges | E62: =K62+N62+Q62+T62+W62+Z62+AC62+AF62+AI62+AL62 -> 1.3166312e+09 | F62: =F53 -> 952.639 | G62: =E62/F62 -> 1382088.3 | I62: =I53 -> 952.639 | J62: =H62/I62 -> 0 | K62: ='Cashflow Statement'!N87 -> 32944081 | L62: =L53 -> 952.639 | M62: =K62/L62 -> 34581.915 | N62: ='Cashflow Statement'!Q87 -> 31760883 | O62: =O53 -> 1047.9029 | P62: =N62/O62 -> 30308.994 | Q62: ='Cashflow Statement'!T87 -> 59923423 | R62: =R53 -> 1152.6932 | S62: =Q62/R62 -> 51985.579 | T62: ='Cashflow Statement'!W87 -> 1.0346466e+08 | U62: =U53 -> 1267.9625 | V62: =T62/U62 -> 81599.145 | W62: ='Cashflow Statement'!Z87 -> 1.4204737e+08 | X62: =X53 -> 1394.7588 | Y62: =W62/X62 -> 101843.69 | Z62: ='Cashflow Statement'!AC87 -> 1.8733977e+08 | AA62: =AA53 -> 1534.2346 | AB62: =Z62/AA62 -> 122106.34 | AC62: ='Cashflow Statement'!AF87 -> 2.3906821e+08 | AD62: =AD53 -> 1687.6581 | AE62: =AC62/AD62 -> 141656.78 | AF62: ='Cashflow Statement'!AI87 -> 1.6920171e+08 | AG62: =AG53 -> 1856.4239 | AH62: =AF62/AG62 -> 91143.895 | AI62: ='Cashflow Statement'!AL87 -> 1.7016024e+08 | AJ62: =AJ53 -> 2042.0663 | AK62: =AI62/AJ62 -> 83327.479 | AL62: ='Cashflow Statement'!AO87 -> 1.8072085e+08 | AM62: =AM53 -> 2246.2729 | AN62: =AL62/AM62 -> 80453.647
C63: TOTAL OPERATION AND MAINTENANCE COST | E63: =SUM(E34:E62) -> 2.8339286e+11 | G63: =SUM(G34:G62) -> 2.974819e+08 | H63: =SUM(H34:H62) -> 0 | J63: =SUM(J34:J62) -> 0 | K63: =SUM(K34:K62) -> 5.2767062e+09 | M63: =SUM(M34:M62) -> 5539040.7 | N63: =SUM(N34:N62) -> 8.1710879e+09 | P63: =SUM(P34:P62) -> 7797562 | Q63: =SUM(Q34:Q62) -> 1.5090476e+10 | S63: =SUM(S34:S62) -> 13091494 | T63: =SUM(T34:T62) -> 2.4188114e+10 | V63: =SUM(V34:V62) -> 19076364 | W63: =SUM(W34:W62) -> 3.5248346e+10 | Y63: =SUM(Y34:Y62) -> 25272002 | Z63: =SUM(Z34:Z62) -> 5.1893013e+10 | AB63: =SUM(AB34:AB62) -> 33823387 | AC63: =SUM(AC34:AC62) -> 4.6102183e+10 | AE63: =SUM(AE34:AE62) -> 27317253 | AF63: =SUM(AF34:AF62) -> 3.7756276e+10 | AH63: =SUM(AH34:AH62) -> 20338176 | AI63: =SUM(AI34:AI62) -> 3.0804392e+10 | AK63: =SUM(AK34:AK62) -> 15084913 | AL63: =SUM(AL34:AL62) -> 2.886227e+10 | AN63: =SUM(AN34:AN62) -> 12848960
C64: EARNINGS BEFORE INTEREST AND TAX | E64: =E31-E63 -> 9.4026875e+11 | G64: =G31-G63 -> 8.820432e+08 | H64: =H31-H63 -> 0 | J64: =J31-J63 -> 0 | K64: =K31-K63 -> -2.003058e+09 | M64: =M31-M63 -> -2102641.2 | N64: =N31-N63 -> 1.4547893e+10 | P64: =P31-P63 -> 13882864 | Q64: =Q31-Q63 -> 4.5118669e+10 | S64: =S31-S63 -> 39141959 | T64: =T31-T63 -> 6.1417847e+10 | V64: =V31-V63 -> 48438220 | W64: =W31-W63 -> 7.7984643e+10 | Y64: =Y31-Y63 -> 55912639 | Z64: =Z31-Z63 -> 1.7213317e+11 | AB64: =AB31-AB63 -> 47015738 | AC64: =AC31-AC63 -> 8.922787e+10 | AE64: =AE31-AE63 -> 52870821 | AF64: =AF31-AF63 -> 1.0941095e+11 | AH64: =AH31-AH63 -> 58936404 | AI64: =AI31-AI63 -> 1.2875679e+11 | AK64: =AK31-AK63 -> 63052208 | AL64: =AL31-AL63 -> 2.4367398e+11 | AN64: =AN31-AN63 -> 1.0847924e+08
C66: Interest | E66: =K66+N66+Q66+T66+W66+Z65+AC66+AF66+AI66+AL66 -> 0 | F66: =F49 -> 952.639 | G66: =E66/F66 -> 0 | I66: =I49 -> 952.639 | J66: =H66/I66 -> 0 | K66: ='Cashflow Statement'!N90 -> 0 | L66: =L49 -> 952.639 | M66: =K66/L66 -> 0 | O66: =O49 -> 1047.9029 | P66: =N66/O66 -> 0 | R66: =R49 -> 1152.6932 | S66: =Q66/R66 -> 0 | U66: =U49 -> 1267.9625 | V66: =T66/U66 -> 0 | X66: =X49 -> 1394.7588 | Y66: =W66/X66 -> 0 | Z66: 0 | AA66: =AA49 -> 1534.2346 | AB66: =Z66/AA66 -> 0 | AC66: 0 | AD66: =AD49 -> 1687.6581 | AE66: =AC66/AD66 -> 0 | AF66: 0 | AG66: =AG49 -> 1856.4239 | AH66: =AF66/AG66 -> 0 | AI66: 0 | AJ66: =AJ49 -> 2042.0663 | AK66: =AI66/AJ66 -> 0 | AL66: 0 | AM66: =AM49 -> 2246.2729 | AN66: =AL66/AM66 -> 0
C67: NET EARNINGS AFTER INTEREST | E67: =E64-E65+E66 -> 9.4026875e+11 | G67: =G64-G65+G66 -> 8.820432e+08 | H67: =H64-H65+H66 -> 0 | J67: =J64-J65+J66 -> 0 | K67: =K64-K65+K66 -> -2.003058e+09 | M67: =M64-M65+M66 -> -2102641.2 | N67: =N64-N65+N66 -> 1.4547893e+10 | P67: =P64-P65+P66 -> 13882864 | Q67: =Q64-Q65+Q66 -> 4.5118669e+10 | S67: =S64-S65+S66 -> 39141959 | T67: =SUM(T64:T66) -> 6.1417847e+10 | V67: =V64-V65+V66 -> 48438220 | W67: =SUM(W64:W66) -> 7.7984643e+10 | Y67: =Y64-Y65+Y66 -> 55912639 | Z67: =SUM(Z64:Z65)-Z66 -> 1.7213317e+11 | AB67: =AB64-AB65+AB66 -> 47015738 | AC67: =AC64-AC65-AC66 -> 8.922787e+10 | AE67: =AE64-AE65+AE66 -> 52870821 | AF67: =AF64-AF65-AF66 -> 1.0941095e+11 | AH67: =AH64-AH65+AH66 -> 58936404 | AI67: =AI64-AI65-AI66 -> 1.2875679e+11 | AK67: =AK64-AK65+AK66 -> 63052208 | AL67: =AL64-AL65-AL66 -> 2.4367398e+11 | AN67: =AN64-AN65+AN66 -> 1.0847924e+08
C70: Tax | E70: =K70+N70+Q70+T70+W70+Z70+AC70+AF70+AI70+AL70 -> 3.109497e+11 | F70: =F60 -> 952.639 | G70: =E70/F70 -> 3.2640874e+08 | I70: =I60 -> 952.639 | J70: =H70/I70 -> 0 | K70: 0 | L70: =L60 -> 952.639 | M70: =K70/L70 -> 0 | N70: =N67*33% -> 4.8008048e+09 | O70: =O60 -> 1047.9029 | P70: =N70/O70 -> 4581345.1 | Q70: =Q67*33% -> 1.4889161e+10 | R70: =R60 -> 1152.6932 | S70: =Q70/R70 -> 12916846 | T70: =T67*33% -> 2.0267889e+10 | U70: =U60 -> 1267.9625 | V70: =T70/U70 -> 15984613 | W70: =W67*33% -> 2.5734932e+10 | X70: =X60 -> 1394.7588 | Y70: =W70/X70 -> 18451171 | Z70: =Z67*33% -> 5.6803947e+10 | AA70: =AA60 -> 1534.2346 | AB70: =Z70/AA70 -> 37024289 | AC70: =AC67*33% -> 2.9445197e+10 | AD70: =AD60 -> 1687.6581 | AE70: =AC70/AD70 -> 17447371 | AF70: =AF67*33% -> 3.6105613e+10 | AG70: =AG60 -> 1856.4239 | AH70: =AF70/AG70 -> 19449013 | AI70: =AI67*33% -> 4.248974e+10 | AJ70: =AJ60 -> 2042.0663 | AK70: =AI70/AJ70 -> 20807229 | AL70: =AL67*33% -> 8.0412413e+10 | AM70: =AM60 -> 2246.2729 | AN70: =AL70/AM70 -> 35798149
C71: NET EARNINGS AFTER TAX | E71: =E68-E69+E70 -> 3.109497e+11 | G71: =G68-G69+G70 -> 3.2640874e+08 | H71: =H68-H69+H70 -> 0 | J71: =J68-J69+J70 -> 0 | K71: =K67-K70 -> -2.003058e+09 | M71: =M67-M70 -> -2102641.2 | N71: =N67-N70 -> 9.7470885e+09 | P71: =P67-P70 -> 9301518.8 | Q71: =Q67-Q70 -> 3.0229508e+10 | S71: =S67-S70 -> 26225112 | T71: =T67-T70 -> 4.1149957e+10 | V71: =V67-V70 -> 32453607 | W71: =W67-W70 -> 5.2249711e+10 | Y71: =Y67-Y70 -> 37461468 | Z71: =Z67-Z70 -> 1.1532923e+11 | AB71: =AB67-AB70 -> 9991448.3 | AC71: =AC67-AC70 -> 5.9782673e+10 | AE71: =AE67-AE70 -> 35423450 | AF71: =AF67-AF70 -> 7.3305336e+10 | AH71: =AH67-AH70 -> 39487391 | AI71: =AI67-AI70 -> 8.6267048e+10 | AK71: =AK67-AK70 -> 42244979 | AL71: =AL67-AL70 -> 1.6326157e+11 | AN71: =AN67-AN70 -> 72681090
C72: Apportionment of Earnings
C73: Dividend | E73: =K73+N73+Q73+T73+W73+Z73+AC73+AF73+AI73+AL73 -> -1.5732976e+10 | F73: =F66 -> 952.639 | G73: =E73/F73 -> -16515150 | I73: =I66 -> 952.639 | J73: =H73/I73 -> 0 | K73: =-K71*2.5% -> 50076450 | L73: =L66 -> 952.639 | M73: =K73/L73 -> 52566.029 | N73: =-N71*2.5% -> -2.4367721e+08 | O73: =O66 -> 1047.9029 | P73: =N73/O73 -> -232537.97 | Q73: =-Q71*2.5% -> -7.5573771e+08 | R73: =R66 -> 1152.6932 | S73: =Q73/R73 -> -655627.81 | T73: =-T71*2.5% -> -1.0287489e+09 | U73: =U66 -> 1267.9625 | V73: =T73/U73 -> -811340.18 | W73: =-W71*2.5% -> -1.3062428e+09 | X73: =X66 -> 1394.7588 | Y73: =W73/X73 -> -936536.71 | Z73: =-Z71*2.5% -> -2.8832307e+09 | AA73: =AA66 -> 1534.2346 | AB73: =Z73/AA73 -> -1879263.2 | AC73: =-AC71*2.5% -> -1.4945668e+09 | AD73: =AD66 -> 1687.6581 | AE73: =AC73/AD73 -> -885586.26 | AF73: =-AF71*2.5% -> -1.8326334e+09 | AG73: =AG66 -> 1856.4239 | AH73: =AF73/AG73 -> -987184.77 | AI73: =-AI71*2.5% -> -2.1566762e+09 | AJ73: =AJ66 -> 2042.0663 | AK73: =AI73/AJ73 -> -1056124.5 | AL73: =-AL71*2.5% -> -4.0815391e+09 | AM73: =AM66 -> 2246.2729 | AN73: =AL73/AM73 -> -1817027.2
C75: ASSET RECOVERY & REPLACEMENT RESERVE | E75: =E67+SUM(E73:E73) -> 9.2453578e+11 | G75: =G67+SUM(G73:G73) -> 8.6552805e+08 | H75: =H67+SUM(H73:H73) -> 0 | J75: =J67+SUM(J73:J73) -> 0 | K75: =K71+K73 -> -1.9529815e+09 | M75: =M71+M73 -> -2050075.2 | N75: =N71+N73 -> 9.5034113e+09 | P75: =P71+P73 -> 9068980.8 | Q75: =Q71+Q73 -> 2.9473771e+10 | S75: =S71+S73 -> 25569485 | T75: =T71+T73 -> 4.0121208e+10 | V75: =V71+V73 -> 31642267 | W75: =W71+W73 -> 5.0943468e+10 | Y75: =Y71+Y73 -> 36524931 | Z75: =Z71+Z73 -> 1.12446e+11 | AB75: =AB71+AB73 -> 8112185.1 | AC75: =AC71+AC73 -> 5.8288106e+10 | AE75: =AE71+AE73 -> 34537864 | AF75: =AF71+AF73 -> 7.1472703e+10 | AH75: =AH71+AH73 -> 38500206 | AI75: =AI71+AI73 -> 8.4110372e+10 | AK75: =AK71+AK73 -> 41188855 | AL75: =AL71+AL73 -> 1.5918003e+11 | AN75: =AN71+AN73 -> 70864063

Sheet Cashflow Statement
C2: Projected Cash Flow Statement
C3: Enhancement of Public Transportation in the FCT
K5: Construction/ Deployment Period | N5: 1 | Q5: =N5+1 -> 2 | T5: =Q5+1 -> 3 | W5: =T5+1 -> 4 | Z5: =W5+1 -> 5 | AC5: =Z5+1 -> 6 | AF5: =AC5+1 -> 7 | AI5: =AF5+1 -> 8 | AL5: =AI5+1 -> 9 | AO5: =AL5+1 -> 10
F6: Rate | H6: Cummulative | K6: 2023 | N6: 45657 | Q6: 46022 | T6: 46387 | W6: 46752 | Z6: 47118 | AC6: 47483 | AF6: 47848 | AI6: 48213 | AL6: 48579 | AO6: 48944
D7: Basis | E7: Rate | G7: Annual Growth Factor | H7: NGN | J7: USD | K7: NGN | M7: USD | N7: NGN | P7: USD | Q7: NGN | S7: USD | T7: NGN | V7: USD | W7: NGN | Y7: USD | Z7: NGN | AB7: USD | AC7: NGN | AE7: USD | AF7: NGN | AH7: USD | AI7: NGN | AK7: USD | AL7: NGN | AN7: USD | AO7: NGN | AQ7: USD
C8: Beginning Cash Balance | F8: ='Parameters and Summary'!E70 -> 952.639 | H8: =K8 -> 0 | I8: ='Exchange Rate growth '!D6 -> 952.639 | J8: =M8 -> 0 | L8: ='Exchange Rate growth '!D6 -> 952.639 | M8: =K8/L8 -> 0 | N8: =K91 -> 445000000 | O8: ='Exchange Rate growth '!D6 -> 952.639 | P8: =N8/O8 -> 467123.43 | Q8: =N91 -> 1.4593225e+10 | R8: ='Exchange Rate growth '!E6 -> 1047.9029 | S8: =Q8/R8 -> 13926123 | T8: =Q91 -> 6.3102839e+10 | U8: ='Exchange Rate growth '!F6 -> 1152.6932 | V8: =T8/U8 -> 54743829 | W8: =T91 -> 1.5662507e+11 | X8: ='Exchange Rate growth '!G6 -> 1267.9625 | Y8: =W8/X8 -> 1.23525e+08 | Z8: =W91 -> 2.773361e+11 | AA8: ='Exchange Rate growth '!H6 -> 1394.7588 | AB8: =Z8/AA8 -> 1.9884162e+08 | AC8: =Z91 -> 4.3260122e+11 | AD8: ='Exchange Rate growth '!I6 -> 1534.2346 | AE8: =AC8/AD8 -> 2.8196549e+08 | AF8: =AC91 -> 4.1624089e+11 | AG8: ='Exchange Rate growth '!J6 -> 1687.6581 | AH8: =AF8/AG8 -> 2.4663816e+08 | AI8: =AF91 -> 2.583263e+11 | AJ8: ='Exchange Rate growth '!K6 -> 1856.4239 | AK8: =AI8/AJ8 -> 1.3915265e+08 | AL8: =AI91 -> 1.2073898e+11 | AM8: ='Exchange Rate growth '!L6 -> 2042.0663 | AN8: =AL8/AM8 -> 59125884 | AO8: =AL91 -> -3.5964561e+10 | AP8: ='Exchange Rate growth '!M6 -> 2246.2729 | AQ8: =AO8/AP8 -> -16010771
C10: CASH INFLOWS
C11: ='[2]Investment Financing'!C6 -> Equity Financing | F11: =F8 -> 952.639 | H11: =K11+N11+Q11+T11+W11+Z11+AC11+AF11+AI11+AL11+AO11 -> 500000000 | I11: =I8 -> 952.639 | J11: =M11+P11+S11+V11+Y11+AB11+AE11+AH11+AK11+AN11+AQ11 -> 524857.79 | K11: 500000000 | L11: =L8 -> 952.639 | M11: =K11/L11 -> 524857.79 | O11: =O8 -> 952.639 | P11: =N11/O11 -> 0 | R11: =R8 -> 1047.9029 | S11: =Q11/R11 -> 0 | U11: =U8 -> 1152.6932 | V11: =T11/U11 -> 0 | X11: =X8 -> 1267.9625 | Y11: =W11/X11 -> 0 | AA11: =AA8 -> 1394.7588 | AB11: =Z11/AA11 -> 0 | AD11: =AD8 -> 1534.2346 | AE11: =AC11/AD11 -> 0 | AG11: =AG8 -> 1687.6581 | AH11: =AF11/AG11 -> 0 | AJ11: =AJ8 -> 1856.4239 | AK11: =AI11/AJ11 -> 0 | AM11: =AM8 -> 2042.0663 | AN11: =AL11/AM11 -> 0 | AP11: =AP8 -> 2246.2729 | AQ11: =AO11/AP11 -> 0
I12: =D12 -> 0
C13: Bonds | F13: =F12 -> 0 | H13: =K13+N13+Q13+T13+W13+Z13+AC13+AF13+AI13+AL13+AO13 -> 100000000000 | I13: =I12 -> 0 | J13: =M13+P13+S13+V13+Y13+AB13+AE13+AH13+AK13+AN13+AQ13 -> #DIV/0! | L13: =L12 -> 0 | M13: =K13/L13 -> #DIV/0! | N13: ='Revenue Schedule'!AE60 -> 0 | O13: =O12 -> 0 | P13: =N13/O13 -> #DIV/0! | Q13: ='Revenue Schedule'!BD60 -> 0 | R13: =R12 -> 0 | S13: =Q13/R13 -> #DIV/0! | T13: ='Revenue Schedule'!CC60 -> 0 | U13: =U12 -> 0 | V13: =T13/U13 -> #DIV/0! | W13: ='Revenue Schedule'!DB60 -> 0 | X13: =X12 -> 0 | Y13: =W13/X13 -> #DIV/0! | Z13: ='Revenue Schedule'!EA60 -> 0 | AA13: =AA11 -> 1394.7588 | AB13: =Z13/AA13 -> 0 | AC13: 100000000000 | AD13: =AD11 -> 1534.2346 | AE13: =AC13/AD13 -> 65179079 | AF13: ='Revenue Schedule'!FY60 -> 0 | AG13: =AG11 -> 1687.6581 | AH13: =AF13/AG13 -> 0 | AI13: ='Revenue Schedule'!GX60 -> 0 | AJ13: =AJ11 -> 1856.4239 | AK13: =AI13/AJ13 -> 0 | AL13: ='Revenue Schedule'!HW60 -> 0 | AM13: =AM11 -> 2042.0663 | AN13: =AL13/AM13 -> 0 | AO13: ='Revenue Schedule'!IV60 -> 0 | AP13: =AP11 -> 2246.2729 | AQ13: =AO13/AP13 -> 0
AC14: 0
C15: Transportation Fare
C16: Taxi | F16: =F11 -> 952.639 | H16: =K16+N16+Q16+T16+W16+Z16+AC16+AF16+AI16+AL16+AO16 -> 7.8514975e+11 | I16: =I11 -> 952.639 | J16: =M16+P16+S16+V16+Y16+AB16+AE16+AH16+AK16+AN16+AQ16 -> 4.9352173e+08 | L16: =L11 -> 952.639 | M16: =K16/L16 -> 0 | N16: ='Revenue Schedule'!AE31 -> 14990400000 | O16: =O11 -> 952.639 | P16: =N16/O16 -> 15735656 | Q16: ='Revenue Schedule'!BD31 -> 31479840000 | R16: =R11 -> 1047.9029 | S16: =Q16/R16 -> 30040799 | T16: ='Revenue Schedule'!CC31 -> 49580748000 | U16: =U11 -> 1152.6932 | V16: =T16/U16 -> 43012962 | W16: ='Revenue Schedule'!DB31 -> 69413047200 | X16: =X11 -> 1267.9625 | Y16: =W16/X16 -> 54743769 | Z16: ='Revenue Schedule'!EA31 -> 91104624450 | AA16: =AA11 -> 1394.7588 | AB16: =Z16/AA16 -> 65319270 | AC16: ='Revenue Schedule'!EZ31 -> 9.5659856e+10 | AD16: =AD11 -> 1534.2346 | AE16: =AC16/AD16 -> 62350213 | AF16: ='Revenue Schedule'!FY31 -> 1.0044285e+11 | AG16: =AG11 -> 1687.6581 | AH16: =AF16/AG16 -> 59516112 | AI16: ='Revenue Schedule'!GX31 -> 1.0546499e+11 | AJ16: =AJ11 -> 1856.4239 | AK16: =AI16/AJ16 -> 56810834 | AL16: ='Revenue Schedule'!HW31 -> 1.1073824e+11 | AM16: =AM11 -> 2042.0663 | AN16: =AL16/AM16 -> 54228524 | AO16: ='Revenue Schedule'!IV31 -> 1.1627515e+11 | AP16: =AP11 -> 2246.2729 | AQ16: =AO16/AP16 -> 51763591
C17: Bus | F17: =F16 -> 952.639 | H17: =K17+N17+Q17+T17+W17+Z17+AC17+AF17+AI17+AL17+AO17 -> 1.1541257e+12 | I17: =I16 -> 952.639 | J17: =M17+P17+S17+V17+Y17+AB17+AE17+AH17+AK17+AN17+AQ17 -> 7.1796372e+08 | L17: =L16 -> 952.639 | M17: =K17/L17 -> 0 | N17: ='Revenue Schedule'!AE64 -> 15662809512 | O17: =O16 -> 952.639 | P17: =N17/O17 -> 16441495 | Q17: ='Revenue Schedule'!BD64 -> 3.28919e+10 | R17: =R16 -> 1047.9029 | S17: =Q17/R17 -> 31388309 | T17: ='Revenue Schedule'!CC64 -> 7.4206793e+10 | U17: =U16 -> 1152.6932 | V17: =T17/U17 -> 64376882 | W17: ='Revenue Schedule'!DB64 -> 1.0388951e+11 | X17: =X16 -> 1267.9625 | Y17: =W17/X17 -> 81934213 | Z17: ='Revenue Schedule'!EA64 -> 1.3635498e+11 | AA17: =AA16 -> 1394.7588 | AB17: =Z17/AA17 -> 97762413 | AC17: ='Revenue Schedule'!EZ64 -> 1.4317273e+11 | AD17: =AD16 -> 1534.2346 | AE17: =AC17/AD17 -> 93318667 | AF17: ='Revenue Schedule'!FY64 -> 1.5033137e+11 | AG17: =AG16 -> 1687.6581 | AH17: =AF17/AG17 -> 89076910 | AI17: ='Revenue Schedule'!GX64 -> 1.5784794e+11 | AJ17: =AJ16 -> 1856.4239 | AK17: =AI17/AJ17 -> 85027959 | AL17: ='Revenue Schedule'!HW64 -> 1.6574033e+11 | AM17: =AM16 -> 2042.0663 | AN17: =AL17/AM17 -> 81163052 | AO17: ='Revenue Schedule'!IV64 -> 1.7402735e+11 | AP17: =AP16 -> 2246.2729 | AQ17: =AO17/AP17 -> 77473822
C20: Fleets Disposal | AO20: 100000000000 | AP20: =AP17 -> 2246.2729 | AQ20: =AO20/AP20 -> 44518188
C22: TOTAL CASH INFLOWS | H22: =SUM(H8:H21) -> 2.0397755e+12 | J22: =SUM(J8:J21) -> #DIV/0! | K22: =SUM(K8:K21) -> 500000000 | M22: =SUM(M8:M21) -> #DIV/0! | N22: =SUM(N8:N21) -> 31098209512 | P22: =SUM(P8:P21) -> #DIV/0! | Q22: =SUM(Q8:Q21) -> 7.8964965e+10 | S22: =SUM(S8:S21) -> #DIV/0! | T22: =SUM(T8:T21) -> 1.8689038e+11 | V22: =SUM(V8:V21) -> #DIV/0! | W22: =SUM(W8:W21) -> 3.2992763e+11 | Y22: =SUM(Y8:Y21) -> #DIV/0! | Z22: =SUM(Z8:Z21) -> 5.047957e+11 | AB22: =SUM(AB8:AB21) -> 3.6192331e+08 | AC22: =SUM(AC8:AC21) -> 7.7143381e+11 | AE22: =SUM(AE8:AE21) -> 5.0281345e+08 | AF22: =SUM(AF8:AF21) -> 6.6701511e+11 | AH22: =SUM(AH8:AH21) -> 3.9523118e+08 | AI22: =SUM(AI8:AI21) -> 5.2163923e+11 | AK22: =SUM(AK8:AK21) -> 2.8099144e+08 | AL22: =SUM(AL8:AL21) -> 3.9721755e+11 | AN22: =SUM(AN8:AN21) -> 1.9451746e+08 | AO22: =SUM(AO8:AO21) -> 3.5433794e+11 | AQ22: =SUM(AQ8:AQ21) -> 1.5774483e+08
C24: CASH OUTFLOWS
C25: INVESTING ACTIVITIES
C28: Infrastructure
C30: Furnitures, Fittings and Equipment | D30: Actual | F30: =F17 -> 952.639 | G30: 1.1 | H30: =K30+N30+Q30+T30+W30+Z30+AC30+AF30+AI30+AL30+AO30 -> 55000000 | I30: =I17 -> 952.639 | J30: =M30+P30+S30+V30+Y30+AB30+AE30+AH30+AK30+AN30+AQ30 -> 57734.357 | K30: =CAPEX!C28 -> 55000000 | L30: =L17 -> 952.639 | M30: =K30/L30 -> 57734.357 | O30: =O17 -> 952.639 | P30: =N30/O30 -> 0 | Q30: =N30*$G30 -> 0 | R30: =R17 -> 1047.9029 | S30: =Q30/R30 -> 0 | T30: =Q30*$G30 -> 0 | U30: =U17 -> 1152.6932 | V30: =T30/U30 -> 0 | W30: =T30*$G30 -> 0 | X30: =X17 -> 1267.9625 | Y30: =W30/X30 -> 0 | Z30: =W30*$G30 -> 0 | AA30: =AA17 -> 1394.7588 | AB30: =Z30/AA30 -> 0 | AC30: =Z30*$G30 -> 0 | AD30: =AD17 -> 1534.2346 | AE30: =AC30/AD30 -> 0 | AF30: =AC30*$G30 -> 0 | AG30: =AG17 -> 1687.6581 | AH30: =AF30/AG30 -> 0 | AI30: =AF30*$G30 -> 0 | AJ30: =AJ17 -> 1856.4239 | AK30: =AI30/AJ30 -> 0 | AL30: =AI30*$G30 -> 0 | AM30: =AM17 -> 2042.0663 | AN30: =AL30/AM30 -> 0 | AO30: =AL30*$G30 -> 0 | AP30: =AP17 -> 2246.2729 | AQ30: =AO30/AP30 -> 0
C33: OPERATING ACTIVITIES
C35: Direct Cost
C37: Direct Labour/Wage Cost
C38: Drivers- Taxi | F38: =F30 -> 952.639 | G38: =G30 -> 1.1 | H38: =K38+N38+Q38+T38+W38+Z38+AC38+AF38+AI38+AL38+AO38 -> 5.3071624e+10 | I38: =I30 -> 952.639 | J38: =M38+P38+S38+V38+Y38+AB38+AE38+AH38+AK38+AN38+AQ38 -> 34955529 | L38: =L30 -> 952.639 | M38: =K38/L38 -> 0 | N38: =OPEX!I9 -> 3330000000 | O38: =O30 -> 952.639 | P38: =N38/O38 -> 3495552.9 | Q38: =N38*G38 -> 3.663e+09 | R38: =R30 -> 1047.9029 | S38: =Q38/R38 -> 3495552.9 | T38: =Q38*$G38 -> 4.0293e+09 | U38: =U30 -> 1152.6932 | V38: =T38/U38 -> 3495552.9 | W38: =T38*$G38 -> 4.43223e+09 | X38: =X30 -> 1267.9625 | Y38: =W38/X38 -> 3495552.9 | Z38: =W38*$G38 -> 4.875453e+09 | AA38: =AA30 -> 1394.7588 | AB38: =Z38/AA38 -> 3495552.9 | AC38: =Z38*$G38 -> 5.3629983e+09 | AD38: =AD30 -> 1534.2346 | AE38: =AC38/AD38 -> 3495552.9 | AF38: =AC38*$G38 -> 5.8992981e+09 | AG38: =AG30 -> 1687.6581 | AH38: =AF38/AG38 -> 3495552.9 | AI38: =AF38*$G38 -> 6.4892279e+09 | AJ38: =AJ30 -> 1856.4239 | AK38: =AI38/AJ38 -> 3495552.9 | AL38: =AI38*$G38 -> 7.1381507e+09 | AM38: =AM30 -> 2042.0663 | AN38: =AL38/AM38 -> 3495552.9 | AO38: =AL38*$G38 -> 7.8519658e+09 | AP38: =AP30 -> 2246.2729 | AQ38: =AO38/AP38 -> 3495552.9
C39: Drivers- Bus | F39: =F38 -> 952.639 | G39: =G38 -> 1.1 | H39: =K39+N39+Q39+T39+W39+Z39+AC39+AF39+AI39+AL39+AO39 -> 1.0040577e+10 | I39: =I38 -> 952.639 | J39: =M39+P39+S39+V39+Y39+AB39+AE39+AH39+AK39+AN39+AQ39 -> 6613208.2 | L39: =L38 -> 952.639 | M39: =K39/L39 -> 0 | N39: =OPEX!I15 -> 630000000 | O39: =O38 -> 952.639 | P39: =N39/O39 -> 661320.82 | Q39: =N39*G39 -> 693000000 | R39: =R38 -> 1047.9029 | S39: =Q39/R39 -> 661320.82 | T39: =Q39*$G39 -> 7.623e+08 | U39: =U38 -> 1152.6932 | V39: =T39/U39 -> 661320.82 | W39: =T39*$G39 -> 8.3853e+08 | X39: =X38 -> 1267.9625 | Y39: =W39/X39 -> 661320.82 | Z39: =W39*$G39 -> 9.22383e+08 | AA39: =AA38 -> 1394.7588 | AB39: =Z39/AA39 -> 661320.82 | AC39: =Z39*$G39 -> 1.0146213e+09 | AD39: =AD38 -> 1534.2346 | AE39: =AC39/AD39 -> 661320.82 | AF39: =AC39*$G39 -> 1.1160834e+09 | AG39: =AG38 -> 1687.6581 | AH39: =AF39/AG39 -> 661320.82 | AI39: =AF39*$G39 -> 1.2276918e+09 | AJ39: =AJ38 -> 1856.4239 | AK39: =AI39/AJ39 -> 661320.82 | AL39: =AI39*$G39 -> 1.350461e+09 | AM39: =AM38 -> 2042.0663 | AN39: =AL39/AM39 -> 661320.82 | AO39: =AL39*$G39 -> 1.485507e+09 | AP39: =AP38 -> 2246.2729 | AQ39: =AO39/AP39 -> 661320.82
C42: Repairs & Maintanance | F42: =F39 -> 952.639 | G42: =G40 -> 0 | H42: =K42+N42+Q42+T42+W42+Z42+AC42+AF42+AI42+AL42+AO42 -> 360000000 | I42: =I39 -> 952.639 | J42: =M42+P42+S42+V42+Y42+AB42+AE42+AH42+AK42+AN42+AQ42 -> 377897.61 | L42: =L39 -> 952.639 | M42: =K42/L42 -> 0 | N42: =OPEX!I42 -> 360000000 | O42: =O39 -> 952.639 | P42: =N42/O42 -> 377897.61 | Q42: =N42*G42 -> 0 | R42: =R39 -> 1047.9029 | S42: =Q42/R42 -> 0 | T42: =Q42*$G42 -> 0 | U42: =U39 -> 1152.6932 | V42: =T42/U42 -> 0 | W42: =T42*$G42 -> 0 | X42: =X39 -> 1267.9625 | Y42: =W42/X42 -> 0 | Z42: =W42*$G42 -> 0 | AA42: =AA39 -> 1394.7588 | AB42: =Z42/AA42 -> 0 | AC42: =Z42*$G42 -> 0 | AD42: =AD39 -> 1534.2346 | AE42: =AC42/AD42 -> 0 | AF42: =AC42*$G42 -> 0 | AG42: =AG39 -> 1687.6581 | AH42: =AF42/AG42 -> 0 | AI42: =AF42*$G42 -> 0 | AJ42: =AJ39 -> 1856.4239 | AK42: =AI42/AJ42 -> 0 | AL42: =AI42*$G42 -> 0 | AM42: =AM39 -> 2042.0663 | AN42: =AL42/AM42 -> 0 | AO42: =AL42*$G42 -> 0 | AP42: =AP39 -> 2246.2729 | AQ42: =AO42/AP42 -> 0
C43: Energy and Power | F43: =F42 -> 952.639 | G43: =G42 -> 0 | H43: =K43+N43+Q43+T43+W43+Z43+AC43+AF43+AI43+AL43+AO43 -> 5299200000 | I43: =I42 -> 952.639 | J43: =M43+P43+S43+V43+Y43+AB43+AE43+AH43+AK43+AN43+AQ43 -> 5562652.8 | L43: =L42 -> 952.639 | M43: =K43/L43 -> 0 | N43: =OPEX!I48 -> 5299200000 | O43: =O42 -> 952.639 | P43: =N43/O43 -> 5562652.8 | Q43: =N43*G43 -> 0 | R43: =R42 -> 1047.9029 | S43: =Q43/R43 -> 0 | T43: =Q43*$G43 -> 0 | U43: =U42 -> 1152.6932 | V43: =T43/U43 -> 0 | W43: =T43*$G43 -> 0 | X43: =X42 -> 1267.9625 | Y43: =W43/X43 -> 0 | Z43: =W43*$G43 -> 0 | AA43: =AA42 -> 1394.7588 | AB43: =Z43/AA43 -> 0 | AC43: =Z43*$G43 -> 0 | AD43: =AD42 -> 1534.2346 | AE43: =AC43/AD43 -> 0 | AF43: =AC43*$G43 -> 0 | AG43: =AG42 -> 1687.6581 | AH43: =AF43/AG43 -> 0 | AI43: =AF43*$G43 -> 0 | AJ43: =AJ42 -> 1856.4239 | AK43: =AI43/AJ43 -> 0 | AL43: =AI43*$G43 -> 0 | AM43: =AM42 -> 2042.0663 | AN43: =AL43/AM43 -> 0 | AO43: =AL43*$G43 -> 0 | AP43: =AP42 -> 2246.2729 | AQ43: =AO43/AP43 -> 0
C46: Fleets Insurance | D46: Asset | E46: 0.01 | F46: =F43 -> 952.639 | H46: =K46+N46+Q46+T46+W46+Z46+AC46+AF46+AI46+AL46+AO46 -> 7.6985677e+10 | I46: =I43 -> 952.639 | J46: =M46+P46+S46+V46+Y46+AB46+AE46+AH46+AK46+AN46+AQ46 -> 49334341 | L46: =L43 -> 952.639 | M46: =K46/L46 -> 0 | N46: =$E46*CAPEX!C8 -> 1.6145783e+09 | O46: =O43 -> 952.639 | P46: =N46/O46 -> 1694848 | Q46: =$E46*CAPEX!D8 -> 3.3906144e+09 | R46: =R43 -> 1047.9029 | S46: =Q46/R46 -> 3235618.9 | T46: =$E46*CAPEX!E8 -> 5.3442542e+09 | U46: =U43 -> 1152.6932 | V46: =T46/U46 -> 4636319.7 | W46: =$E46*CAPEX!F8 -> 7.4932579e+09 | X46: =X43 -> 1267.9625 | Y46: =W46/X46 -> 5909684.1 | Z46: =$E46*CAPEX!G8 -> 9.857162e+09 | AA46: =AA43 -> 1394.7588 | AB46: =Z46/AA46 -> 7067288.1 | AC46: =$E46*CAPEX!H8 -> 9.857162e+09 | AD46: =AD43 -> 1534.2346 | AE46: =AC46/AD46 -> 6424807.4 | AF46: =$E46*CAPEX!I8 -> 9.857162e+09 | AG46: =AG43 -> 1687.6581 | AH46: =AF46/AG46 -> 5840734 | AI46: =$E46*CAPEX!J8 -> 9.857162e+09 | AJ46: =AJ43 -> 1856.4239 | AK46: =AI46/AJ46 -> 5309758.2 | AL46: =$E46*CAPEX!J8 -> 9.857162e+09 | AM46: =AM43 -> 2042.0663 | AN46: =AL46/AM46 -> 4827052.9 | AO46: =$E46*CAPEX!K8 -> 9.857162e+09 | AP46: =AP43 -> 2246.2729 | AQ46: =AO46/AP46 -> 4388229.9
C50: Operating & Maintenance Cost
C51: Personnel costs | F51: =F46 -> 952.639 | G51: =G38 -> 1.1 | H51: =K51+N51+Q51+T51+W51+Z51+AC51+AF51+AI51+AL51+AO51 -> 9.3712057e+09 | I51: =I46 -> 952.639 | J51: =M51+P51+S51+V51+Y51+AB51+AE51+AH51+AK51+AN51+AQ51 -> 6172327.6 | L51: =L46 -> 952.639 | M51: =K51/L51 -> 0 | N51: =OPEX!I36 -> 588000000 | O51: =O46 -> 952.639 | P51: =N51/O51 -> 617232.76 | Q51: =N51*G51 -> 646800000 | R51: =R46 -> 1047.9029 | S51: =Q51/R51 -> 617232.76 | T51: =Q51*$G51 -> 711480000 | U51: =U46 -> 1152.6932 | V51: =T51/U51 -> 617232.76 | W51: =T51*$G51 -> 7.82628e+08 | X51: =X46 -> 1267.9625 | Y51: =W51/X51 -> 617232.76 | Z51: =W51*$G51 -> 8.608908e+08 | AA51: =AA46 -> 1394.7588 | AB51: =Z51/AA51 -> 617232.76 | AC51: =Z51*$G51 -> 9.4697988e+08 | AD51: =AD46 -> 1534.2346 | AE51: =AC51/AD51 -> 617232.76 | AF51: =AC51*$G51 -> 1.0416779e+09 | AG51: =AG46 -> 1687.6581 | AH51: =AF51/AG51 -> 617232.76 | AI51: =AF51*$G51 -> 1.1458457e+09 | AJ51: =AJ46 -> 1856.4239 | AK51: =AI51/AJ51 -> 617232.76 | AL51: =AI51*$G51 -> 1.2604302e+09 | AM51: =AM46 -> 2042.0663 | AN51: =AL51/AM51 -> 617232.76 | AO51: =AL51*$G51 -> 1.3864732e+09 | AP51: =AP46 -> 2246.2729 | AQ51: =AO51/AP51 -> 617232.76
C53: Other operating costs
C54: Admin Assets Insurance | D54: Asset Cost | E54: 0.01 | F54: =F51 -> 952.639 | G54: =G51 -> 1.1 | H54: =K54+N54+Q54+T54+W54+Z54+AC54+AF54+AI54+AL54+AO54 -> 5500000 | I54: =I51 -> 952.639 | J54: =M54+P54+S54+V54+Y54+AB54+AE54+AH54+AK54+AN54+AQ54 -> 3902.2789 | L54: =L51 -> 952.639 | M54: =K54/L54 -> 0 | N54: =$E54*CAPEX!C30 -> 550000 | O54: =O51 -> 952.639 | P54: =N54/O54 -> 577.34357 | Q54: =$E54*CAPEX!D30 -> 550000 | R54: =R51 -> 1047.9029 | S54: =Q54/R54 -> 524.85779 | T54: =$E54*CAPEX!E30 -> 550000 | U54: =U51 -> 1152.6932 | V54: =T54/U54 -> 477.14345 | W54: =$E54*CAPEX!F30 -> 550000 | X54: =X51 -> 1267.9625 | Y54: =W54/X54 -> 433.76677 | Z54: =$E54*CAPEX!G30 -> 550000 | AA54: =AA51 -> 1394.7588 | AB54: =Z54/AA54 -> 394.33343 | AC54: =$E54*CAPEX!H30 -> 550000 | AD54: =AD51 -> 1534.2346 | AE54: =AC54/AD54 -> 358.48493 | AF54: =$E54*CAPEX!I30 -> 550000 | AG54: =AG51 -> 1687.6581 | AH54: =AF54/AG54 -> 325.89539 | AI54: =$E54*CAPEX!J30 -> 550000 | AJ54: =AJ51 -> 1856.4239 | AK54: =AI54/AJ54 -> 296.26854 | AL54: =$E54*CAPEX!K30 -> 550000 | AM54: =AM51 -> 2042.0663 | AN54: =AL54/AM54 -> 269.33504 | AO54: =$E54*CAPEX!L30 -> 550000 | AP54: =AP51 -> 2246.2729 | AQ54: =AO54/AP54 -> 244.85003
C55: Marketing Expenses and Public Relation | D55: Revenue | E55: 0.02 | F55: =F54 -> 952.639 | G55: =G54 -> 1.1 | H55: =K55+N55+Q55+T55+W55+Z55+AC55+AF55+AI55+AL55+AO55 -> 7.686641e+10 | I55: =I54 -> 952.639 | J55: =M55+P55+S55+V55+Y55+AB55+AE55+AH55+AK55+AN55+AQ55 -> 48471157 | L55: =L54 -> 952.639 | M55: =K55/L55 -> 0 | N55: =$E55*N22 -> 6.2196419e+08 | O55: =O54 -> 952.639 | P55: =N55/O55 -> 652885.5 | Q55: =$E55*Q22 -> 1.5792993e+09 | R55: =R54 -> 1047.9029 | S55: =Q55/R55 -> 1507104.6 | T55: =$E55*T22 -> 3.7378076e+09 | U55: =U54 -> 1152.6932 | V55: =T55/U55 -> 3242673.5 | W55: =$E55*W22 -> 6.5985525e+09 | X55: =X54 -> 1267.9625 | Y55: =W55/X55 -> 5204059.6 | Z55: =$E55*Z22 -> 1.0095914e+10 | AA55: =AA54 -> 1394.7588 | AB55: =Z55/AA55 -> 7238466.1 | AC55: =$E55*AC22 -> 1.5428676e+10 | AD55: =AD54 -> 1534.2346 | AE55: =AC55/AD55 -> 10056269 | AF55: =$E55*AF22 -> 1.3340302e+10 | AG55: =AG54 -> 1687.6581 | AH55: =AF55/AG55 -> 7904623.6 | AI55: =$E55*AI22 -> 1.0432785e+10 | AJ55: =AJ54 -> 1856.4239 | AK55: =AI55/AJ55 -> 5619828.9 | AL55: =$E55*AL22 -> 7.944351e+09 | AM55: =AM54 -> 2042.0663 | AN55: =AL55/AM55 -> 3890349.2 | AO55: =$E55*AO22 -> 7.0867588e+09 | AP55: =AP54 -> 2246.2729 | AQ55: =AO55/AP55 -> 3154896.6
C56: Pension Contribution | D56: Salary of total staff | E56: 0.08 | F56: =F55 -> 952.639 | G56: =G55 -> 1.1 | H56: =K56+N56+Q56+T56+W56+Z56+AC56+AF56+AI56+AL56+AO56 -> 5.7986726e+09 | I56: =I55 -> 952.639 | J56: =M56+P56+S56+V56+Y56+AB56+AE56+AH56+AK56+AN56+AQ56 -> 3819285.2 | L56: =L55 -> 952.639 | M56: =K56/L56 -> 0 | N56: =$E56*(N38+N39+N51) -> 363840000 | O56: =O55 -> 952.639 | P56: =N56/O56 -> 381928.52 | Q56: =$E56*(Q38+Q39+Q51) -> 400224000 | R56: =R55 -> 1047.9029 | S56: =Q56/R56 -> 381928.52 | T56: =$E56*(T38+T39+T51) -> 4.402464e+08 | U56: =U55 -> 1152.6932 | V56: =T56/U56 -> 381928.52 | W56: =$E56*(W38+W39+W51) -> 4.8427104e+08 | X56: =X55 -> 1267.9625 | Y56: =W56/X56 -> 381928.52 | Z56: =$E56*(Z38+Z39+Z51) -> 5.3269814e+08 | AA56: =AA55 -> 1394.7588 | AB56: =Z56/AA56 -> 381928.52 | AC56: =$E56*(AC38+AC39+AC51) -> 5.8596796e+08 | AD56: =AD55 -> 1534.2346 | AE56: =AC56/AD56 -> 381928.52 | AF56: =$E56*(AF38+AF39+AF51) -> 6.4456475e+08 | AG56: =AG55 -> 1687.6581 | AH56: =AF56/AG56 -> 381928.52 | AI56: =$E56*(AI38+AI39+AI51) -> 7.0902123e+08 | AJ56: =AJ55 -> 1856.4239 | AK56: =AI56/AJ56 -> 381928.52 | AL56: =$E56*(AL38+AL39+AL51) -> 7.7992335e+08 | AM56: =AM55 -> 2042.0663 | AN56: =AL56/AM56 -> 381928.52 | AO56: =$E56*(AO38+AO39+AO51) -> 8.5791569e+08 | AP56: =AP55 -> 2246.2729 | AQ56: =AO56/AP56 -> 381928.52
C57: Group Life | D57: Salary of total staff | E57: 0.01 | F57: =F56 -> 952.639 | G57: =G56 -> 1.1 | H57: =K57+N57+Q57+T57+W57+Z57+AC57+AF57+AI57+AL57+AO57 -> 7.2483407e+08 | I57: =I56 -> 952.639 | J57: =M57+P57+S57+V57+Y57+AB57+AE57+AH57+AK57+AN57+AQ57 -> 477410.65 | L57: =L56 -> 952.639 | M57: =K57/L57 -> 0 | N57: =$E57*(N38+N39+N51) -> 45480000 | O57: =O56 -> 952.639 | P57: =N57/O57 -> 47741.065 | Q57: =$E57*(Q38+Q39+Q51) -> 50028000 | R57: =R56 -> 1047.9029 | S57: =Q57/R57 -> 47741.065 | T57: =$E57*(T38+T39+T51) -> 55030800 | U57: =U56 -> 1152.6932 | V57: =T57/U57 -> 47741.065 | W57: =$E57*(W38+W39+W51) -> 60533880 | X57: =X56 -> 1267.9625 | Y57: =W57/X57 -> 47741.065 | Z57: =$E57*(Z38+Z39+Z51) -> 66587268 | AA57: =AA56 -> 1394.7588 | AB57: =Z57/AA57 -> 47741.065 | AC57: =$E57*(AC38+AC39+AC51) -> 73245995 | AD57: =AD56 -> 1534.2346 | AE57: =AC57/AD57 -> 47741.065 | AF57: =$E57*(AF38+AF39+AF51) -> 80570594 | AG57: =AG56 -> 1687.6581 | AH57: =AF57/AG57 -> 47741.065 | AI57: =$E57*(AI38+AI39+AI51) -> 88627654 | AJ57: =AJ56 -> 1856.4239 | AK57: =AI57/AJ57 -> 47741.065 | AL57: =$E57*(AL38+AL39+AL51) -> 97490419 | AM57: =AM56 -> 2042.0663 | AN57: =AL57/AM57 -> 47741.065 | AO57: =$E57*(AO38+AO39+AO51) -> 1.0723946e+08 | AP57: =AP56 -> 2246.2729 | AQ57: =AO57/AP57 -> 47741.065
C58: NSITF | D58: Salary of total staff | E58: 0.01 | F58: =F57 -> 952.639 | G58: =G57 -> 1.1 | H58: =K58+N58+Q58+T58+W58+Z58+AC58+AF58+AI58+AL58+AO58 -> 7.2483407e+08 | I58: =I57 -> 952.639 | J58: =M58+P58+S58+V58+Y58+AB58+AE58+AH58+AK58+AN58+AQ58 -> 477410.65 | L58: =L57 -> 952.639 | M58: =K58/L58 -> 0 | N58: =$E58*(N38+N39+N51) -> 45480000 | O58: =O57 -> 952.639 | P58: =N58/O58 -> 47741.065 | Q58: =$E58*(Q38+Q39+Q51) -> 50028000 | R58: =R57 -> 1047.9029 | S58: =Q58/R58 -> 47741.065 | T58: =$E58*(T38+T39+T51) -> 55030800 | U58: =U57 -> 1152.6932 | V58: =T58/U58 -> 47741.065 | W58: =$E58*(W38+W39+W51) -> 60533880 | X58: =X57 -> 1267.9625 | Y58: =W58/X58 -> 47741.065 | Z58: =$E58*(Z38+Z39+Z51) -> 66587268 | AA58: =AA57 -> 1394.7588 | AB58: =Z58/AA58 -> 47741.065 | AC58: =$E58*(AC38+AC39+AC51) -> 73245995 | AD58: =AD57 -> 1534.2346 | AE58: =AC58/AD58 -> 47741.065 | AF58: =$E58*(AF38+AF39+AF51) -> 80570594 | AG58: =AG57 -> 1687.6581 | AH58: =AF58/AG58 -> 47741.065 | AI58: =$E58*(AI38+AI39+AI51) -> 88627654 | AJ58: =AJ57 -> 1856.4239 | AK58: =AI58/AJ58 -> 47741.065 | AL58: =$E58*(AL38+AL39+AL51) -> 97490419 | AM58: =AM57 -> 2042.0663 | AN58: =AL58/AM58 -> 47741.065 | AO58: =$E58*(AO38+AO39+AO51) -> 1.0723946e+08 | AP58: =AP57 -> 2246.2729 | AQ58: =AO58/AP58 -> 47741.065
C59: NHIS | D59: Salary of total staff | E59: 0.025 | F59: =F58 -> 952.639 | G59: =G58 -> 1.1 | H59: =K59+N59+Q59+T59+W59+Z59+AC59+AF59+AI59+AL59+AO59 -> 1.8120852e+09 | I59: =I58 -> 952.639 | J59: =M59+P59+S59+V59+Y59+AB59+AE59+AH59+AK59+AN59+AQ59 -> 1193526.6 | L59: =L58 -> 952.639 | M59: =K59/L59 -> 0 | N59: =$E59*(N38+N39+N51) -> 113700000 | O59: =O58 -> 952.639 | P59: =N59/O59 -> 119352.66 | Q59: =$E59*(Q38+Q39+Q51) -> 125070000 | R59: =R58 -> 1047.9029 | S59: =Q59/R59 -> 119352.66 | T59: =$E59*(T38+T39+T51) -> 1.37577e+08 | U59: =U58 -> 1152.6932 | V59: =T59/U59 -> 119352.66 | W59: =$E59*(W38+W39+W51) -> 1.513347e+08 | X59: =X58 -> 1267.9625 | Y59: =W59/X59 -> 119352.66 | Z59: =$E59*(Z38+Z39+Z51) -> 1.6646817e+08 | AA59: =AA58 -> 1394.7588 | AB59: =Z59/AA59 -> 119352.66 | AC59: =$E59*(AC38+AC39+AC51) -> 1.8311499e+08 | AD59: =AD58 -> 1534.2346 | AE59: =AC59/AD59 -> 119352.66 | AF59: =$E59*(AF38+AF39+AF51) -> 2.0142649e+08 | AG59: =AG58 -> 1687.6581 | AH59: =AF59/AG59 -> 119352.66 | AI59: =$E59*(AI38+AI39+AI51) -> 2.2156913e+08 | AJ59: =AJ58 -> 1856.4239 | AK59: =AI59/AJ59 -> 119352.66 | AL59: =$E59*(AL38+AL39+AL51) -> 2.4372605e+08 | AM59: =AM58 -> 2042.0663 | AN59: =AL59/AM59 -> 119352.66 | AO59: =$E59*(AO38+AO39+AO51) -> 2.6809865e+08 | AP59: =AP58 -> 2246.2729 | AQ59: =AO59/AP59 -> 119352.66
C60: Board Expenses | D60: N50m per Member | F60: =F59 -> 952.639 | G60: =G59 -> 1.1 | H60: =K60+N60+Q60+T60+W60+Z60+AC60+AF60+AI60+AL60+AO60 -> 1.5937425e+10 | I60: =I59 -> 952.639 | J60: =M60+P60+S60+V60+Y60+AB60+AE60+AH60+AK60+AN60+AQ60 -> 10497156 | L60: =L59 -> 952.639 | M60: =K60/L60 -> 0 | N60: =50000000*20 -> 1000000000 | O60: =O59 -> 952.639 | P60: =N60/O60 -> 1049715.6 | Q60: =N60*G60 -> 1100000000 | R60: =R59 -> 1047.9029 | S60: =Q60/R60 -> 1049715.6 | T60: =Q60*$G60 -> 1210000000 | U60: =U59 -> 1152.6932 | V60: =T60/U60 -> 1049715.6 | W60: =T60*$G60 -> 1331000000 | X60: =X59 -> 1267.9625 | Y60: =W60/X60 -> 1049715.6 | Z60: =W60*$G60 -> 1464100000 | AA60: =AA59 -> 1394.7588 | AB60: =Z60/AA60 -> 1049715.6 | AC60: =Z60*$G60 -> 1.61051e+09 | AD60: =AD59 -> 1534.2346 | AE60: =AC60/AD60 -> 1049715.6 | AF60: =AC60*$G60 -> 1.771561e+09 | AG60: =AG59 -> 1687.6581 | AH60: =AF60/AG60 -> 1049715.6 | AI60: =AF60*$G60 -> 1.9487171e+09 | AJ60: =AJ59 -> 1856.4239 | AK60: =AI60/AJ60 -> 1049715.6 | AL60: =AI60*$G60 -> 2.1435888e+09 | AM60: =AM59 -> 2042.0663 | AN60: =AL60/AM60 -> 1049715.6 | AO60: =AL60*$G60 -> 2.3579477e+09 | AP60: =AP59 -> 2246.2729 | AQ60: =AO60/AP60 -> 1049715.6
C61: Printing & Stationary | D61: N10m per year | F61: =F60 -> 952.639 | G61: =G60 -> 1.1 | H61: =K61+N61+Q61+T61+W61+Z61+AC61+AF61+AI61+AL61+AO61 -> 1.5937425e+08 | I61: =I60 -> 952.639 | J61: =M61+P61+S61+V61+Y61+AB61+AE61+AH61+AK61+AN61+AQ61 -> 104971.56 | L61: =L60 -> 952.639 | M61: =K61/L61 -> 0 | N61: =10000000 -> 10000000 | O61: =O60 -> 952.639 | P61: =N61/O61 -> 10497.156 | Q61: =N61*G61 -> 11000000 | R61: =R60 -> 1047.9029 | S61: =Q61/R61 -> 10497.156 | T61: =Q61*$G61 -> 12100000 | U61: =U60 -> 1152.6932 | V61: =T61/U61 -> 10497.156 | W61: =T61*$G61 -> 13310000 | X61: =X60 -> 1267.9625 | Y61: =W61/X61 -> 10497.156 | Z61: =W61*$G61 -> 14641000 | AA61: =AA60 -> 1394.7588 | AB61: =Z61/AA61 -> 10497.156 | AC61: =Z61*$G61 -> 16105100 | AD61: =AD60 -> 1534.2346 | AE61: =AC61/AD61 -> 10497.156 | AF61: =AC61*$G61 -> 17715610 | AG61: =AG60 -> 1687.6581 | AH61: =AF61/AG61 -> 10497.156 | AI61: =AF61*$G61 -> 19487171 | AJ61: =AJ60 -> 1856.4239 | AK61: =AI61/AJ61 -> 10497.156 | AL61: =AI61*$G61 -> 21435888 | AM61: =AM60 -> 2042.0663 | AN61: =AL61/AM61 -> 10497.156 | AO61: =AL61*$G61 -> 23579477 | AP61: =AP60 -> 2246.2729 | AQ61: =AO61/AP61 -> 10497.156
C62: Vehicle Maintenance | D62: Motor running cost | E62: 0.05 | F62: =F61 -> 952.639 | G62: =G61 -> 1.1 | H62: =K62+N62+Q62+T62+W62+Z62+AC62+AF62+AI62+AL62+AO62 -> 264960000 | I62: =I61 -> 952.639 | J62: =M62+P62+S62+V62+Y62+AB62+AE62+AH62+AK62+AN62+AQ62 -> 278132.64 | L62: =L61 -> 952.639 | M62: =K62/L62 -> 0 | N62: =$E62*N43 -> 264960000 | O62: =O61 -> 952.639 | P62: =N62/O62 -> 278132.64 | Q62: =$E62*Q43 -> 0 | R62: =R61 -> 1047.9029 | S62: =Q62/R62 -> 0 | T62: =$E62*T43 -> 0 | U62: =U61 -> 1152.6932 | V62: =T62/U62 -> 0 | W62: =$E62*W43 -> 0 | X62: =X61 -> 1267.9625 | Y62: =W62/X62 -> 0 | Z62: =$E62*Z43 -> 0 | AA62: =AA61 -> 1394.7588 | AB62: =Z62/AA62 -> 0 | AC62: =$E62*AC43 -> 0 | AD62: =AD61 -> 1534.2346 | AE62: =AC62/AD62 -> 0 | AF62: =$E62*AF43 -> 0 | AG62: =AG61 -> 1687.6581 | AH62: =AF62/AG62 -> 0 | AI62: =$E62*AI43 -> 0 | AJ62: =AJ61 -> 1856.4239 | AK62: =AI62/AJ62 -> 0 | AL62: =$E62*AL43 -> 0 | AM62: =AM61 -> 2042.0663 | AN62: =AL62/AM62 -> 0 | AO62: =$E62*AO43 -> 0 | AP62: =AP61 -> 2246.2729 | AQ62: =AO62/AP62 -> 0
C63: Rent | D63: Estimate | F63: =F62 -> 952.639 | G63: =G62 -> 1.1 | H63: =K63+N63+Q63+T63+W63+Z63+AC63+AF63+AI63+AL63+AO63 -> 7.9687123e+08 | I63: =I62 -> 952.639 | J63: =M63+P63+S63+V63+Y63+AB63+AE63+AH63+AK63+AN63+AQ63 -> 524857.79 | L63: =L62 -> 952.639 | M63: =K63/L63 -> 0 | N63: =50000000 -> 50000000 | O63: =O62 -> 952.639 | P63: =N63/O63 -> 52485.779 | Q63: =N63*G63 -> 55000000 | R63: =R62 -> 1047.9029 | S63: =Q63/R63 -> 52485.779 | T63: =Q63*$G63 -> 60500000 | U63: =U62 -> 1152.6932 | V63: =T63/U63 -> 52485.779 | W63: =T63*$G63 -> 66550000 | X63: =X62 -> 1267.9625 | Y63: =W63/X63 -> 52485.779 | Z63: =W63*$G63 -> 73205000 | AA63: =AA62 -> 1394.7588 | AB63: =Z63/AA63 -> 52485.779 | AC63: =Z63*$G63 -> 80525500 | AD63: =AD62 -> 1534.2346 | AE63: =AC63/AD63 -> 52485.779 | AF63: =AC63*$G63 -> 88578050 | AG63: =AG62 -> 1687.6581 | AH63: =AF63/AG63 -> 52485.779 | AI63: =AF63*$G63 -> 97435855 | AJ63: =AJ62 -> 1856.4239 | AK63: =AI63/AJ63 -> 52485.779 | AL63: =AI63*$G63 -> 1.0717944e+08 | AM63: =AM62 -> 2042.0663 | AN63: =AL63/AM63 -> 52485.779 | AO63: =AL63*$G63 -> 1.1789738e+08 | AP63: =AP62 -> 2246.2729 | AQ63: =AO63/AP63 -> 52485.779
C64: Maintenance - Buildings | D64: Rent | E64: 0.2 | F64: =F63 -> 952.639 | G64: =G63 -> 1.1 | H64: =K64+N64+Q64+T64+W64+Z64+AC64+AF64+AI64+AL64+AO64 -> 1.5937425e+08 | I64: =I63 -> 952.639 | J64: =M64+P64+S64+V64+Y64+AB64+AE64+AH64+AK64+AN64+AQ64 -> 104971.56 | L64: =L63 -> 952.639 | M64: =K64/L64 -> 0 | N64: =$E64*N63 -> 10000000 | O64: =O63 -> 952.639 | P64: =N64/O64 -> 10497.156 | Q64: =$E64*Q63 -> 11000000 | R64: =R63 -> 1047.9029 | S64: =Q64/R64 -> 10497.156 | T64: =$E64*T63 -> 12100000 | U64: =U63 -> 1152.6932 | V64: =T64/U64 -> 10497.156 | W64: =$E64*W63 -> 13310000 | X64: =X63 -> 1267.9625 | Y64: =W64/X64 -> 10497.156 | Z64: =$E64*Z63 -> 14641000 | AA64: =AA63 -> 1394.7588 | AB64: =Z64/AA64 -> 10497.156 | AC64: =$E64*AC63 -> 16105100 | AD64: =AD63 -> 1534.2346 | AE64: =AC64/AD64 -> 10497.156 | AF64: =$E64*AF63 -> 17715610 | AG64: =AG63 -> 1687.6581 | AH64: =AF64/AG64 -> 10497.156 | AI64: =$E64*AI63 -> 19487171 | AJ64: =AJ63 -> 1856.4239 | AK64: =AI64/AJ64 -> 10497.156 | AL64: =$E64*AL63 -> 21435888 | AM64: =AM63 -> 2042.0663 | AN64: =AL64/AM64 -> 10497.156 | AO64: =$E64*AO63 -> 23579477 | AP64: =AP63 -> 2246.2729 | AQ64: =AO64/AP64 -> 10497.156
C65: Maintenance - Equipment | D65: Equipment cost | E65: 0.01 | F65: =F64 -> 952.639 | G65: =G64 -> 1.1 | H65: =K65+N65+Q65+T65+W65+Z65+AC65+AF65+AI65+AL65+AO65 -> 8765583.5 | I65: =I64 -> 952.639 | J65: =M65+P65+S65+V65+Y65+AB65+AE65+AH65+AK65+AN65+AQ65 -> 5773.4357 | L65: =L64 -> 952.639 | M65: =K65/L65 -> 0 | N65: =E65*CAPEX!C30 -> 550000 | O65: =O64 -> 952.639 | P65: =N65/O65 -> 577.34357 | Q65: =N65*G65 -> 605000 | R65: =R64 -> 1047.9029 | S65: =Q65/R65 -> 577.34357 | T65: =Q65*$G65 -> 665500 | U65: =U64 -> 1152.6932 | V65: =T65/U65 -> 577.34357 | W65: =T65*$G65 -> 732050 | X65: =X64 -> 1267.9625 | Y65: =W65/X65 -> 577.34357 | Z65: =W65*$G65 -> 805255 | AA65: =AA64 -> 1394.7588 | AB65: =Z65/AA65 -> 577.34357 | AC65: =Z65*$G65 -> 885780.5 | AD65: =AD64 -> 1534.2346 | AE65: =AC65/AD65 -> 577.34357 | AF65: =AC65*$G65 -> 974358.55 | AG65: =AG64 -> 1687.6581 | AH65: =AF65/AG65 -> 577.34357 | AI65: =AF65*$G65 -> 1071794.4 | AJ65: =AJ64 -> 1856.4239 | AK65: =AI65/AJ65 -> 577.34357 | AL65: =AI65*$G65 -> 1178973.8 | AM65: =AM64 -> 2042.0663 | AN65: =AL65/AM65 -> 577.34357 | AO65: =AL65*$G65 -> 1296871.2 | AP65: =AP64 -> 2246.2729 | AQ65: =AO65/AP65 -> 577.34357
C66: Postage & Communication | D66: Salary Cost | E66: 0.02 | F66: =F65 -> 952.639 | G66: =G65 -> 1.1 | H66: =K66+N66+Q66+T66+W66+Z66+AC66+AF66+AI66+AL66+AO66 -> 1.4496681e+09 | I66: =I65 -> 952.639 | J66: =M66+P66+S66+V66+Y66+AB66+AE66+AH66+AK66+AN66+AQ66 -> 954821.29 | L66: =L65 -> 952.639 | M66: =K66/L66 -> 0 | N66: =E66*(N38+N39+N51) -> 90960000 | O66: =O65 -> 952.639 | P66: =N66/O66 -> 95482.129 | Q66: =N66*G66 -> 1.00056e+08 | R66: =R65 -> 1047.9029 | S66: =Q66/R66 -> 95482.129 | T66: =Q66*$G66 -> 1.100616e+08 | U66: =U65 -> 1152.6932 | V66: =T66/U66 -> 95482.129 | W66: =T66*$G66 -> 1.2106776e+08 | X66: =X65 -> 1267.9625 | Y66: =W66/X66 -> 95482.129 | Z66: =W66*$G66 -> 1.3317454e+08 | AA66: =AA65 -> 1394.7588 | AB66: =Z66/AA66 -> 95482.129 | AC66: =Z66*$G66 -> 1.4649199e+08 | AD66: =AD65 -> 1534.2346 | AE66: =AC66/AD66 -> 95482.129 | AF66: =AC66*$G66 -> 1.6114119e+08 | AG66: =AG65 -> 1687.6581 | AH66: =AF66/AG66 -> 95482.129 | AI66: =AF66*$G66 -> 1.7725531e+08 | AJ66: =AJ65 -> 1856.4239 | AK66: =AI66/AJ66 -> 95482.129 | AL66: =AI66*$G66 -> 1.9498084e+08 | AM66: =AM65 -> 2042.0663 | AN66: =AL66/AM66 -> 95482.129 | AO66: =AL66*$G66 -> 2.1447892e+08 | AP66: =AP65 -> 2246.2729 | AQ66: =AO66/AP66 -> 95482.129
C67: Human Capital Development (ITF Inclusive) | D67: Salary Cost | E67: 0.02 | F67: =F66 -> 952.639 | G67: =G66 -> 1.1 | H67: =K67+N67+Q67+T67+W67+Z67+AC67+AF67+AI67+AL67+AO67 -> 1.4496681e+09 | I67: =I66 -> 952.639 | J67: =M67+P67+S67+V67+Y67+AB67+AE67+AH67+AK67+AN67+AQ67 -> 954821.29 | L67: =L66 -> 952.639 | M67: =K67/L67 -> 0 | N67: =E67*(N38+N39+N51) -> 90960000 | O67: =O66 -> 952.639 | P67: =N67/O67 -> 95482.129 | Q67: =N67*G67 -> 1.00056e+08 | R67: =R66 -> 1047.9029 | S67: =Q67/R67 -> 95482.129 | T67: =Q67*$G67 -> 1.100616e+08 | U67: =U66 -> 1152.6932 | V67: =T67/U67 -> 95482.129 | W67: =T67*$G67 -> 1.2106776e+08 | X67: =X66 -> 1267.9625 | Y67: =W67/X67 -> 95482.129 | Z67: =W67*$G67 -> 1.3317454e+08 | AA67: =AA66 -> 1394.7588 | AB67: =Z67/AA67 -> 95482.129 | AC67: =Z67*$G67 -> 1.4649199e+08 | AD67: =AD66 -> 1534.2346 | AE67: =AC67/AD67 -> 95482.129 | AF67: =AC67*$G67 -> 1.6114119e+08 | AG67: =AG66 -> 1687.6581 | AH67: =AF67/AG67 -> 95482.129 | AI67: =AF67*$G67 -> 1.7725531e+08 | AJ67: =AJ66 -> 1856.4239 | AK67: =AI67/AJ67 -> 95482.129 | AL67: =AI67*$G67 -> 1.9498084e+08 | AM67: =AM66 -> 2042.0663 | AN67: =AL67/AM67 -> 95482.129 | AO67: =AL67*$G67 -> 2.1447892e+08 | AP67: =AP66 -> 2246.2729 | AQ67: =AO67/AP67 -> 95482.129
C68: Government Rates | D68: Revenue | E68: 0.02 | F68: =F67 -> 952.639 | G68: =G67 -> 1.1 | H68: =K68+N68+Q68+T68+W68+Z68+AC68+AF68+AI68+AL68+AO68 -> 7.686641e+10 | I68: =I67 -> 952.639 | J68: =M68+P68+S68+V68+Y68+AB68+AE68+AH68+AK68+AN68+AQ68 -> 48471157 | L68: =L67 -> 952.639 | M68: =K68/L68 -> 0 | N68: =$E68*N22 -> 6.2196419e+08 | O68: =O67 -> 952.639 | P68: =N68/O68 -> 652885.5 | Q68: =$E68*Q22 -> 1.5792993e+09 | R68: =R67 -> 1047.9029 | S68: =Q68/R68 -> 1507104.6 | T68: =$E68*T22 -> 3.7378076e+09 | U68: =U67 -> 1152.6932 | V68: =T68/U68 -> 3242673.5 | W68: =$E68*W22 -> 6.5985525e+09 | X68: =X67 -> 1267.9625 | Y68: =W68/X68 -> 5204059.6 | Z68: =$E68*Z22 -> 1.0095914e+10 | AA68: =AA67 -> 1394.7588 | AB68: =Z68/AA68 -> 7238466.1 | AC68: =$E68*AC22 -> 1.5428676e+10 | AD68: =AD67 -> 1534.2346 | AE68: =AC68/AD68 -> 10056269 | AF68: =$E68*AF22 -> 1.3340302e+10 | AG68: =AG67 -> 1687.6581 | AH68: =AF68/AG68 -> 7904623.6 | AI68: =$E68*AI22 -> 1.0432785e+10 | AJ68: =AJ67 -> 1856.4239 | AK68: =AI68/AJ68 -> 5619828.9 | AL68: =$E68*AL22 -> 7.944351e+09 | AM68: =AM67 -> 2042.0663 | AN68: =AL68/AM68 -> 3890349.2 | AO68: =$E68*AO22 -> 7.0867588e+09 | AP68: =AP67 -> 2246.2729 | AQ68: =AO68/AP68 -> 3154896.6
C69: Travelling Expenses | D69: Revenue | E69: 0.005 | F69: =F68 -> 952.639 | G69: =G68 -> 1.1 | H69: =K69+N69+Q69+T69+W69+Z69+AC69+AF69+AI69+AL69+AO69 -> 1.9216603e+10 | I69: =I68 -> 952.639 | J69: =M69+P69+S69+V69+Y69+AB69+AE69+AH69+AK69+AN69+AQ69 -> 12117789 | L69: =L68 -> 952.639 | M69: =K69/L69 -> 0 | N69: =$E69*N22 -> 1.5549105e+08 | O69: =O68 -> 952.639 | P69: =N69/O69 -> 163221.38 | Q69: =$E69*Q22 -> 3.9482483e+08 | R69: =R68 -> 1047.9029 | S69: =Q69/R69 -> 376776.15 | T69: =$E69*T22 -> 9.344519e+08 | U69: =U68 -> 1152.6932 | V69: =T69/U69 -> 810668.36 | W69: =$E69*W22 -> 1.6496381e+09 | X69: =X68 -> 1267.9625 | Y69: =W69/X69 -> 1301014.9 | Z69: =$E69*Z22 -> 2.5239785e+09 | AA69: =AA68 -> 1394.7588 | AB69: =Z69/AA69 -> 1809616.5 | AC69: =$E69*AC22 -> 3.857169e+09 | AD69: =AD68 -> 1534.2346 | AE69: =AC69/AD69 -> 2514067.2 | AF69: =$E69*AF22 -> 3.3350755e+09 | AG69: =AG68 -> 1687.6581 | AH69: =AF69/AG69 -> 1976155.9 | AI69: =$E69*AI22 -> 2.6081962e+09 | AJ69: =AJ68 -> 1856.4239 | AK69: =AI69/AJ69 -> 1404957.2 | AL69: =$E69*AL22 -> 1.9860877e+09 | AM69: =AM68 -> 2042.0663 | AN69: =AL69/AM69 -> 972587.3 | AO69: =$E69*AO22 -> 1.7716897e+09 | AP69: =AP68 -> 2246.2729 | AQ69: =AO69/AP69 -> 788724.15
C70: Audit Fees | D70: Estimate | F70: =F69 -> 952.639 | G70: =G69 -> 1.1 | H70: =K70+N70+Q70+T70+W70+Z70+AC70+AF70+AI70+AL70+AO70 -> 8.7655835e+08 | I70: =I69 -> 952.639 | J70: =M70+P70+S70+V70+Y70+AB70+AE70+AH70+AK70+AN70+AQ70 -> 577343.57 | L70: =L69 -> 952.639 | M70: =K70/L70 -> 0 | N70: 55000000 | O70: =O69 -> 952.639 | P70: =N70/O70 -> 57734.357 | Q70: =N70*G70 -> 60500000 | R70: =R69 -> 1047.9029 | S70: =Q70/R70 -> 57734.357 | T70: =Q70*$G70 -> 66550000 | U70: =U69 -> 1152.6932 | V70: =T70/U70 -> 57734.357 | W70: =T70*$G70 -> 73205000 | X70: =X69 -> 1267.9625 | Y70: =W70/X70 -> 57734.357 | Z70: =W70*$G70 -> 80525500 | AA70: =AA69 -> 1394.7588 | AB70: =Z70/AA70 -> 57734.357 | AC70: =Z70*$G70 -> 88578050 | AD70: =AD69 -> 1534.2346 | AE70: =AC70/AD70 -> 57734.357 | AF70: =AC70*$G70 -> 97435855 | AG70: =AG69 -> 1687.6581 | AH70: =AF70/AG70 -> 57734.357 | AI70: =AF70*$G70 -> 1.0717944e+08 | AJ70: =AJ69 -> 1856.4239 | AK70: =AI70/AJ70 -> 57734.357 | AL70: =AI70*$G70 -> 1.1789738e+08 | AM70: =AM69 -> 2042.0663 | AN70: =AL70/AM70 -> 57734.357 | AO70: =AL70*$G70 -> 1.2968712e+08 | AP70: =AP69 -> 2246.2729 | AQ70: =AO70/AP70 -> 57734.357
C71: Legal & Secretarial Expenses | D71: Estimate | F71: =F70 -> 952.639 | G71: =G70 -> 1.1 | H71: =K71+N71+Q71+T71+W71+Z71+AC71+AF71+AI71+AL71+AO71 -> 3.9843562e+08 | I71: =I70 -> 952.639 | J71: =M71+P71+S71+V71+Y71+AB71+AE71+AH71+AK71+AN71+AQ71 -> 262428.89 | L71: =L70 -> 952.639 | M71: =K71/L71 -> 0 | N71: 25000000 | O71: =O70 -> 952.639 | P71: =N71/O71 -> 26242.889 | Q71: =N71*G71 -> 27500000 | R71: =R70 -> 1047.9029 | S71: =Q71/R71 -> 26242.889 | T71: =Q71*$G71 -> 30250000 | U71: =U70 -> 1152.6932 | V71: =T71/U71 -> 26242.889 | W71: =T71*$G71 -> 33275000 | X71: =X70 -> 1267.9625 | Y71: =W71/X71 -> 26242.889 | Z71: =W71*$G71 -> 36602500 | AA71: =AA70 -> 1394.7588 | AB71: =Z71/AA71 -> 26242.889 | AC71: =Z71*$G71 -> 40262750 | AD71: =AD70 -> 1534.2346 | AE71: =AC71/AD71 -> 26242.889 | AF71: =AC71*$G71 -> 44289025 | AG71: =AG70 -> 1687.6581 | AH71: =AF71/AG71 -> 26242.889 | AI71: =AF71*$G71 -> 48717928 | AJ71: =AJ70 -> 1856.4239 | AK71: =AI71/AJ71 -> 26242.889 | AL71: =AI71*$G71 -> 53589720 | AM71: =AM70 -> 2042.0663 | AN71: =AL71/AM71 -> 26242.889 | AO71: =AL71*$G71 -> 58948692 | AP71: =AP70 -> 2246.2729 | AQ71: =AO71/AP71 -> 26242.889
C72: Consultancies & Other Professional Fees | D72: Revenue | E72: 0.015 | F72: =F71 -> 952.639 | G72: =G71 -> 1.1 | H72: =K72+N72+Q72+T72+W72+Z72+AC72+AF72+AI72+AL72+AO72 -> 5.7649808e+10 | I72: =I71 -> 952.639 | J72: =M72+P72+S72+V72+Y72+AB72+AE72+AH72+AK72+AN72+AQ72 -> 36353367 | L72: =L71 -> 952.639 | M72: =K72/L72 -> 0 | N72: =$E72*N22 -> 4.6647314e+08 | O72: =O71 -> 952.639 | P72: =N72/O72 -> 489664.13 | Q72: =$E72*Q22 -> 1.1844745e+09 | R72: =R71 -> 1047.9029 | S72: =Q72/R72 -> 1130328.5 | T72: =$E72*T22 -> 2.8033557e+09 | U72: =U71 -> 1152.6932 | V72: =T72/U72 -> 2432005.1 | W72: =$E72*W22 -> 4.9489144e+09 | X72: =X71 -> 1267.9625 | Y72: =W72/X72 -> 3903044.7 | Z72: =$E72*Z22 -> 7.5719355e+09 | AA72: =AA71 -> 1394.7588 | AB72: =Z72/AA72 -> 5428849.6 | AC72: =$E72*AC22 -> 1.1571507e+10 | AD72: =AD71 -> 1534.2346 | AE72: =AC72/AD72 -> 7542201.7 | AF72: =$E72*AF22 -> 1.0005227e+10 | AG72: =AG71 -> 1687.6581 | AH72: =AF72/AG72 -> 5928467.7 | AI72: =$E72*AI22 -> 7.8245885e+09 | AJ72: =AJ71 -> 1856.4239 | AK72: =AI72/AJ72 -> 4214871.6 | AL72: =$E72*AL22 -> 5.9582632e+09 | AM72: =AM71 -> 2042.0663 | AN72: =AL72/AM72 -> 2917761.9 | AO72: =$E72*AO22 -> 5.3150691e+09 | AP72: =AP71 -> 2246.2729 | AQ72: =AO72/AP72 -> 2366172.5
C73: Staff Medical Expenses | D73: Salary Cost | E73: 0.1 | F73: =F72 -> 952.639 | G73: =G72 -> 1.1 | H73: =K73+N73+Q73+T73+W73+Z73+AC73+AF73+AI73+AL73+AO73 -> 7.2483407e+09 | I73: =I72 -> 952.639 | J73: =M73+P73+S73+V73+Y73+AB73+AE73+AH73+AK73+AN73+AQ73 -> 4774106.5 | L73: =L72 -> 952.639 | M73: =K73/L73 -> 0 | N73: =$E73*(N38+N39+N51) -> 454800000 | O73: =O72 -> 952.639 | P73: =N73/O73 -> 477410.65 | Q73: =$E73*(Q38+Q39+Q51) -> 500280000 | R73: =R72 -> 1047.9029 | S73: =Q73/R73 -> 477410.65 | T73: =$E73*(T38+T39+T51) -> 5.50308e+08 | U73: =U72 -> 1152.6932 | V73: =T73/U73 -> 477410.65 | W73: =$E73*(W38+W39+W51) -> 6.053388e+08 | X73: =X72 -> 1267.9625 | Y73: =W73/X73 -> 477410.65 | Z73: =$E73*(Z38+Z39+Z51) -> 6.6587268e+08 | AA73: =AA72 -> 1394.7588 | AB73: =Z73/AA73 -> 477410.65 | AC73: =$E73*(AC38+AC39+AC51) -> 7.3245995e+08 | AD73: =AD72 -> 1534.2346 | AE73: =AC73/AD73 -> 477410.65 | AF73: =$E73*(AF38+AF39+AF51) -> 8.0570594e+08 | AG73: =AG72 -> 1687.6581 | AH73: =AF73/AG73 -> 477410.65 | AI73: =$E73*(AI38+AI39+AI51) -> 8.8627654e+08 | AJ73: =AJ72 -> 1856.4239 | AK73: =AI73/AJ73 -> 477410.65 | AL73: =$E73*(AL38+AL39+AL51) -> 9.7490419e+08 | AM73: =AM72 -> 2042.0663 | AN73: =AL73/AM73 -> 477410.65 | AO73: =$E73*(AO38+AO39+AO51) -> 1.0723946e+09 | AP73: =AP72 -> 2246.2729 | AQ73: =AO73/AP73 -> 477410.65
C77: Stamp Duties etc | F77: =F73 -> 952.639 | H77: =K77+N77+Q77+T77+W77+Z77+AC77+AF77+AI77+AL77+AO77 -> 4.2354288e+09 | I77: =I73 -> 952.639 | J77: =M77+P77+S77+V77+Y77+AB77+AE77+AH77+AK77+AN77+AQ77 -> 2734403.5 | K77: =(SUM(K31:K76)/1000*2) -> 0 | L77: =L73 -> 952.639 | M77: =K77/L77 -> 0 | N77: =(SUM(N31:N76)*1%) -> 1.6308951e+08 | O77: =O73 -> 952.639 | P77: =N77/O77 -> 171197.6 | Q77: =(SUM(Q31:Q76)*1%) -> 1.5723209e+08 | R77: =R73 -> 1047.9029 | S77: =Q77/R77 -> 150044.53 | T77: =(SUM(T31:T76)*1%) -> 2.4911789e+08 | U77: =U73 -> 1152.6932 | V77: =T77/U77 -> 216118.12 | W77: =(SUM(W31:W76)*1%) -> 3.6478383e+08 | X77: =X73 -> 1267.9625 | Y77: =W77/X77 -> 287692.92 | Z77: =(SUM(Z31:Z76)*1%) -> 5.0253264e+08 | AA77: =AA73 -> 1394.7588 | AB77: =Z77/AA77 -> 360300.76 | AC77: =(SUM(AC31:AC76)*1%) -> 6.7262331e+08 | AD77: =AD73 -> 1534.2346 | AE77: =AC77/AD77 -> 438409.68 | AF77: =(SUM(AF31:AF76)*1%) -> 6.2109068e+08 | AG77: =AG73 -> 1687.6581 | AH77: =AF77/AG77 -> 368019.26 | AI77: =(SUM(AI31:AI76)*1%) -> 5.4609561e+08 | AJ77: =AJ73 -> 1856.4239 | AK77: =AI77/AJ77 -> 294165.36 | AL77: =(SUM(AL31:AL76)*1%) -> 4.8489609e+08 | AM77: =AM73 -> 2042.0663 | AN77: =AL77/AM77 -> 237453.65 | AO77: =(SUM(AO31:AO76)*1%) -> 4.7396717e+08 | AP77: =AP73 -> 2246.2729 | AQ77: =AO77/AP77 -> 211001.59
C78: Tax | F78: =F70 -> 952.639 | G78: =G77 -> 0 | H78: =K78+N78+Q78+T78+W78+Z78+AC78+AF78+AI78+AL78+AO78 -> 2.3053729e+11 | I78: =I77 -> 952.639 | J78: =M78+P78+S78+V78+Y78+AB78+AE78+AH78+AK78+AN78+AQ78 -> 1.3332898e+08 | L78: =L77 -> 952.639 | M78: =K78/L78 -> 0 | O78: =O77 -> 952.639 | P78: =N78/O78 -> 0 | Q78: ='Income Statement'!K70 -> 0 | R78: =R77 -> 1047.9029 | S78: =Q78/R78 -> 0 | T78: ='Income Statement'!N70 -> 4.8008048e+09 | U78: =U77 -> 1152.6932 | V78: =T78/U78 -> 4164859.2 | W78: ='Income Statement'!Q70 -> 1.4889161e+10 | X78: =X77 -> 1267.9625 | Y78: =W78/X78 -> 11742588 | Z78: ='Income Statement'!T70 -> 2.0267889e+10 | AA78: =AA77 -> 1394.7588 | AB78: =Z78/AA78 -> 14531466 | AC78: ='Income Statement'!W70 -> 2.5734932e+10 | AD78: =AD77 -> 1534.2346 | AE78: =AC78/AD78 -> 16773792 | AF78: ='Income Statement'!Z70 -> 5.6803947e+10 | AG78: =AG77 -> 1687.6581 | AH78: =AF78/AG78 -> 33658445 | AI78: ='Income Statement'!AC70 -> 2.9445197e+10 | AJ78: =AJ77 -> 1856.4239 | AK78: =AI78/AJ78 -> 15861246 | AL78: ='Income Statement'!AF70 -> 3.6105613e+10 | AM78: =AM77 -> 2042.0663 | AN78: =AL78/AM78 -> 17680921 | AO78: ='Income Statement'!AI70 -> 4.248974e+10 | AP78: =AP77 -> 2246.2729 | AQ78: =AO78/AP78 -> 18915662
H81: =K81+N81+Q81+T81+W81+Z81+AC81+AF81+AI81+AL81+AO81 -> 0 | J81: =M81+P81+S81+V81+Y81+AB81+AE81+AH81+AK81+AN81+AQ81 -> 0
C82: FINANCING ACTIVITIES
C83: Loan Interest Payment
C85: Dividend | F85: =F77 -> 952.639 | G85: =G84 -> 0 | H85: =K85+N85+Q85+T85+W85+Z85+AC85+AF85+AI85+AL85+AO85 -> 1.1651437e+10 | I85: =I78 -> 952.639 | J85: =M85+P85+S85+V85+Y85+AB85+AE85+AH85+AK85+AN85+AQ85 -> 6719668.5 | L85: =L78 -> 952.639 | M85: =K85/L85 -> 0 | O85: =O78 -> 952.639 | P85: =N85/O85 -> 0 | Q85: =-'Income Statement'!K73 -> -50076450 | R85: =R78 -> 1047.9029 | S85: =Q85/R85 -> -47787.3 | T85: =-'Income Statement'!N73 -> 2.4367721e+08 | U85: =U78 -> 1152.6932 | V85: =T85/U85 -> 211398.15 | W85: =-'Income Statement'!Q73 -> 7.5573771e+08 | X85: =X78 -> 1267.9625 | Y85: =W85/X85 -> 596025.28 | Z85: =-'Income Statement'!T73 -> 1.0287489e+09 | AA85: =AA78 -> 1394.7588 | AB85: =Z85/AA85 -> 737581.98 | AC85: =-'Income Statement'!W73 -> 1.3062428e+09 | AD85: =AD78 -> 1534.2346 | AE85: =AC85/AD85 -> 851397 | AF85: =-'Income Statement'!Z73 -> 2.8832307e+09 | AG85: =AG78 -> 1687.6581 | AH85: =AF85/AG85 -> 1708421.1 | AI85: =-'Income Statement'!AC73 -> 1.4945668e+09 | AJ85: =AJ78 -> 1856.4239 | AK85: =AI85/AJ85 -> 805078.42 | AL85: =-'Income Statement'!AF73 -> 1.8326334e+09 | AM85: =AM78 -> 2042.0663 | AN85: =AL85/AM85 -> 897440.7 | AO85: =-'Income Statement'!AI73 -> 2.1566762e+09 | AP85: =AP78 -> 2246.2729 | AQ85: =AO85/AP85 -> 960113.16
C87: Bank Charges | F87: =F85 -> 952.639 | H87: =K87+N87+Q87+T87+W87+Z87+AC87+AF87+AI87+AL87+AO87 -> 1.3166312e+09 | I87: =I85 -> 952.639 | J87: =M87+P87+S87+V87+Y87+AB87+AE87+AH87+AK87+AN87+AQ87 -> 819007.46 | K87: =(SUM(K35:K83)/1000*2) -> 0 | L87: =L85 -> 952.639 | M87: =K87/L87 -> 0 | N87: =(SUM(N35:N83)/1000*2) -> 32944081 | O87: =O85 -> 952.639 | P87: =N87/O87 -> 34581.915 | Q87: =(SUM(Q35:Q83)/1000*2) -> 31760883 | R87: =R85 -> 1047.9029 | S87: =Q87/R87 -> 30308.994 | T87: =(SUM(T35:T83)/1000*2) -> 59923423 | U87: =U85 -> 1152.6932 | V87: =T87/U87 -> 51985.579 | W87: =(SUM(W35:W83)/1000*2) -> 1.0346466e+08 | X87: =X85 -> 1267.9625 | Y87: =W87/X87 -> 81599.145 | Z87: =(SUM(Z35:Z83)/1000*2) -> 1.4204737e+08 | AA87: =AA85 -> 1394.7588 | AB87: =Z87/AA87 -> 101843.69 | AC87: =(SUM(AC35:AC83)/1000*2) -> 1.8733977e+08 | AD87: =AD85 -> 1534.2346 | AE87: =AC87/AD87 -> 122106.34 | AF87: =(SUM(AF35:AF83)/1000*2) -> 2.3906821e+08 | AG87: =AG85 -> 1687.6581 | AH87: =AF87/AG87 -> 141656.78 | AI87: =(SUM(AI35:AI83)/1000*2) -> 1.6920171e+08 | AJ87: =AJ85 -> 1856.4239 | AK87: =AI87/AJ87 -> 91143.895 | AL87: =(SUM(AL35:AL83)/1000*2) -> 1.7016024e+08 | AM87: =AM85 -> 2042.0663 | AN87: =AL87/AM87 -> 83327.479 | AO87: =(SUM(AO35:AO83)/1000*2) -> 1.8072085e+08 | AP87: =AP85 -> 2246.2729 | AQ87: =AO87/AP87 -> 80453.647
C88: TOTAL CASH OUTFLOWS | H88: =SUM(H26:H87) -> 6.7133866e+11 | J88: =SUM(J26:J87) -> 4.1710014e+08 | K88: =SUM(K26:K87) -> 55000000 | M88: =SUM(M26:M87) -> 57734.357 | N88: =SUM(N26:N87) -> 1.6504984e+10 | P88: =SUM(P26:P87) -> 17325539 | Q88: =SUM(Q26:Q87) -> 1.5862126e+10 | S88: =SUM(S26:S87) -> 15137019 | T88: =SUM(T26:T87) -> 3.0265312e+10 | V88: =SUM(V26:V87) -> 26256173 | W88: =SUM(W26:W87) -> 5.259153e+10 | Y88: =SUM(Y26:Y87) -> 41477197 | Z88: =SUM(Z26:Z87) -> 7.2194482e+10 | AB88: =SUM(AB26:AB87) -> 51761268 | AC88: =SUM(AC26:AC87) -> 9.5163469e+10 | AE88: =SUM(AE26:AE87) -> 62026672 | AF88: =SUM(AF26:AF87) -> 1.226564e+11 | AH88: =SUM(AH26:AH87) -> 72678468 | AI88: =SUM(AI26:AI87) -> 8.6264622e+10 | AK88: =SUM(AK26:AK87) -> 46468170 | AL88: =SUM(AL26:AL87) -> 8.7082912e+10 | AN88: =SUM(AN26:AN87) -> 42644508 | AO88: =SUM(AO26:AO87) -> 9.2697821e+10 | AQ88: =SUM(AQ26:AQ87) -> 41267390
C90: Asset Repayments- Long term finance | F90: =F89 -> 0 | H90: =K90+N90+Q90+T90+W90+Z90+AC90+AF90+AI90+AL90+AO90 -> 1.5875058e+12 | I90: =I87 -> 952.639 | J90: =M90+P90+S90+V90+Y90+AB90+AE90+AH90+AK90+AN90+AQ90 -> 847424000 | L90: =L87 -> 952.639 | M90: =K90/L90 -> 0 | O90: =O87 -> 952.639 | P90: =N90/O90 -> 0 | R90: =R87 -> 1047.9029 | S90: =Q90/R90 -> 0 | U90: =U87 -> 1152.6932 | V90: =T90/U90 -> 0 | X90: =X87 -> 1267.9625 | Y90: =W90/X90 -> 0 | AA90: =AA87 -> 1394.7588 | AB90: =Z90/AA90 -> 0 | AC90: ='Facility Repayment Plan'!H30 -> 2.6002945e+11 | AD90: =AD87 -> 1534.2346 | AE90: =AC90/AD90 -> 169484800 | AF90: ='Facility Repayment Plan'!I30 -> 2.860324e+11 | AG90: =AG87 -> 1687.6581 | AH90: =AF90/AG90 -> 169484800 | AI90: ='Facility Repayment Plan'!J30 -> 3.1463564e+11 | AJ90: =AJ87 -> 1856.4239 | AK90: =AI90/AJ90 -> 1.694848e+08 | AL90: ='Facility Repayment Plan'!K30 -> 3.460992e+11 | AM90: =AM87 -> 2042.0663 | AN90: =AL90/AM90 -> 169484800 | AO90: ='Facility Repayment Plan'!L30 -> 3.8070912e+11 | AP90: =AP87 -> 2246.2729 | AQ90: =AO90/AP90 -> 169484800
C91: NET CASHFLOW | H91: =H22-H88-H90-H89 -> -2.19069e+11 | J91: =J22-J88-J90-J89 -> #DIV/0! | K91: =K22-K88-K90-K89 -> 445000000 | M91: =M22-M88-M90-M89 -> #DIV/0! | N91: =N22-N88-N90-N89 -> 1.4593225e+10 | P91: =P22-P88-P90-P89 -> #DIV/0! | Q91: =Q22-Q88-Q90-Q89 -> 6.3102839e+10 | S91: =S22-S88-S90-S89 -> #DIV/0! | T91: =T22-T88-T90-T89 -> 1.5662507e+11 | V91: =V22-V88-V90-V89 -> #DIV/0! | W91: =W22-W88-W90-W89 -> 2.773361e+11 | Y91: =Y22-Y88-Y90-Y89 -> #DIV/0! | Z91: =Z22-Z88-Z90-Z89 -> 4.3260122e+11 | AB91: =AB22-AB88-AB90-AB89 -> 3.1016204e+08 | AC91: =AC22-AC88-AC90-AC89 -> 4.1624089e+11 | AE91: =AE22-AE88-AE90-AE89 -> 2.7130198e+08 | AF91: =AF22-AF88-AF90-AF89 -> 2.583263e+11 | AH91: =AH22-AH88-AH90-AH89 -> 1.5306791e+08 | AI91: =AI22-AI88-AI90-AI89 -> 1.2073898e+11 | AK91: =AK22-AK88-AK90-AK89 -> 65038473 | AL91: =AL22-AL88-AL90-AL89 -> -3.5964561e+10 | AN91: =AN22-AN88-AN90-AN89 -> -17611848 | AO91: =AO22-AO88-AO90-AO89 -> -1.19069e+11 | AQ91: =AQ22-AQ88-AQ90-AQ89 -> -53007360
C94: Debt Service Coverage Ratio (Principal + Interest) | H94: =(H83+H89)/(H91+(H83+H89)) -> 0 | J94: =(J83+J89)/(J91+(J83+J89)) -> #DIV/0! | N94: =(N83+N89)/(N91-(N83-N89)) -> 0 | P94: =(P83+P89)/(P91-(P83-P89)) -> #DIV/0! | Q94: =(Q83+Q89)/(Q91+(Q83+Q89)) -> 0 | S94: =(S83+S89)/(S91+(S83+S89)) -> #DIV/0! | T94: =(T83+T89)/(T91+(T83+T89)) -> 0 | V94: =(V83+V89)/(V91+(V83+V89)) -> #DIV/0! | W94: =(W83+W89)/(W91+(W83+W89)) -> 0 | Y94: =(Y83+Y89)/(Y91+(Y83+Y89)) -> #DIV/0! | Z94: =(Z83+Z89)/(Z91+(Z83+Z89)) -> 0 | AB94: =(AB83+AB89)/(AB91+(AB83+AB89)) -> 0 | AC94: =(AC83+AC89)/(AC91+(AC83+AC89)) -> 0 | AE94: =(AE83+AE89)/(AE91+(AE83+AE89)) -> 0 | AF94: =(AF83+AF89)/(AF91+(AF83+AF89)) -> 0 | AH94: =(AH83+AH89)/(AH91+(AH83+AH89)) -> 0 | AI94: =(AI83+AI89)/(AI91+(AI83+AI89)) -> 0 | AK94: =(AK83+AK89)/(AK91+(AK83+AK89)) -> 0 | AL94: =(AL83+AL89)/(AL91+(AL83+AL89)) -> 0 | AN94: =(AN83+AN89)/(AN91+(AN83+AN89)) -> 0 | AO94: =(AO83+AO89)/(AO91+(AO83+AO89)) -> 0 | AQ94: =(AQ83+AQ89)/(AQ91+(AQ83+AQ89)) -> 0
C96: Free Cash Flow Debt | H96: =H22-SUM(H26:H82)-H87 -> 1.3800882e+12 | J96: =J22-SUM(J26:J82)-J87 -> #DIV/0! | N96: =N22-SUM(N26:N82)-N87 -> 1.4593225e+10 | P96: =P22-SUM(P26:P82)-P87 -> #DIV/0! | Q96: =Q22-SUM(Q26:Q82)-Q87 -> 6.3052763e+10 | S96: =S22-SUM(S26:S82)-S87 -> #DIV/0! | T96: =T22-SUM(T26:T82)-T87 -> 1.5686875e+11 | V96: =V22-SUM(V26:V82)-V87 -> #DIV/0! | W96: =W22-SUM(W26:W82)-W87 -> 2.7809183e+11 | Y96: =Y22-SUM(Y26:Y82)-Y87 -> #DIV/0! | Z96: =Z22-SUM(Z26:Z82)-Z87 -> 4.3362997e+11 | AB96: =AB22-SUM(AB26:AB82)-AB87 -> 3.1089962e+08 | AC96: =AC22-SUM(AC26:AC82)-AC87 -> 6.7757658e+11 | AE96: =AE22-SUM(AE26:AE82)-AE87 -> 4.4163817e+08 | AF96: =AF22-SUM(AF26:AF82)-AF87 -> 5.4724193e+11 | AH96: =AH22-SUM(AH26:AH82)-AH87 -> 3.2426114e+08 | AI96: =AI22-SUM(AI26:AI82)-AI87 -> 4.3686918e+11 | AK96: =AK22-SUM(AK26:AK82)-AK87 -> 2.3532835e+08 | AL96: =AL22-SUM(AL26:AL82)-AL87 -> 3.1196727e+11 | AN96: =AN22-SUM(AN26:AN82)-AN87 -> 1.5277039e+08 | AO96: =AO22-SUM(AO26:AO82)-AO87 -> 2.637968e+11 | AQ96: =AQ22-SUM(AQ26:AQ82)-AQ87 -> 1.1743755e+08
C97: Debt (Prinipal + Interest) | H97: =H83+H89 -> 0 | J97: =J83+J89 -> 0 | N97: =N83+N89 -> 0 | P97: =P83+P89 -> 0 | Q97: =Q83+Q89 -> 0 | S97: =S83+S89 -> 0 | T97: =T83+T89 -> 0 | V97: =V83+V89 -> 0 | W97: =W83+W89 -> 0 | Y97: =Y83+Y89 -> 0 | Z97: =Z83+Z89 -> 0 | AB97: =AB83+AB89 -> 0 | AC97: =AC83+AC89 -> 0 | AE97: =AE83+AE89 -> 0 | AF97: =AF83+AF89 -> 0 | AH97: =AH83+AH89 -> 0 | AI97: =AI83+AI89 -> 0 | AK97: =AK83+AK89 -> 0 | AL97: =AL83+AL89 -> 0 | AN97: =AN83+AN89 -> 0 | AO97: =AO83+AO89 -> 0 | AQ97: =AQ83+AQ89 -> 0
C98: Debt Service Coverage Ratio (Principal + Interest) | H98: =H97/H96 -> 0 | J98: =J97/J96 -> #DIV/0! | N98: =N97/N96 -> 0 | P98: =P97/P96 -> #DIV/0! | Q98: =Q97/Q96 -> 0 | S98: =S97/S96 -> #DIV/0! | T98: =T97/T96 -> 0 | V98: =V97/V96 -> #DIV/0! | W98: =W97/W96 -> 0 | Y98: =Y97/Y96 -> #DIV/0! | Z98: =Z97/Z96 -> 0 | AB98: =AB97/AB96 -> 0 | AC98: =AC97/AC96 -> 0 | AE98: =AE97/AE96 -> 0 | AF98: =AF97/AF96 -> 0 | AH98: =AH97/AH96 -> 0 | AI98: =AI97/AI96 -> 0 | AK98: =AK97/AK96 -> 0 | AL98: =AL97/AL96 -> 0 | AN98: =AN97/AN96 -> 0 | AO98: =AO97/AO96 -> 0 | AQ98: =AQ97/AQ96 -> 0

Sheet Fleet Inventory
B2: Fleet Inventory
B5: Taxi | C5: Year 1 | D5: Year 2 | E5: Year 3 | F5: Year 4 | G5: Year 5 | H5: Year 6 | I5: Year 7 | J5: Year 8 | K5: Year 9 | L5: Year 10 | M5: Total
C6: Units | D6: Units | E6: Units | F6: Units | G6: Units | H6: Units | I6: Units | J6: Units | K6: Units | L6: Units | M6: Units
B7: Opening | D7: =C10 -> 2000 | E7: =D10 -> 4000 | F7: =E10 -> 6000 | G7: =F10 -> 8000 | H7: =G10 -> 10000 | I7: =H10 -> 10000 | J7: =I10 -> 10000 | K7: =J10 -> 10000 | L7: =K10 -> 10000 | M7: =C7 -> 0
B8: Addition | C8: ='Facility Repayment Plan'!C13 -> 2000 | D8: ='Facility Repayment Plan'!H13 -> 2000 | E8: ='Facility Repayment Plan'!M13 -> 2000 | F8: ='Facility Repayment Plan'!R13 -> 2000 | G8: ='Facility Repayment Plan'!W13 -> 2000 | H8: ='Facility Repayment Plan'!AB13 -> 0 | I8: ='Facility Repayment Plan'!AG13 -> 0 | J8: ='Facility Repayment Plan'!AL13 -> 0 | K8: ='Facility Repayment Plan'!AQ13 -> 0 | L8: ='Facility Repayment Plan'!AV13 -> 0 | M8: =SUM(C8:L8) -> 10000
B9: Disposal | M9: =SUM(C9:L9) -> 0
B10: Closing | C10: =C7+C8-C9 -> 2000 | D10: =D7+D8-D9 -> 4000 | E10: =E7+E8-E9 -> 6000 | F10: =F7+F8-F9 -> 8000 | G10: =G7+G8-G9 -> 10000 | H10: =H7+H8-H9 -> 10000 | I10: =I7+I8-I9 -> 10000 | J10: =J7+J8-J9 -> 10000 | ... L10: =L7+L8-L9 -> 10000 | M10: =L10 -> 10000
B14: Bus | C14: Year 1 | D14: Year 2 | E14: Year 3 | F14: Year 4 | G14: Year 5 | H14: Year 6 | I14: Year 7 | J14: Year 8 | K14: Year 9 | L14: Year 10 | M14: Total
C15: Units | D15: Units | E15: Units | F15: Units | G15: Units | H15: Units | I15: Units | J15: Units | K15: Units | L15: Units | M15: Units
B16: Opening | D16: =C19 -> 400 | E16: =D19 -> 800 | F16: =E19 -> 1200 | G16: =F19 -> 1600 | H16: =G19 -> 2000 | I16: =H19 -> 2000 | J16: =I19 -> 2000 | K16: =J19 -> 2000 | L16: =K19 -> 2000 | M16: =C16 -> 0
B17: Addition | C17: ='Facility Repayment Plan'!C14 -> 400 | D17: ='Facility Repayment Plan'!H14 -> 400 | E17: ='Facility Repayment Plan'!M14 -> 400 | F17: ='Facility Repayment Plan'!R14 -> 400 | G17: ='Facility Repayment Plan'!W14 -> 400 | H17: ='Facility Repayment Plan'!AB14 -> 0 | I17: ='Facility Repayment Plan'!AG14 -> 0 | J17: ='Facility Repayment Plan'!AL14 -> 0 | K17: ='Facility Repayment Plan'!AQ14 -> 0 | L17: ='Facility Repayment Plan'!AV14 -> 0 | M17: =SUM(C17:L17) -> 2000
B18: Disposal | M18: =SUM(C18:L18) -> 0
B19: Closing | C19: =C16+C17-C18 -> 400 | D19: =D16+D17-D18 -> 800 | E19: =E16+E17-E18 -> 1200 | F19: =F16+F17-F18 -> 1600 | G19: =G16+G17-G18 -> 2000 | H19: =H16+H17-H18 -> 2000 | I19: =I16+I17-I18 -> 2000 | J19: =J16+J17-J18 -> 2000 | ... L19: =L16+L17-L18 -> 2000 | M19: =L19 -> 2000

Sheet Revenue Schedule
B2: Revenue Schedule
B3: Cars- Deployment and Passanger Efficiency Analysis
H4: Year 1 | AG4: Year 2 | BF4: Year 3 | CE4: Year 4 | DD4: Year 5 | EC4: Year 6 | FB4: Year 7 | GA4: Year 8 | GZ4: Year 9 | HY4: Year 10
O6: Daily | T6: Weekly | X6: Monthly | AB6: Annual | AN6: Daily | AS6: Weekly | AW6: Monthly | BA6: Annual | BM6: Daily | BR6: Weekly | BV6: Monthly | BZ6: Annual | CL6: Daily | CQ6: Weekly | CU6: Monthly | CY6: Annual | DK6: Daily | DP6: Weekly | DT6: Monthly | DX6: Annual | EJ6: Daily | EO6: Weekly | ES6: Monthly | EW6: Annual | FI6: Daily | FN6: Weekly | FR6: Monthly | FV6: Annual | GH6: Daily | GM6: Weekly | GQ6: Monthly | GU6: Annual | HG6: Daily | HL6: Weekly | HP6: Monthly | HT6: Annual | IF6: Daily | IK6: Weekly | IO6: Monthly | IS6: Annual
B7: Shift | C7: Hours | D7: Timing | E7: Location | F7: Season | G7: Timing | H7: Available QTY | I7: Fleet Allocation Per Location | K7: Deployment Efficiency | M7: Std Occupancy | O7: Average Occupancy Utilisation | Q7: Minimum Daily Trips | R7: Fare - NGN | T7: Days in Week | U7: Minimum Daily Trips | V7: Average Capacity Utilisation | W7: Fare- NGN | X7: Days in Month | Y7: Minimum Daily Trips | Z7: Average Capacity Utilisation | AA7: Fare- NGN | AB7: Days in Month | AC7: Minimum Daily Trips | AD7: Average Capacity Utilisation | AE7: Fare- NGN | AG7: Available QTY | AH7: Fleet Allocation Per Location | AJ7: Deployment Efficiency | AL7: Std Occupancy | AN7: Average Occupancy Utilisation | AP7: Minimum Daily Trips | AQ7: Fare - NGN | AS7: Days in Week | AT7: Minimum Daily Trips | AU7: Average Capacity Utilisation | AV7: Fare- NGN | AW7: Days in Month | AX7: Minimum Daily Trips | AY7: Average Capacity Utilisation | AZ7: Fare- NGN | BA7: Days in Month | BB7: Minimum Daily Trips | BC7: Average Capacity Utilisation | BD7: Fare- NGN | BF7: Available QTY | BG7: Fleet Allocation Per Location | BI7: Deployment Efficiency | BK7: Std Occupancy | BM7: Average Occupancy Utilisation | BO7: Minimum Daily Trips | BP7: Fare - NGN | BR7: Days in Week | BS7: Minimum Daily Trips | BT7: Average Capacity Utilisation | BU7: Fare- NGN | BV7: Days in Month | BW7: Minimum Daily Trips | BX7: Average Capacity Utilisation | BY7: Fare- NGN | BZ7: Days in Month | CA7: Minimum Daily Trips | CB7: Average Capacity Utilisation | CC7: Fare- NGN | CE7: Available QTY | CF7: Fleet Allocation Per Location | CH7: Deployment Efficiency | CJ7: Std Occupancy | CL7: Average Occupancy Utilisation | CN7: Minimum Daily Trips | CO7: Fare - NGN | CQ7: Days in Week | CR7: Minimum Daily Trips | CS7: Average Capacity Utilisation | CT7: Fare- NGN | CU7: Days in Month | CV7: Minimum Daily Trips | CW7: Average Capacity Utilisation | CX7: Fare- NGN | CY7: Days in Month | CZ7: Minimum Daily Trips | DA7: Average Capacity Utilisation | DB7: Fare- NGN | DD7: Available QTY | DE7: Fleet Allocation Per Location | DG7: Deployment Efficiency | DI7: Std Occupancy | DK7: Average Occupancy Utilisation | DM7: Minimum Daily Trips | DN7: Fare - NGN | DP7: Days in Week | DQ7: Minimum Daily Trips | DR7: Average Capacity Utilisation | DS7: Fare- NGN | DT7: Days in Month | DU7: Minimum Daily Trips | DV7: Average Capacity Utilisation | DW7: Fare- NGN | DX7: Days in Month | DY7: Minimum Daily Trips | DZ7: Average Capacity Utilisation | EA7: Fare- NGN | EC7: Available QTY | ED7: Fleet Allocation Per Location | EF7: Deployment Efficiency | EH7: Std Occupancy | EJ7: Average Occupancy Utilisation | EL7: Minimum Daily Trips | EM7: Fare - NGN | EO7: Days in Week | EP7: Minimum Daily Trips | EQ7: Average Capacity Utilisation | ER7: Fare- NGN | ES7: Days in Month | ET7: Minimum Daily Trips | EU7: Average Capacity Utilisation | EV7: Fare- NGN | EW7: Days in Month | EX7: Minimum Daily Trips | EY7: Average Capacity Utilisation | EZ7: Fare- NGN | FB7: Available QTY | FC7: Fleet Allocation Per Location | FE7: Deployment Efficiency | FG7: Std Occupancy | FI7: Average Occupancy Utilisation | FK7: Minimum Daily Trips | FL7: Fare - NGN | FN7: Days in Week | FO7: Minimum Daily Trips | FP7: Average Capacity Utilisation | FQ7: Fare- NGN | FR7: Days in Month | FS7: Minimum Daily Trips | FT7: Average Capacity Utilisation | FU7: Fare- NGN | FV7: Days in Month | FW7: Minimum Daily Trips | FX7: Average Capacity Utilisation | FY7: Fare- NGN | GA7: Available QTY | GB7: Fleet Allocation Per Location | GD7: Deployment Efficiency | GF7: Std Occupancy | GH7: Average Occupancy Utilisation | GJ7: Minimum Daily Trips | GK7: Fare - NGN | GM7: Days in Week | GN7: Minimum Daily Trips | GO7: Average Capacity Utilisation | GP7: Fare- NGN | GQ7: Days in Month | GR7: Minimum Daily Trips | GS7: Average Capacity Utilisation | GT7: Fare- NGN | GU7: Days in Month | GV7: Minimum Daily Trips | GW7: Average Capacity Utilisation | GX7: Fare- NGN | GZ7: Available QTY | HA7: Fleet Allocation Per Location | HC7: Deployment Efficiency | HE7: Std Occupancy | HG7: Average Occupancy Utilisation | HI7: Minimum Daily Trips | HJ7: Fare - NGN | HL7: Days in Week | HM7: Minimum Daily Trips | HN7: Average Capacity Utilisation | HO7: Fare- NGN | HP7: Days in Month | HQ7: Minimum Daily Trips | HR7: Average Capacity Utilisation | HS7: Fare- NGN | HT7: Days in Month | HU7: Minimum Daily Trips | HV7: Average Capacity Utilisation | HW7: Fare- NGN | HY7: Available QTY | HZ7: Fleet Allocation Per Location | IB7: Deployment Efficiency | ID7: Std Occupancy | IF7: Average Occupancy Utilisation | IH7: Minimum Daily Trips | II7: Fare - NGN | IK7: Days in Week | IL7: Minimum Daily Trips | IM7: Average Capacity Utilisation | IN7: Fare- NGN | IO7: Days in Month | IP7: Minimum Daily Trips | IQ7: Average Capacity Utilisation | IR7: Fare- NGN | IS7: Days in Month | IT7: Minimum Daily Trips | IU7: Average Capacity Utilisation | IV7: Fare- NGN
I8: Rate | J8: QTY | K8: Rate | L8: Efficiency | M8: Unit | N8: Total | O8: Rate | P8: Pax | Q8: No | R8: Unit | S8: Total | T8: Days | U8: No | V8: Pax | X8: Days | Y8: No | Z8: Pax | AB8: Days | AC8: No | AD8: Pax | AH8: Rate | AI8: QTY | AJ8: Rate | AK8: Efficiency | AL8: Unit | AM8: Total | AN8: Rate | AO8: Pax | AP8: No | AQ8: Unit | AR8: Total | AS8: Days | AT8: No | AU8: Pax | AW8: Days | AX8: No | AY8: Pax | BA8: Days | BB8: No | BC8: Pax | BG8: Rate | BH8: QTY | BI8: Rate | BJ8: Efficiency | BK8: Unit | BL8: Total | BM8: Rate | BN8: Pax | BO8: No | BP8: Unit | BQ8: Total | BR8: Days | BS8: No | BT8: Pax | BV8: Days | BW8: No | BX8: Pax | BZ8: Days | CA8: No | CB8: Pax | CF8: Rate | CG8: QTY | CH8: Rate | CI8: Efficiency | CJ8: Unit | CK8: Total | CL8: Rate | CM8: Pax | CN8: No | CO8: Unit | CP8: Total | CQ8: Days | CR8: No | CS8: Pax | CU8: Days | CV8: No | CW8: Pax | CY8: Days | CZ8: No | DA8: Pax | DE8: Rate | DF8: QTY | DG8: Rate | DH8: Efficiency | DI8: Unit | DJ8: Total | DK8: Rate | DL8: Pax | DM8: No | DN8: Unit | DO8: Total | DP8: Days | DQ8: No | DR8: Pax | DT8: Days | DU8: No | DV8: Pax | DX8: Days | DY8: No | DZ8: Pax | ED8: Rate | EE8: QTY | EF8: Rate | EG8: Efficiency | EH8: Unit | EI8: Total | EJ8: Rate | EK8: Pax | EL8: No | EM8: Unit | EN8: Total | EO8: Days | EP8: No | EQ8: Pax | ES8: Days | ET8: No | EU8: Pax | EW8: Days | EX8: No | EY8: Pax | FC8: Rate | FD8: QTY | FE8: Rate | FF8: Efficiency | FG8: Unit | FH8: Total | FI8: Rate | FJ8: Pax | FK8: No | FL8: Unit | FM8: Total | FN8: Days | FO8: No | FP8: Pax | FR8: Days | FS8: No | FT8: Pax | FV8: Days | FW8: No | FX8: Pax | GB8: Rate | GC8: QTY | GD8: Rate | GE8: Efficiency | GF8: Unit | GG8: Total | GH8: Rate | GI8: Pax | GJ8: No | GK8: Unit | GL8: Total | GM8: Days | GN8: No | GO8: Pax | GQ8: Days | GR8: No | GS8: Pax | GU8: Days | GV8: No | GW8: Pax | HA8: Rate | HB8: QTY | HC8: Rate | HD8: Efficiency | HE8: Unit | HF8: Total | HG8: Rate | HH8: Pax | HI8: No | HJ8: Unit | HK8: Total | HL8: Days | HM8: No | HN8: Pax | HP8: Days | HQ8: No | HR8: Pax | HT8: Days | HU8: No | HV8: Pax | HZ8: Rate | IA8: QTY | IB8: Rate | IC8: Efficiency | ID8: Unit | IE8: Total | IF8: Rate | IG8: Pax | IH8: No | II8: Unit | IJ8: Total | IK8: Days | IL8: No | IM8: Pax | IO8: Days | IP8: No | IQ8: Pax | IS8: Days | IT8: No | IU8: Pax
B9: 1 | C9: 8 | D9: 6am- 6pm | F9: Peak | G9: =D9 -> 6am- 6pm | H9: ='Fleet Inventory'!C8 -> 2000 | I9: 1 | J9: =H9*I9 -> 2000 | M9: 1 | N9: =J9*M9 -> 2000 | AG9: ='Fleet Inventory'!D7+'Fleet Inventory'!D8 -> 4000 | AH9: 1 | AI9: =AG9*AH9 -> 4000 | AL9: 1 | AM9: =AI9*AL9 -> 4000 | BF9: ='Fleet Inventory'!E7+'Fleet Inventory'!E8 -> 6000 | BG9: 1 | BH9: =BF9*BG9 -> 6000 | BK9: 1 | BL9: =BH9*BK9 -> 6000 | CE9: ='Fleet Inventory'!F7+'Fleet Inventory'!F8 -> 8000 | CF9: 1 | CG9: =CE9*CF9 -> 8000 | CJ9: 1 | CK9: =CG9*CJ9 -> 8000 | DD9: ='Fleet Inventory'!G7+'Fleet Inventory'!G8 -> 10000 | DE9: 1 | DF9: =DD9*DE9 -> 10000 | DI9: 1 | DJ9: =DF9*DI9 -> 10000 | EC9: ='Fleet Inventory'!H7+'Fleet Inventory'!H8 -> 10000 | ED9: 1 | EE9: =EC9*ED9 -> 10000 | EH9: 1 | EI9: =EE9*EH9 -> 10000 | FB9: ='Fleet Inventory'!I7+'Fleet Inventory'!I8 -> 10000 | FC9: 1 | FD9: =FB9*FC9 -> 10000 | FG9: 1 | FH9: =FD9*FG9 -> 10000 | GA9: ='Fleet Inventory'!J7+'Fleet Inventory'!J8 -> 10000 | GB9: 1 | GC9: =GA9*GB9 -> 10000 | GF9: 1 | GG9: =GC9*GF9 -> 10000 | GZ9: ='Fleet Inventory'!K7+'Fleet Inventory'!K8 -> 10000 | HA9: 1 | HB9: =GZ9*HA9 -> 10000 | HE9: 1 | HF9: =HB9*HE9 -> 10000 | HY9: ='Fleet Inventory'!L7+'Fleet Inventory'!L8 -> 10000 | HZ9: 1 | IA9: =HY9*HZ9 -> 10000 | ID9: 1 | IE9: =IA9*ID9 -> 10000
E10: Retail and Recreation (+56%) | I10: 0.21 | J10: =I10*H$9 -> 420 | K10: 1 | L10: =J10*K10 -> 420 | M10: 1 | N10: =L10*M10 -> 420 | O10: ='Parameters and Summary'!E74 -> 1 | P10: =N10*O10 -> 420 | Q10: 15 | R10: ='Parameters and Summary'!E24 -> 1500 | S10: =R10*P10*Q10 -> 9450000 | T10: 6 | U10: =Q10 -> 15 | V10: =T10*P10 -> 2520 | W10: =V10*R10*U10 -> 56700000 | X10: 24 | Y10: =U10 -> 15 | Z10: =X10*P10*Y10 -> 151200 | AA10: =Z10*R10 -> 226800000 | AB10: =X10*12 -> 288 | AC10: =Y10 -> 15 | AD10: =AB10*P10*AC10 -> 1814400 | AE10: =AD10*R10 -> 2721600000 | AH10: 0.21 | AI10: =AH10*AG$9 -> 840 | AJ10: 1 | AK10: =AI10*AJ10 -> 840 | AL10: 1 | AM10: =AK10*AL10 -> 840 | AN10: ='Parameters and Summary'!E74 -> 1 | AO10: =AM10*AN10 -> 840 | AP10: 15 | AQ10: ='Parameters and Summary'!G24 -> 1575 | AR10: =AQ10*AO10*AP10 -> 19845000 | AS10: 6 | AT10: =AP10 -> 15 | AU10: =AS10*AO10 -> 5040 | AV10: =AU10*AQ10*AT10 -> 119070000 | AW10: 24 | AX10: =AT10 -> 15 | AY10: =AW10*AO10*AX10 -> 302400 | AZ10: =AY10*AQ10 -> 476280000 | BA10: =AW10*12 -> 288 | BB10: =AX10 -> 15 | BC10: =BA10*AO10*BB10 -> 3628800 | BD10: =BC10*AQ10 -> 5715360000 | BG10: 0.21 | BH10: =BG10*BF$9 -> 1260 | BI10: 1 | BJ10: =BH10*BI10 -> 1260 | BK10: 1 | BL10: =BJ10*BK10 -> 1260 | BM10: ='Parameters and Summary'!E74 -> 1 | BN10: =BL10*BM10 -> 1260 | BO10: 15 | BP10: ='Parameters and Summary'!H24 -> 1653.75 | BQ10: =BP10*BN10*BO10 -> 31255875 | BR10: 6 | BS10: =BO10 -> 15 | BT10: =BR10*BN10 -> 7560 | BU10: =BT10*BP10*BS10 -> 187535250 | BV10: 24 | BW10: =BS10 -> 15 | BX10: =BV10*BN10*BW10 -> 453600 | BY10: =BX10*BP10 -> 750141000 | BZ10: =BV10*12 -> 288 | CA10: =BW10 -> 15 | CB10: =BZ10*BN10*CA10 -> 5443200 | CC10: =CB10*BP10 -> 9001692000 | CF10: 0.21 | CG10: =CF10*CE$9 -> 1680 | CH10: 1 | CI10: =CG10*CH10 -> 1680 | CJ10: 1 | CK10: =CI10*CJ10 -> 1680 | CL10: ='Parameters and Summary'!E74 -> 1 | CM10: =CK10*CL10 -> 1680 | CN10: 15 | CO10: ='Parameters and Summary'!I24 -> 1736.4375 | CP10: =CO10*CM10*CN10 -> 43758225 | CQ10: 6 | CR10: =CN10 -> 15 | CS10: =CQ10*CM10 -> 10080 | CT10: =CS10*CO10*CR10 -> 262549350 | CU10: 24 | CV10: =CR10 -> 15 | CW10: =CU10*CM10*CV10 -> 604800 | CX10: =CW10*CO10 -> 1050197400 | CY10: =CU10*12 -> 288 | CZ10: =CV10 -> 15 | DA10: =CY10*CM10*CZ10 -> 7257600 | DB10: =DA10*CO10 -> 12602368800 | DE10: 0.21 | DF10: =DE10*DD$9 -> 2100 | DG10: 1 | DH10: =DF10*DG10 -> 2100 | DI10: 1 | DJ10: =DH10*DI10 -> 2100 | DK10: ='Parameters and Summary'!E74 -> 1 | DL10: =DJ10*DK10 -> 2100 | DM10: 15 | DN10: ='Parameters and Summary'!J24 -> 1823.2594 | DO10: =DN10*DL10*DM10 -> 57432670 | DP10: 6 | DQ10: =DM10 -> 15 | DR10: =DP10*DL10 -> 12600 | DS10: =DR10*DN10*DQ10 -> 3.4459602e+08 | DT10: 24 | DU10: =DQ10 -> 15 | DV10: =DT10*DL10*DU10 -> 756000 | DW10: =DV10*DN10 -> 1.3783841e+09 | DX10: =DT10*12 -> 288 | DY10: =DU10 -> 15 | DZ10: =DX10*DL10*DY10 -> 9072000 | EA10: =DZ10*DN10 -> 16540609050 | ED10: 0.21 | EE10: =ED10*EC$9 -> 2100 | EF10: 1 | EG10: =EE10*EF10 -> 2100 | EH10: 1 | EI10: =EG10*EH10 -> 2100 | EJ10: ='Parameters and Summary'!E74 -> 1 | EK10: =EI10*EJ10 -> 2100 | EL10: 15 | EM10: ='Parameters and Summary'!K24 -> 1914.4223 | EN10: =EM10*EK10*EL10 -> 60304304 | EO10: 6 | EP10: =EL10 -> 15 | EQ10: =EO10*EK10 -> 12600 | ER10: =EQ10*EM10*EP10 -> 3.6182582e+08 | ES10: 24 | ET10: =EP10 -> 15 | EU10: =ES10*EK10*ET10 -> 756000 | EV10: =EU10*EM10 -> 1.4473033e+09 | EW10: =ES10*12 -> 288 | EX10: =ET10 -> 15 | EY10: =EW10*EK10*EX10 -> 9072000 | EZ10: =EY10*EM10 -> 1.736764e+10 | FC10: 0.21 | FD10: =FC10*FB$9 -> 2100 | FE10: 1 | FF10: =FD10*FE10 -> 2100 | FG10: 1 | FH10: =FF10*FG10 -> 2100 | FI10: ='Parameters and Summary'!E74 -> 1 | FJ10: =FH10*FI10 -> 2100 | FK10: 15 | FL10: ='Parameters and Summary'!L24 -> 2010.1435 | FM10: =FL10*FJ10*FK10 -> 63319519 | FN10: 6 | FO10: =FK10 -> 15 | FP10: =FN10*FJ10 -> 12600 | FQ10: =FP10*FL10*FO10 -> 3.7991711e+08 | FR10: 24 | FS10: =FO10 -> 15 | FT10: =FR10*FJ10*FS10 -> 756000 | FU10: =FT10*FL10 -> 1.5196685e+09 | FV10: =FR10*12 -> 288 | FW10: =FS10 -> 15 | FX10: =FV10*FJ10*FW10 -> 9072000 | FY10: =FX10*FL10 -> 1.8236021e+10 | GB10: 0.21 | GC10: =GB10*GA$9 -> 2100 | GD10: 1 | GE10: =GC10*GD10 -> 2100 | GF10: 1 | GG10: =GE10*GF10 -> 2100 | GH10: ='Parameters and Summary'!E74 -> 1 | GI10: =GG10*GH10 -> 2100 | GJ10: 15 | GK10: ='Parameters and Summary'!M24 -> 2110.6506 | GL10: =GK10*GI10*GJ10 -> 66485495 | GM10: 6 | GN10: =GJ10 -> 15 | GO10: =GM10*GI10 -> 12600 | GP10: =GO10*GK10*GN10 -> 3.9891297e+08 | GQ10: 24 | GR10: =GN10 -> 15 | GS10: =GQ10*GI10*GR10 -> 756000 | GT10: =GS10*GK10 -> 1.5956519e+09 | GU10: =GQ10*12 -> 288 | GV10: =GR10 -> 15 | GW10: =GU10*GI10*GV10 -> 9072000 | GX10: =GW10*GK10 -> 1.9147823e+10 | HA10: 0.21 | HB10: =HA10*GZ$9 -> 2100 | HC10: 1 | HD10: =HB10*HC10 -> 2100 | HE10: 1 | HF10: =HD10*HE10 -> 2100 | HG10: ='Parameters and Summary'!E74 -> 1 | HH10: =HF10*HG10 -> 2100 | HI10: 15 | HJ10: ='Parameters and Summary'!N24 -> 2216.1832 | HK10: =HJ10*HH10*HI10 -> 69809770 | HL10: 6 | HM10: =HI10 -> 15 | HN10: =HL10*HH10 -> 12600 | HO10: =HN10*HJ10*HM10 -> 4.1885862e+08 | HP10: 24 | HQ10: =HM10 -> 15 | HR10: =HP10*HH10*HQ10 -> 756000 | HS10: =HR10*HJ10 -> 1.6754345e+09 | HT10: =HP10*12 -> 288 | HU10: =HQ10 -> 15 | HV10: =HT10*HH10*HU10 -> 9072000 | HW10: =HV10*HJ10 -> 2.0105214e+10 | HZ10: 0.21 | IA10: =HZ10*HY$9 -> 2100 | IB10: 1 | IC10: =IA10*IB10 -> 2100 | ID10: 1 | IE10: =IC10*ID10 -> 2100 | IF10: ='Parameters and Summary'!E74 -> 1 | IG10: =IE10*IF10 -> 2100 | IH10: 15 | II10: ='Parameters and Summary'!O24 -> 2326.9923 | IJ10: =II10*IG10*IH10 -> 73300258 | IK10: 6 | IL10: =IH10 -> 15 | IM10: =IK10*IG10 -> 12600 | IN10: =IM10*II10*IL10 -> 4.3980155e+08 | IO10: 24 | IP10: =IL10 -> 15 | IQ10: =IO10*IG10*IP10 -> 756000 | IR10: =IQ10*II10 -> 1.7592062e+09 | IS10: =IO10*12 -> 288 | IT10: =IP10 -> 15 | IU10: =IS10*IG10*IT10 -> 9072000 | IV10: =IU10*II10 -> 2.1110474e+10
E11: Supermarket and Pharmacy (+75%) | I11: 0.3 | J11: =I11*H$9 -> 600 | K11: =K10 -> 1 | L11: =J11*K11 -> 600 | M11: 1 | N11: =L11*M11 -> 600 | O11: ='Parameters and Summary'!E75 -> 1 | P11: =N11*O11 -> 600 | Q11: =Q10 -> 15 | R11: =R10 -> 1500 | S11: =R11*P11*Q11 -> 13500000 | T11: 6 | U11: =Q11 -> 15 | V11: =T11*P11 -> 3600 | W11: =V11*R11*U11 -> 81000000 | X11: 24 | Y11: =U11 -> 15 | Z11: =X11*P11*Y11 -> 216000 | AA11: =Z11*R11 -> 324000000 | AB11: =X11*12 -> 288 | AC11: =Y11 -> 15 | AD11: =AB11*P11*AC11 -> 2592000 | AE11: =AD11*R11 -> 3888000000 | AH11: 0.3 | AI11: =AH11*AG$9 -> 1200 | AJ11: =AJ10 -> 1 | AK11: =AI11*AJ11 -> 1200 | AL11: 1 | AM11: =AK11*AL11 -> 1200 | AN11: ='Parameters and Summary'!E75 -> 1 | AO11: =AM11*AN11 -> 1200 | AP11: =AP10 -> 15 | AQ11: =AQ10 -> 1575 | AR11: =AQ11*AO11*AP11 -> 28350000 | AS11: 6 | AT11: =AP11 -> 15 | AU11: =AS11*AO11 -> 7200 | AV11: =AU11*AQ11*AT11 -> 170100000 | AW11: 24 | AX11: =AT11 -> 15 | AY11: =AW11*AO11*AX11 -> 432000 | AZ11: =AY11*AQ11 -> 680400000 | BA11: =AW11*12 -> 288 | BB11: =AX11 -> 15 | BC11: =BA11*AO11*BB11 -> 5184000 | BD11: =BC11*AQ11 -> 8164800000 | BG11: 0.3 | BH11: =BG11*BF$9 -> 1800 | BI11: =BI10 -> 1 | BJ11: =BH11*BI11 -> 1800 | BK11: 1 | BL11: =BJ11*BK11 -> 1800 | BM11: ='Parameters and Summary'!E75 -> 1 | BN11: =BL11*BM11 -> 1800 | BO11: =BO10 -> 15 | BP11: =BP10 -> 1653.75 | BQ11: =BP11*BN11*BO11 -> 44651250 | BR11: 6 | BS11: =BO11 -> 15 | BT11: =BR11*BN11 -> 10800 | BU11: =BT11*BP11*BS11 -> 267907500 | BV11: 24 | BW11: =BS11 -> 15 | BX11: =BV11*BN11*BW11 -> 648000 | BY11: =BX11*BP11 -> 1071630000 | BZ11: =BV11*12 -> 288 | CA11: =BW11 -> 15 | CB11: =BZ11*BN11*CA11 -> 7776000 | CC11: =CB11*BP11 -> 12859560000 | CF11: 0.3 | CG11: =CF11*CE$9 -> 2400 | CH11: =CH10 -> 1 | CI11: =CG11*CH11 -> 2400 | CJ11: 1 | CK11: =CI11*CJ11 -> 2400 | CL11: =CL10 -> 1 | CM11: =CK11*CL11 -> 2400 | CN11: =CN10 -> 15 | CO11: =CO10 -> 1736.4375 | CP11: =CO11*CM11*CN11 -> 62511750 | CQ11: 6 | CR11: =CN11 -> 15 | CS11: =CQ11*CM11 -> 14400 | CT11: =CS11*CO11*CR11 -> 375070500 | CU11: 24 | CV11: =CR11 -> 15 | CW11: =CU11*CM11*CV11 -> 864000 | CX11: =CW11*CO11 -> 1500282000 | CY11: =CU11*12 -> 288 | CZ11: =CV11 -> 15 | DA11: =CY11*CM11*CZ11 -> 10368000 | DB11: =DA11*CO11 -> 18003384000 | DE11: 0.3 | DF11: =DE11*DD$9 -> 3000 | DG11: =DG10 -> 1 | DH11: =DF11*DG11 -> 3000 | DI11: 1 | DJ11: =DH11*DI11 -> 3000 | DK11: ='Parameters and Summary'!E75 -> 1 | DL11: =DJ11*DK11 -> 3000 | DM11: =DM10 -> 15 | DN11: =DN10 -> 1823.2594 | DO11: =DN11*DL11*DM11 -> 82046672 | DP11: 6 | DQ11: =DM11 -> 15 | DR11: =DP11*DL11 -> 18000 | DS11: =DR11*DN11*DQ11 -> 4.9228003e+08 | DT11: 24 | DU11: =DQ11 -> 15 | DV11: =DT11*DL11*DU11 -> 1080000 | DW11: =DV11*DN11 -> 1969120125 | DX11: =DT11*12 -> 288 | DY11: =DU11 -> 15 | DZ11: =DX11*DL11*DY11 -> 12960000 | EA11: =DZ11*DN11 -> 23629441500 | ED11: 0.3 | EE11: =ED11*EC$9 -> 3000 | EF11: =EF10 -> 1 | EG11: =EE11*EF11 -> 3000 | EH11: 1 | EI11: =EG11*EH11 -> 3000 | EJ11: ='Parameters and Summary'!E75 -> 1 | EK11: =EI11*EJ11 -> 3000 | EL11: =EL10 -> 15 | EM11: =EM10 -> 1914.4223 | EN11: =EM11*EK11*EL11 -> 86149005 | EO11: 6 | EP11: =EL11 -> 15 | EQ11: =EO11*EK11 -> 18000 | ER11: =EQ11*EM11*EP11 -> 5.1689403e+08 | ES11: 24 | ET11: =EP11 -> 15 | EU11: =ES11*EK11*ET11 -> 1080000 | EV11: =EU11*EM11 -> 2.0675761e+09 | EW11: =ES11*12 -> 288 | EX11: =ET11 -> 15 | EY11: =EW11*EK11*EX11 -> 12960000 | EZ11: =EY11*EM11 -> 2.4810914e+10 | FC11: 0.3 | FD11: =FC11*FB$9 -> 3000 | FE11: =FE10 -> 1 | FF11: =FD11*FE11 -> 3000 | FG11: 1 | FH11: =FF11*FG11 -> 3000 | FI11: ='Parameters and Summary'!E75 -> 1 | FJ11: =FH11*FI11 -> 3000 | FK11: =FK10 -> 15 | FL11: =FL10 -> 2010.1435 | FM11: =FL11*FJ11*FK11 -> 90456456 | FN11: 6 | FO11: =FK11 -> 15 | FP11: =FN11*FJ11 -> 18000 | FQ11: =FP11*FL11*FO11 -> 5.4273873e+08 | FR11: 24 | FS11: =FO11 -> 15 | FT11: =FR11*FJ11*FS11 -> 1080000 | FU11: =FT11*FL11 -> 2.1709549e+09 | FV11: =FR11*12 -> 288 | FW11: =FS11 -> 15 | FX11: =FV11*FJ11*FW11 -> 12960000 | FY11: =FX11*FL11 -> 2.6051459e+10 | GB11: 0.3 | GC11: =GB11*GA$9 -> 3000 | GD11: =GD10 -> 1 | GE11: =GC11*GD11 -> 3000 | GF11: 1 | GG11: =GE11*GF11 -> 3000 | GH11: ='Parameters and Summary'!E75 -> 1 | GI11: =GG11*GH11 -> 3000 | GJ11: =GJ10 -> 15 | GK11: =GK10 -> 2110.6506 | GL11: =GK11*GI11*GJ11 -> 94979279 | GM11: 6 | GN11: =GJ11 -> 15 | GO11: =GM11*GI11 -> 18000 | GP11: =GO11*GK11*GN11 -> 5.6987567e+08 | GQ11: 24 | GR11: =GN11 -> 15 | GS11: =GQ11*GI11*GR11 -> 1080000 | GT11: =GS11*GK11 -> 2.2795027e+09 | GU11: =GQ11*12 -> 288 | GV11: =GR11 -> 15 | GW11: =GU11*GI11*GV11 -> 12960000 | GX11: =GW11*GK11 -> 2.7354032e+10 | HA11: 0.3 | HB11: =HA11*GZ$9 -> 3000 | HC11: =HC10 -> 1 | HD11: =HB11*HC11 -> 3000 | HE11: 1 | HF11: =HD11*HE11 -> 3000 | HG11: ='Parameters and Summary'!E75 -> 1 | HH11: =HF11*HG11 -> 3000 | HI11: =HI10 -> 15 | HJ11: =HJ10 -> 2216.1832 | HK11: =HJ11*HH11*HI11 -> 99728242 | HL11: 6 | HM11: =HI11 -> 15 | HN11: =HL11*HH11 -> 18000 | HO11: =HN11*HJ11*HM11 -> 5.9836945e+08 | HP11: 24 | HQ11: =HM11 -> 15 | HR11: =HP11*HH11*HQ11 -> 1080000 | HS11: =HR11*HJ11 -> 2.3934778e+09 | HT11: =HP11*12 -> 288 | HU11: =HQ11 -> 15 | HV11: =HT11*HH11*HU11 -> 12960000 | HW11: =HV11*HJ11 -> 2.8721734e+10 | HZ11: 0.3 | IA11: =HZ11*HY$9 -> 3000 | IB11: =IB10 -> 1 | IC11: =IA11*IB11 -> 3000 | ID11: 1 | IE11: =IC11*ID11 -> 3000 | IF11: ='Parameters and Summary'!E75 -> 1 | IG11: =IE11*IF11 -> 3000 | IH11: =IH10 -> 15 | II11: =II10 -> 2326.9923 | IJ11: =II11*IG11*IH11 -> 1.0471465e+08 | IK11: 6 | IL11: =IH11 -> 15 | IM11: =IK11*IG11 -> 18000 | IN11: =IM11*II11*IL11 -> 6.2828793e+08 | IO11: 24 | IP11: =IL11 -> 15 | IQ11: =IO11*IG11*IP11 -> 1080000 | IR11: =IQ11*II11 -> 2.5131517e+09 | IS11: =IO11*12 -> 288 | IT11: =IP11 -> 15 | IU11: =IS11*IG11*IT11 -> 12960000 | IV11: =IU11*II11 -> 3.0157821e+10
E12: Parks (+43%) | I12: 0.14 | J12: =I12*H$9 -> 280 | K12: =K11 -> 1 | L12: =J12*K12 -> 280 | M12: 1 | N12: =L12*M12 -> 280 | O12: ='Parameters and Summary'!E76 -> 1 | P12: =N12*O12 -> 280 | Q12: =Q11 -> 15 | R12: =R11 -> 1500 | S12: =R12*P12*Q12 -> 6300000 | T12: 6 | U12: =Q12 -> 15 | V12: =T12*P12 -> 1680 | W12: =V12*R12*U12 -> 37800000 | X12: 24 | Y12: =U12 -> 15 | Z12: =X12*P12*Y12 -> 100800 | AA12: =Z12*R12 -> 151200000 | AB12: =X12*12 -> 288 | AC12: =Y12 -> 15 | AD12: =AB12*P12*AC12 -> 1209600 | AE12: =AD12*R12 -> 1814400000 | AH12: 0.14 | AI12: =AH12*AG$9 -> 560 | AJ12: =AJ11 -> 1 | AK12: =AI12*AJ12 -> 560 | AL12: 1 | AM12: =AK12*AL12 -> 560 | AN12: ='Parameters and Summary'!E76 -> 1 | AO12: =AM12*AN12 -> 560 | AP12: =AP11 -> 15 | AQ12: =AQ11 -> 1575 | AR12: =AQ12*AO12*AP12 -> 13230000 | AS12: 6 | AT12: =AP12 -> 15 | AU12: =AS12*AO12 -> 3360 | AV12: =AU12*AQ12*AT12 -> 79380000 | AW12: 24 | AX12: =AT12 -> 15 | AY12: =AW12*AO12*AX12 -> 201600 | AZ12: =AY12*AQ12 -> 317520000 | BA12: =AW12*12 -> 288 | BB12: =AX12 -> 15 | BC12: =BA12*AO12*BB12 -> 2419200 | BD12: =BC12*AQ12 -> 3810240000 | BG12: 0.14 | BH12: =BG12*BF$9 -> 840 | BI12: =BI11 -> 1 | BJ12: =BH12*BI12 -> 840 | BK12: 1 | BL12: =BJ12*BK12 -> 840 | BM12: ='Parameters and Summary'!E76 -> 1 | BN12: =BL12*BM12 -> 840 | BO12: =BO11 -> 15 | BP12: =BP11 -> 1653.75 | BQ12: =BP12*BN12*BO12 -> 20837250 | BR12: 6 | BS12: =BO12 -> 15 | BT12: =BR12*BN12 -> 5040 | BU12: =BT12*BP12*BS12 -> 1.250235e+08 | BV12: 24 | BW12: =BS12 -> 15 | BX12: =BV12*BN12*BW12 -> 302400 | BY12: =BX12*BP12 -> 5.00094e+08 | BZ12: =BV12*12 -> 288 | CA12: =BW12 -> 15 | CB12: =BZ12*BN12*CA12 -> 3628800 | CC12: =CB12*BP12 -> 6.001128e+09 | CF12: 0.14 | CG12: =CF12*CE$9 -> 1120 | CH12: =CH11 -> 1 | CI12: =CG12*CH12 -> 1120 | CJ12: 1 | CK12: =CI12*CJ12 -> 1120 | CL12: =CL11 -> 1 | CM12: =CK12*CL12 -> 1120 | CN12: =CN11 -> 15 | CO12: =CO11 -> 1736.4375 | CP12: =CO12*CM12*CN12 -> 29172150 | CQ12: 6 | CR12: =CN12 -> 15 | CS12: =CQ12*CM12 -> 6720 | CT12: =CS12*CO12*CR12 -> 175032900 | CU12: 24 | CV12: =CR12 -> 15 | CW12: =CU12*CM12*CV12 -> 403200 | CX12: =CW12*CO12 -> 700131600 | CY12: =CU12*12 -> 288 | CZ12: =CV12 -> 15 | DA12: =CY12*CM12*CZ12 -> 4838400 | DB12: =DA12*CO12 -> 8401579200 | DE12: 0.14 | DF12: =DE12*DD$9 -> 1400 | DG12: =DG11 -> 1 | DH12: =DF12*DG12 -> 1400 | DI12: 1 | DJ12: =DH12*DI12 -> 1400 | DK12: ='Parameters and Summary'!E76 -> 1 | DL12: =DJ12*DK12 -> 1400 | DM12: =DM11 -> 15 | DN12: =DN11 -> 1823.2594 | DO12: =DN12*DL12*DM12 -> 38288447 | DP12: 6 | DQ12: =DM12 -> 15 | DR12: =DP12*DL12 -> 8400 | DS12: =DR12*DN12*DQ12 -> 2.2973068e+08 | DT12: 24 | DU12: =DQ12 -> 15 | DV12: =DT12*DL12*DU12 -> 504000 | DW12: =DV12*DN12 -> 9.1892273e+08 | DX12: =DT12*12 -> 288 | DY12: =DU12 -> 15 | DZ12: =DX12*DL12*DY12 -> 6048000 | EA12: =DZ12*DN12 -> 1.1027073e+10 | ED12: 0.14 | EE12: =ED12*EC$9 -> 1400 | EF12: =EF11 -> 1 | EG12: =EE12*EF12 -> 1400 | EH12: 1 | EI12: =EG12*EH12 -> 1400 | EJ12: ='Parameters and Summary'!E76 -> 1 | EK12: =EI12*EJ12 -> 1400 | EL12: =EL11 -> 15 | EM12: =EM11 -> 1914.4223 | EN12: =EM12*EK12*EL12 -> 40202869 | EO12: 6 | EP12: =EL12 -> 15 | EQ12: =EO12*EK12 -> 8400 | ER12: =EQ12*EM12*EP12 -> 2.4121722e+08 | ES12: 24 | ET12: =EP12 -> 15 | EU12: =ES12*EK12*ET12 -> 504000 | EV12: =EU12*EM12 -> 9.6486886e+08 | EW12: =ES12*12 -> 288 | EX12: =ET12 -> 15 | EY12: =EW12*EK12*EX12 -> 6048000 | EZ12: =EY12*EM12 -> 1.1578426e+10 | FC12: 0.14 | FD12: =FC12*FB$9 -> 1400 | FE12: =FE11 -> 1 | FF12: =FD12*FE12 -> 1400 | FG12: 1 | FH12: =FF12*FG12 -> 1400 | FI12: ='Parameters and Summary'!E76 -> 1 | FJ12: =FH12*FI12 -> 1400 | FK12: =FK11 -> 15 | FL12: =FL11 -> 2010.1435 | FM12: =FL12*FJ12*FK12 -> 42213013 | FN12: 6 | FO12: =FK12 -> 15 | FP12: =FN12*FJ12 -> 8400 | FQ12: =FP12*FL12*FO12 -> 2.5327808e+08 | FR12: 24 | FS12: =FO12 -> 15 | FT12: =FR12*FJ12*FS12 -> 504000 | FU12: =FT12*FL12 -> 1.0131123e+09 | FV12: =FR12*12 -> 288 | FW12: =FS12 -> 15 | FX12: =FV12*FJ12*FW12 -> 6048000 | FY12: =FX12*FL12 -> 1.2157348e+10 | GB12: 0.14 | GC12: =GB12*GA$9 -> 1400 | GD12: =GD11 -> 1 | GE12: =GC12*GD12 -> 1400 | GF12: 1 | GG12: =GE12*GF12 -> 1400 | GH12: ='Parameters and Summary'!E76 -> 1 | GI12: =GG12*GH12 -> 1400 | GJ12: =GJ11 -> 15 | GK12: =GK11 -> 2110.6506 | GL12: =GK12*GI12*GJ12 -> 44323663 | GM12: 6 | GN12: =GJ12 -> 15 | GO12: =GM12*GI12 -> 8400 | GP12: =GO12*GK12*GN12 -> 2.6594198e+08 | GQ12: 24 | GR12: =GN12 -> 15 | GS12: =GQ12*GI12*GR12 -> 504000 | GT12: =GS12*GK12 -> 1.0637679e+09 | GU12: =GQ12*12 -> 288 | GV12: =GR12 -> 15 | GW12: =GU12*GI12*GV12 -> 6048000 | GX12: =GW12*GK12 -> 1.2765215e+10 | HA12: 0.14 | HB12: =HA12*GZ$9 -> 1400 | HC12: =HC11 -> 1 | HD12: =HB12*HC12 -> 1400 | HE12: 1 | HF12: =HD12*HE12 -> 1400 | HG12: ='Parameters and Summary'!E76 -> 1 | HH12: =HF12*HG12 -> 1400 | HI12: =HI11 -> 15 | HJ12: =HJ11 -> 2216.1832 | HK12: =HJ12*HH12*HI12 -> 46539846 | HL12: 6 | HM12: =HI12 -> 15 | HN12: =HL12*HH12 -> 8400 | HO12: =HN12*HJ12*HM12 -> 2.7923908e+08 | HP12: 24 | HQ12: =HM12 -> 15 | HR12: =HP12*HH12*HQ12 -> 504000 | HS12: =HR12*HJ12 -> 1.1169563e+09 | HT12: =HP12*12 -> 288 | HU12: =HQ12 -> 15 | HV12: =HT12*HH12*HU12 -> 6048000 | HW12: =HV12*HJ12 -> 1.3403476e+10 | HZ12: 0.14 | IA12: =HZ12*HY$9 -> 1400 | IB12: =IB11 -> 1 | IC12: =IA12*IB12 -> 1400 | ID12: 1 | IE12: =IC12*ID12 -> 1400 | IF12: ='Parameters and Summary'!E76 -> 1 | IG12: =IE12*IF12 -> 1400 | IH12: =IH11 -> 15 | II12: =II11 -> 2326.9923 | IJ12: =II12*IG12*IH12 -> 48866839 | IK12: 6 | IL12: =IH12 -> 15 | IM12: =IK12*IG12 -> 8400 | IN12: =IM12*II12*IL12 -> 2.9320103e+08 | IO12: 24 | IP12: =IL12 -> 15 | IQ12: =IO12*IG12*IP12 -> 504000 | IR12: =IQ12*II12 -> 1.1728041e+09 | IS12: =IO12*12 -> 288 | IT12: =IP12 -> 15 | IU12: =IS12*IG12*IT12 -> 6048000 | IV12: =IU12*II12 -> 1.407365e+10
E13: Workplaces (+73%) | I13: 0.175 | J13: =I13*H$9 -> 350 | K13: =K12 -> 1 | L13: =J13*K13 -> 350 | M13: 1 | N13: =L13*M13 -> 350 | O13: ='Parameters and Summary'!E77 -> 1 | P13: =N13*O13 -> 350 | Q13: =Q12 -> 15 | R13: =R12 -> 1500 | S13: =R13*P13*Q13 -> 7875000 | T13: 6 | U13: =Q13 -> 15 | V13: =T13*P13 -> 2100 | W13: =V13*R13*U13 -> 47250000 | X13: 24 | Y13: =U13 -> 15 | Z13: =X13*P13*Y13 -> 126000 | AA13: =Z13*R13 -> 189000000 | AB13: =X13*12 -> 288 | AC13: =Y13 -> 15 | AD13: =AB13*P13*AC13 -> 1512000 | AE13: =AD13*R13 -> 2268000000 | AH13: 0.175 | AI13: =AH13*AG$9 -> 700 | AJ13: =AJ12 -> 1 | AK13: =AI13*AJ13 -> 700 | AL13: 1 | AM13: =AK13*AL13 -> 700 | AN13: ='Parameters and Summary'!E77 -> 1 | AO13: =AM13*AN13 -> 700 | AP13: =AP12 -> 15 | AQ13: =AQ12 -> 1575 | AR13: =AQ13*AO13*AP13 -> 16537500 | AS13: 6 | AT13: =AP13 -> 15 | AU13: =AS13*AO13 -> 4200 | AV13: =AU13*AQ13*AT13 -> 99225000 | AW13: 24 | AX13: =AT13 -> 15 | AY13: =AW13*AO13*AX13 -> 252000 | AZ13: =AY13*AQ13 -> 396900000 | BA13: =AW13*12 -> 288 | BB13: =AX13 -> 15 | BC13: =BA13*AO13*BB13 -> 3024000 | BD13: =BC13*AQ13 -> 4762800000 | BG13: 0.175 | BH13: =BG13*BF$9 -> 1050 | BI13: =BI12 -> 1 | BJ13: =BH13*BI13 -> 1050 | BK13: 1 | BL13: =BJ13*BK13 -> 1050 | BM13: ='Parameters and Summary'!E77 -> 1 | BN13: =BL13*BM13 -> 1050 | BO13: =BO12 -> 15 | BP13: =BP12 -> 1653.75 | BQ13: =BP13*BN13*BO13 -> 26046562 | BR13: 6 | BS13: =BO13 -> 15 | BT13: =BR13*BN13 -> 6300 | BU13: =BT13*BP13*BS13 -> 156279375 | BV13: 24 | BW13: =BS13 -> 15 | BX13: =BV13*BN13*BW13 -> 378000 | BY13: =BX13*BP13 -> 625117500 | BZ13: =BV13*12 -> 288 | CA13: =BW13 -> 15 | CB13: =BZ13*BN13*CA13 -> 4536000 | CC13: =CB13*BP13 -> 7501410000 | CF13: 0.175 | CG13: =CF13*CE$9 -> 1400 | CH13: =CH12 -> 1 | CI13: =CG13*CH13 -> 1400 | CJ13: 1 | CK13: =CI13*CJ13 -> 1400 | CL13: =CL12 -> 1 | CM13: =CK13*CL13 -> 1400 | CN13: =CN12 -> 15 | CO13: =CO12 -> 1736.4375 | CP13: =CO13*CM13*CN13 -> 36465188 | CQ13: 6 | CR13: =CN13 -> 15 | CS13: =CQ13*CM13 -> 8400 | CT13: =CS13*CO13*CR13 -> 218791125 | CU13: 24 | CV13: =CR13 -> 15 | CW13: =CU13*CM13*CV13 -> 504000 | CX13: =CW13*CO13 -> 875164500 | CY13: =CU13*12 -> 288 | CZ13: =CV13 -> 15 | DA13: =CY13*CM13*CZ13 -> 6048000 | DB13: =DA13*CO13 -> 10501974000 | DE13: 0.175 | DF13: =DE13*DD$9 -> 1750 | DG13: =DG12 -> 1 | DH13: =DF13*DG13 -> 1750 | DI13: 1 | DJ13: =DH13*DI13 -> 1750 | DK13: ='Parameters and Summary'!E77 -> 1 | DL13: =DJ13*DK13 -> 1750 | DM13: =DM12 -> 15 | DN13: =DN12 -> 1823.2594 | DO13: =DN13*DL13*DM13 -> 47860559 | DP13: 6 | DQ13: =DM13 -> 15 | DR13: =DP13*DL13 -> 10500 | DS13: =DR13*DN13*DQ13 -> 2.8716335e+08 | DT13: 24 | DU13: =DQ13 -> 15 | DV13: =DT13*DL13*DU13 -> 630000 | DW13: =DV13*DN13 -> 1.1486534e+09 | DX13: =DT13*12 -> 288 | DY13: =DU13 -> 15 | DZ13: =DX13*DL13*DY13 -> 7560000 | EA13: =DZ13*DN13 -> 13783840875 | ED13: 0.175 | EE13: =ED13*EC$9 -> 1750 | EF13: =EF12 -> 1 | EG13: =EE13*EF13 -> 1750 | EH13: 1 | EI13: =EG13*EH13 -> 1750 | EJ13: ='Parameters and Summary'!E77 -> 1 | EK13: =EI13*EJ13 -> 1750 | EL13: =EL12 -> 15 | EM13: =EM12 -> 1914.4223 | EN13: =EM13*EK13*EL13 -> 50253587 | EO13: 6 | EP13: =EL13 -> 15 | EQ13: =EO13*EK13 -> 10500 | ER13: =EQ13*EM13*EP13 -> 3.0152152e+08 | ES13: 24 | ET13: =EP13 -> 15 | EU13: =ES13*EK13*ET13 -> 630000 | EV13: =EU13*EM13 -> 1.2060861e+09 | EW13: =ES13*12 -> 288 | EX13: =ET13 -> 15 | EY13: =EW13*EK13*EX13 -> 7560000 | EZ13: =EY13*EM13 -> 1.4473033e+10 | FC13: 0.175 | FD13: =FC13*FB$9 -> 1750 | FE13: =FE12 -> 1 | FF13: =FD13*FE13 -> 1750 | FG13: 1 | FH13: =FF13*FG13 -> 1750 | FI13: ='Parameters and Summary'!E77 -> 1 | FJ13: =FH13*FI13 -> 1750 | FK13: =FK12 -> 15 | FL13: =FL12 -> 2010.1435 | FM13: =FL13*FJ13*FK13 -> 52766266 | FN13: 6 | FO13: =FK13 -> 15 | FP13: =FN13*FJ13 -> 10500 | FQ13: =FP13*FL13*FO13 -> 3.165976e+08 | FR13: 24 | FS13: =FO13 -> 15 | FT13: =FR13*FJ13*FS13 -> 630000 | FU13: =FT13*FL13 -> 1.2663904e+09 | FV13: =FR13*12 -> 288 | FW13: =FS13 -> 15 | FX13: =FV13*FJ13*FW13 -> 7560000 | FY13: =FX13*FL13 -> 1.5196685e+10 | GB13: 0.175 | GC13: =GB13*GA$9 -> 1750 | GD13: =GD12 -> 1 | GE13: =GC13*GD13 -> 1750 | GF13: 1 | GG13: =GE13*GF13 -> 1750 | GH13: ='Parameters and Summary'!E77 -> 1 | GI13: =GG13*GH13 -> 1750 | GJ13: =GJ12 -> 15 | GK13: =GK12 -> 2110.6506 | GL13: =GK13*GI13*GJ13 -> 55404579 | GM13: 6 | GN13: =GJ13 -> 15 | GO13: =GM13*GI13 -> 10500 | GP13: =GO13*GK13*GN13 -> 3.3242747e+08 | GQ13: 24 | GR13: =GN13 -> 15 | GS13: =GQ13*GI13*GR13 -> 630000 | GT13: =GS13*GK13 -> 1.3297099e+09 | GU13: =GQ13*12 -> 288 | GV13: =GR13 -> 15 | GW13: =GU13*GI13*GV13 -> 7560000 | GX13: =GW13*GK13 -> 1.5956519e+10 | HA13: 0.175 | HB13: =HA13*GZ$9 -> 1750 | HC13: =HC12 -> 1 | HD13: =HB13*HC13 -> 1750 | HE13: 1 | HF13: =HD13*HE13 -> 1750 | HG13: ='Parameters and Summary'!E77 -> 1 | HH13: =HF13*HG13 -> 1750 | HI13: =HI12 -> 15 | HJ13: =HJ12 -> 2216.1832 | HK13: =HJ13*HH13*HI13 -> 58174808 | HL13: 6 | HM13: =HI13 -> 15 | HN13: =HL13*HH13 -> 10500 | HO13: =HN13*HJ13*HM13 -> 3.4904885e+08 | HP13: 24 | HQ13: =HM13 -> 15 | HR13: =HP13*HH13*HQ13 -> 630000 | HS13: =HR13*HJ13 -> 1.3961954e+09 | HT13: =HP13*12 -> 288 | HU13: =HQ13 -> 15 | HV13: =HT13*HH13*HU13 -> 7560000 | HW13: =HV13*HJ13 -> 1.6754345e+10 | HZ13: 0.175 | IA13: =HZ13*HY$9 -> 1750 | IB13: =IB12 -> 1 | IC13: =IA13*IB13 -> 1750 | ID13: 1 | IE13: =IC13*ID13 -> 1750 | IF13: ='Parameters and Summary'!E77 -> 1 | IG13: =IE13*IF13 -> 1750 | IH13: =IH12 -> 15 | II13: =II12 -> 2326.9923 | IJ13: =II13*IG13*IH13 -> 61083549 | IK13: 6 | IL13: =IH13 -> 15 | IM13: =IK13*IG13 -> 10500 | IN13: =IM13*II13*IL13 -> 3.6650129e+08 | IO13: 24 | IP13: =IL13 -> 15 | IQ13: =IO13*IG13*IP13 -> 630000 | IR13: =IQ13*II13 -> 1.4660052e+09 | IS13: =IO13*12 -> 288 | IT13: =IP13 -> 15 | IU13: =IS13*IG13*IT13 -> 7560000 | IV13: =IU13*II13 -> 1.7592062e+10
E14: Residential Areas (+19%) | I14: 0.105 | J14: =I14*H$9 -> 210 | K14: =K13 -> 1 | L14: =J14*K14 -> 210 | M14: 1 | N14: =L14*M14 -> 210 | O14: ='Parameters and Summary'!E78 -> 1 | P14: =N14*O14 -> 210 | Q14: =Q13 -> 15 | R14: =R13 -> 1500 | S14: =R14*P14*Q14 -> 4725000 | T14: 6 | U14: =Q14 -> 15 | V14: =T14*P14 -> 1260 | W14: =V14*R14*U14 -> 28350000 | X14: 24 | Y14: =U14 -> 15 | Z14: =X14*P14*Y14 -> 75600 | AA14: =Z14*R14 -> 113400000 | AB14: =X14*12 -> 288 | AC14: =Y14 -> 15 | AD14: =AB14*P14*AC14 -> 907200 | AE14: =AD14*R14 -> 1360800000 | AH14: 0.105 | AI14: =AH14*AG$9 -> 420 | AJ14: =AJ13 -> 1 | AK14: =AI14*AJ14 -> 420 | AL14: 1 | AM14: =AK14*AL14 -> 420 | AN14: ='Parameters and Summary'!E78 -> 1 | AO14: =AM14*AN14 -> 420 | AP14: =AP13 -> 15 | AQ14: =AQ13 -> 1575 | AR14: =AQ14*AO14*AP14 -> 9922500 | AS14: 6 | AT14: =AP14 -> 15 | AU14: =AS14*AO14 -> 2520 | AV14: =AU14*AQ14*AT14 -> 59535000 | AW14: 24 | AX14: =AT14 -> 15 | AY14: =AW14*AO14*AX14 -> 151200 | AZ14: =AY14*AQ14 -> 238140000 | BA14: =AW14*12 -> 288 | BB14: =AX14 -> 15 | BC14: =BA14*AO14*BB14 -> 1814400 | BD14: =BC14*AQ14 -> 2857680000 | BG14: 0.105 | BH14: =BG14*BF$9 -> 630 | BI14: =BI13 -> 1 | BJ14: =BH14*BI14 -> 630 | BK14: 1 | BL14: =BJ14*BK14 -> 630 | BM14: ='Parameters and Summary'!E78 -> 1 | BN14: =BL14*BM14 -> 630 | BO14: =BO13 -> 15 | BP14: =BP13 -> 1653.75 | BQ14: =BP14*BN14*BO14 -> 15627938 | BR14: 6 | BS14: =BO14 -> 15 | BT14: =BR14*BN14 -> 3780 | BU14: =BT14*BP14*BS14 -> 93767625 | BV14: 24 | BW14: =BS14 -> 15 | BX14: =BV14*BN14*BW14 -> 226800 | BY14: =BX14*BP14 -> 375070500 | BZ14: =BV14*12 -> 288 | CA14: =BW14 -> 15 | CB14: =BZ14*BN14*CA14 -> 2721600 | CC14: =CB14*BP14 -> 4500846000 | CF14: 0.105 | CG14: =CF14*CE$9 -> 840 | CH14: =CH13 -> 1 | CI14: =CG14*CH14 -> 840 | CJ14: 1 | CK14: =CI14*CJ14 -> 840 | CL14: =CL13 -> 1 | CM14: =CK14*CL14 -> 840 | CN14: =CN13 -> 15 | CO14: =CO13 -> 1736.4375 | CP14: =CO14*CM14*CN14 -> 21879112 | CQ14: 6 | CR14: =CN14 -> 15 | CS14: =CQ14*CM14 -> 5040 | CT14: =CS14*CO14*CR14 -> 131274675 | CU14: 24 | CV14: =CR14 -> 15 | CW14: =CU14*CM14*CV14 -> 302400 | CX14: =CW14*CO14 -> 525098700 | CY14: =CU14*12 -> 288 | CZ14: =CV14 -> 15 | DA14: =CY14*CM14*CZ14 -> 3628800 | DB14: =DA14*CO14 -> 6301184400 | DE14: 0.105 | DF14: =DE14*DD$9 -> 1050 | DG14: =DG13 -> 1 | DH14: =DF14*DG14 -> 1050 | DI14: 1 | DJ14: =DH14*DI14 -> 1050 | DK14: ='Parameters and Summary'!E78 -> 1 | DL14: =DJ14*DK14 -> 1050 | DM14: =DM13 -> 15 | DN14: =DN13 -> 1823.2594 | DO14: =DN14*DL14*DM14 -> 28716335 | DP14: 6 | DQ14: =DM14 -> 15 | DR14: =DP14*DL14 -> 6300 | DS14: =DR14*DN14*DQ14 -> 1.7229801e+08 | DT14: 24 | DU14: =DQ14 -> 15 | DV14: =DT14*DL14*DU14 -> 378000 | DW14: =DV14*DN14 -> 6.8919204e+08 | DX14: =DT14*12 -> 288 | DY14: =DU14 -> 15 | DZ14: =DX14*DL14*DY14 -> 4536000 | EA14: =DZ14*DN14 -> 8270304525 | ED14: 0.105 | EE14: =ED14*EC$9 -> 1050 | EF14: =EF13 -> 1 | EG14: =EE14*EF14 -> 1050 | EH14: 1 | EI14: =EG14*EH14 -> 1050 | EJ14: ='Parameters and Summary'!E78 -> 1 | EK14: =EI14*EJ14 -> 1050 | EL14: =EL13 -> 15 | EM14: =EM13 -> 1914.4223 | EN14: =EM14*EK14*EL14 -> 30152152 | EO14: 6 | EP14: =EL14 -> 15 | EQ14: =EO14*EK14 -> 6300 | ER14: =EQ14*EM14*EP14 -> 1.8091291e+08 | ES14: 24 | ET14: =EP14 -> 15 | EU14: =ES14*EK14*ET14 -> 378000 | EV14: =EU14*EM14 -> 7.2365165e+08 | EW14: =ES14*12 -> 288 | EX14: =ET14 -> 15 | EY14: =EW14*EK14*EX14 -> 4536000 | EZ14: =EY14*EM14 -> 8.6838198e+09 | FC14: 0.105 | FD14: =FC14*FB$9 -> 1050 | FE14: =FE13 -> 1 | FF14: =FD14*FE14 -> 1050 | FG14: 1 | FH14: =FF14*FG14 -> 1050 | FI14: ='Parameters and Summary'!E78 -> 1 | FJ14: =FH14*FI14 -> 1050 | FK14: =FK13 -> 15 | FL14: =FL13 -> 2010.1435 | FM14: =FL14*FJ14*FK14 -> 31659760 | FN14: 6 | FO14: =FK14 -> 15 | FP14: =FN14*FJ14 -> 6300 | FQ14: =FP14*FL14*FO14 -> 1.8995856e+08 | FR14: 24 | FS14: =FO14 -> 15 | FT14: =FR14*FJ14*FS14 -> 378000 | FU14: =FT14*FL14 -> 7.5983423e+08 | FV14: =FR14*12 -> 288 | FW14: =FS14 -> 15 | FX14: =FV14*FJ14*FW14 -> 4536000 | FY14: =FX14*FL14 -> 9.1180107e+09 | GB14: 0.105 | GC14: =GB14*GA$9 -> 1050 | GD14: =GD13 -> 1 | GE14: =GC14*GD14 -> 1050 | GF14: 1 | GG14: =GE14*GF14 -> 1050 | GH14: ='Parameters and Summary'!E78 -> 1 | GI14: =GG14*GH14 -> 1050 | GJ14: =GJ13 -> 15 | GK14: =GK13 -> 2110.6506 | GL14: =GK14*GI14*GJ14 -> 33242747 | GM14: 6 | GN14: =GJ14 -> 15 | GO14: =GM14*GI14 -> 6300 | GP14: =GO14*GK14*GN14 -> 1.9945648e+08 | GQ14: 24 | GR14: =GN14 -> 15 | GS14: =GQ14*GI14*GR14 -> 378000 | GT14: =GS14*GK14 -> 7.9782594e+08 | GU14: =GQ14*12 -> 288 | GV14: =GR14 -> 15 | GW14: =GU14*GI14*GV14 -> 4536000 | GX14: =GW14*GK14 -> 9.5739113e+09 | HA14: 0.105 | HB14: =HA14*GZ$9 -> 1050 | HC14: =HC13 -> 1 | HD14: =HB14*HC14 -> 1050 | HE14: 1 | HF14: =HD14*HE14 -> 1050 | HG14: ='Parameters and Summary'!E78 -> 1 | HH14: =HF14*HG14 -> 1050 | HI14: =HI13 -> 15 | HJ14: =HJ13 -> 2216.1832 | HK14: =HJ14*HH14*HI14 -> 34904885 | HL14: 6 | HM14: =HI14 -> 15 | HN14: =HL14*HH14 -> 6300 | HO14: =HN14*HJ14*HM14 -> 2.0942931e+08 | HP14: 24 | HQ14: =HM14 -> 15 | HR14: =HP14*HH14*HQ14 -> 378000 | HS14: =HR14*HJ14 -> 8.3771724e+08 | HT14: =HP14*12 -> 288 | HU14: =HQ14 -> 15 | HV14: =HT14*HH14*HU14 -> 4536000 | HW14: =HV14*HJ14 -> 1.0052607e+10 | HZ14: 0.105 | IA14: =HZ14*HY$9 -> 1050 | IB14: =IB13 -> 1 | IC14: =IA14*IB14 -> 1050 | ID14: 1 | IE14: =IC14*ID14 -> 1050 | IF14: ='Parameters and Summary'!E78 -> 1 | IG14: =IE14*IF14 -> 1050 | IH14: =IH13 -> 15 | II14: =II13 -> 2326.9923 | IJ14: =II14*IG14*IH14 -> 36650129 | IK14: 6 | IL14: =IH14 -> 15 | IM14: =IK14*IG14 -> 6300 | IN14: =IM14*II14*IL14 -> 2.1990077e+08 | IO14: 24 | IP14: =IL14 -> 15 | IQ14: =IO14*IG14*IP14 -> 378000 | IR14: =IQ14*II14 -> 8.796031e+08 | IS14: =IO14*12 -> 288 | IT14: =IP14 -> 15 | IU14: =IS14*IG14*IT14 -> 4536000 | IV14: =IU14*II14 -> 1.0555237e+10
E15: Public Transport (+33%) | I15: 0.07 | J15: =I15*H$9 -> 140 | K15: =K14 -> 1 | L15: =J15*K15 -> 140 | M15: 1 | N15: =L15*M15 -> 140 | O15: ='Parameters and Summary'!E79 -> 1 | P15: =N15*O15 -> 140 | Q15: =Q14 -> 15 | R15: =R14 -> 1500 | S15: =R15*P15*Q15 -> 3150000 | T15: 6 | U15: =Q15 -> 15 | V15: =T15*P15 -> 840 | W15: =V15*R15*U15 -> 18900000 | X15: 24 | Y15: =U15 -> 15 | Z15: =X15*P15*Y15 -> 50400 | AA15: =Z15*R15 -> 75600000 | AB15: =X15*12 -> 288 | AC15: =Y15 -> 15 | AD15: =AB15*P15*AC15 -> 604800 | AE15: =AD15*R15 -> 907200000 | AH15: 0.07 | AI15: =AH15*AG$9 -> 280 | AJ15: =AJ14 -> 1 | AK15: =AI15*AJ15 -> 280 | AL15: 1 | AM15: =AK15*AL15 -> 280 | AN15: ='Parameters and Summary'!E79 -> 1 | AO15: =AM15*AN15 -> 280 | AP15: =AP14 -> 15 | AQ15: =AQ14 -> 1575 | AR15: =AQ15*AO15*AP15 -> 6615000 | AS15: 6 | AT15: =AP15 -> 15 | AU15: =AS15*AO15 -> 1680 | AV15: =AU15*AQ15*AT15 -> 39690000 | AW15: 24 | AX15: =AT15 -> 15 | AY15: =AW15*AO15*AX15 -> 100800 | AZ15: =AY15*AQ15 -> 158760000 | BA15: =AW15*12 -> 288 | BB15: =AX15 -> 15 | BC15: =BA15*AO15*BB15 -> 1209600 | BD15: =BC15*AQ15 -> 1905120000 | BG15: 0.07 | BH15: =BG15*BF$9 -> 420 | BI15: =BI14 -> 1 | BJ15: =BH15*BI15 -> 420 | BK15: 1 | BL15: =BJ15*BK15 -> 420 | BM15: ='Parameters and Summary'!E79 -> 1 | BN15: =BL15*BM15 -> 420 | BO15: =BO14 -> 15 | BP15: =BP14 -> 1653.75 | BQ15: =BP15*BN15*BO15 -> 10418625 | BR15: 6 | BS15: =BO15 -> 15 | BT15: =BR15*BN15 -> 2520 | BU15: =BT15*BP15*BS15 -> 62511750 | BV15: 24 | BW15: =BS15 -> 15 | BX15: =BV15*BN15*BW15 -> 151200 | BY15: =BX15*BP15 -> 2.50047e+08 | BZ15: =BV15*12 -> 288 | CA15: =BW15 -> 15 | CB15: =BZ15*BN15*CA15 -> 1814400 | CC15: =CB15*BP15 -> 3.000564e+09 | CF15: 0.07 | CG15: =CF15*CE$9 -> 560 | CH15: =CH14 -> 1 | CI15: =CG15*CH15 -> 560 | CJ15: 1 | CK15: =CI15*CJ15 -> 560 | CL15: =CL14 -> 1 | CM15: =CK15*CL15 -> 560 | CN15: =CN14 -> 15 | CO15: =CO14 -> 1736.4375 | CP15: =CO15*CM15*CN15 -> 14586075 | CQ15: 6 | CR15: =CN15 -> 15 | CS15: =CQ15*CM15 -> 3360 | CT15: =CS15*CO15*CR15 -> 87516450 | CU15: 24 | CV15: =CR15 -> 15 | CW15: =CU15*CM15*CV15 -> 201600 | CX15: =CW15*CO15 -> 350065800 | CY15: =CU15*12 -> 288 | CZ15: =CV15 -> 15 | DA15: =CY15*CM15*CZ15 -> 2419200 | DB15: =DA15*CO15 -> 4200789600 | DE15: 0.07 | DF15: =DE15*DD$9 -> 700 | DG15: =DG14 -> 1 | DH15: =DF15*DG15 -> 700 | DI15: 1 | DJ15: =DH15*DI15 -> 700 | DK15: ='Parameters and Summary'!E79 -> 1 | DL15: =DJ15*DK15 -> 700 | DM15: =DM14 -> 15 | DN15: =DN14 -> 1823.2594 | DO15: =DN15*DL15*DM15 -> 19144223 | DP15: 6 | DQ15: =DM15 -> 15 | DR15: =DP15*DL15 -> 4200 | DS15: =DR15*DN15*DQ15 -> 1.1486534e+08 | DT15: 24 | DU15: =DQ15 -> 15 | DV15: =DT15*DL15*DU15 -> 252000 | DW15: =DV15*DN15 -> 4.5946136e+08 | DX15: =DT15*12 -> 288 | DY15: =DU15 -> 15 | DZ15: =DX15*DL15*DY15 -> 3024000 | EA15: =DZ15*DN15 -> 5.5135364e+09 | ED15: 0.07 | EE15: =ED15*EC$9 -> 700 | EF15: =EF14 -> 1 | EG15: =EE15*EF15 -> 700 | EH15: 1 | EI15: =EG15*EH15 -> 700 | EJ15: ='Parameters and Summary'!E79 -> 1 | EK15: =EI15*EJ15 -> 700 | EL15: =EL14 -> 15 | EM15: =EM14 -> 1914.4223 | EN15: =EM15*EK15*EL15 -> 20101435 | EO15: 6 | EP15: =EL15 -> 15 | EQ15: =EO15*EK15 -> 4200 | ER15: =EQ15*EM15*EP15 -> 1.2060861e+08 | ES15: 24 | ET15: =EP15 -> 15 | EU15: =ES15*EK15*ET15 -> 252000 | EV15: =EU15*EM15 -> 4.8243443e+08 | EW15: =ES15*12 -> 288 | EX15: =ET15 -> 15 | EY15: =EW15*EK15*EX15 -> 3024000 | EZ15: =EY15*EM15 -> 5.7892132e+09 | FC15: 0.07 | FD15: =FC15*FB$9 -> 700 | FE15: =FE14 -> 1 | FF15: =FD15*FE15 -> 700 | FG15: 1 | FH15: =FF15*FG15 -> 700 | FI15: ='Parameters and Summary'!E79 -> 1 | FJ15: =FH15*FI15 -> 700 | FK15: =FK14 -> 15 | FL15: =FL14 -> 2010.1435 | FM15: =FL15*FJ15*FK15 -> 21106506 | FN15: 6 | FO15: =FK15 -> 15 | FP15: =FN15*FJ15 -> 4200 | FQ15: =FP15*FL15*FO15 -> 1.2663904e+08 | FR15: 24 | FS15: =FO15 -> 15 | FT15: =FR15*FJ15*FS15 -> 252000 | FU15: =FT15*FL15 -> 5.0655615e+08 | FV15: =FR15*12 -> 288 | FW15: =FS15 -> 15 | FX15: =FV15*FJ15*FW15 -> 3024000 | FY15: =FX15*FL15 -> 6.0786738e+09 | GB15: 0.07 | GC15: =GB15*GA$9 -> 700 | GD15: =GD14 -> 1 | GE15: =GC15*GD15 -> 700 | GF15: 1 | GG15: =GE15*GF15 -> 700 | GH15: ='Parameters and Summary'!E79 -> 1 | GI15: =GG15*GH15 -> 700 | GJ15: =GJ14 -> 15 | GK15: =GK14 -> 2110.6506 | GL15: =GK15*GI15*GJ15 -> 22161832 | GM15: 6 | GN15: =GJ15 -> 15 | GO15: =GM15*GI15 -> 4200 | GP15: =GO15*GK15*GN15 -> 1.3297099e+08 | GQ15: 24 | GR15: =GN15 -> 15 | GS15: =GQ15*GI15*GR15 -> 252000 | GT15: =GS15*GK15 -> 5.3188396e+08 | GU15: =GQ15*12 -> 288 | GV15: =GR15 -> 15 | GW15: =GU15*GI15*GV15 -> 3024000 | GX15: =GW15*GK15 -> 6.3826075e+09 | HA15: 0.07 | HB15: =HA15*GZ$9 -> 700 | HC15: =HC14 -> 1 | HD15: =HB15*HC15 -> 700 | HE15: 1 | HF15: =HD15*HE15 -> 700 | HG15: ='Parameters and Summary'!E79 -> 1 | HH15: =HF15*HG15 -> 700 | HI15: =HI14 -> 15 | HJ15: =HJ14 -> 2216.1832 | HK15: =HJ15*HH15*HI15 -> 23269923 | HL15: 6 | HM15: =HI15 -> 15 | HN15: =HL15*HH15 -> 4200 | HO15: =HN15*HJ15*HM15 -> 1.3961954e+08 | HP15: 24 | HQ15: =HM15 -> 15 | HR15: =HP15*HH15*HQ15 -> 252000 | HS15: =HR15*HJ15 -> 5.5847816e+08 | HT15: =HP15*12 -> 288 | HU15: =HQ15 -> 15 | HV15: =HT15*HH15*HU15 -> 3024000 | HW15: =HV15*HJ15 -> 6.7017379e+09 | HZ15: 0.07 | IA15: =HZ15*HY$9 -> 700 | IB15: =IB14 -> 1 | IC15: =IA15*IB15 -> 700 | ID15: 1 | IE15: =IC15*ID15 -> 700 | IF15: ='Parameters and Summary'!E79 -> 1 | IG15: =IE15*IF15 -> 700 | IH15: =IH14 -> 15 | II15: =II14 -> 2326.9923 | IJ15: =II15*IG15*IH15 -> 24433419 | IK15: 6 | IL15: =IH15 -> 15 | IM15: =IK15*IG15 -> 4200 | IN15: =IM15*II15*IL15 -> 1.4660052e+08 | IO15: 24 | IP15: =IL15 -> 15 | IQ15: =IO15*IG15*IP15 -> 252000 | IR15: =IQ15*II15 -> 5.8640207e+08 | IS15: =IO15*12 -> 288 | IT15: =IP15 -> 15 | IU15: =IS15*IG15*IT15 -> 3024000 | IV15: =IU15*II15 -> 7.0368248e+09
B16: 2 | C16: 8 | D16: 6pm - 9pm | F16: Off peak | G16: =D16 -> 6pm - 9pm | H16: =H9 -> 2000 | I16: 0.75 | J16: =H16*I16 -> 1500 | M16: 1 | N16: =J16*M16 -> 1500 | S16: =SUM(S10:S15)/N9 -> 22500 | AG16: =AG9 -> 4000 | AH16: 0.75 | AI16: =AG16*AH16 -> 3000 | AL16: 1 | AM16: =AI16*AL16 -> 3000 | AR16: =SUM(AR10:AR15)/4000 -> 23625 | BF16: =BF9 -> 6000 | BG16: 0.75 | BH16: =BF16*BG16 -> 4500 | BK16: 1 | BL16: =BH16*BK16 -> 4500 | BQ16: =SUM(BQ10:BQ15)/BL9 -> 24806.25 | CE16: =CE9 -> 8000 | CF16: 0.75 | CG16: =CE16*CF16 -> 6000 | CJ16: 1 | CK16: =CG16*CJ16 -> 6000 | DD16: =DD9 -> 10000 | DE16: 0.75 | DF16: =DD16*DE16 -> 7500 | DI16: 1 | DJ16: =DF16*DI16 -> 7500 | EC16: =EC9 -> 10000 | ED16: 0.75 | EE16: =EC16*ED16 -> 7500 | EH16: 1 | EI16: =EE16*EH16 -> 7500 | FB16: =FB9 -> 10000 | FC16: 0.75 | FD16: =FB16*FC16 -> 7500 | FG16: 1 | FH16: =FD16*FG16 -> 7500 | GA16: =GA9 -> 10000 | GB16: 0.75 | GC16: =GA16*GB16 -> 7500 | GF16: 1 | GG16: =GC16*GF16 -> 7500 | GZ16: =GZ9 -> 10000 | HA16: 0.75 | HB16: =GZ16*HA16 -> 7500 | HE16: 1 | HF16: =HB16*HE16 -> 7500 | HY16: =HY9 -> 10000 | HZ16: 0.75 | IA16: =HY16*HZ16 -> 7500 | ID16: 1 | IE16: =IA16*ID16 -> 7500
E17: Retail and Recreation (+56%) | I17: 0.21 | J17: =I17*H$16 -> 420 | K17: 0.75 | L17: =J17*K17 -> 315 | M17: 1 | N17: =L17*M17 -> 315 | O17: ='Parameters and Summary'!E74 -> 1 | P17: =N17*O17 -> 315 | Q17: 3 | R17: =R10 -> 1500 | S17: =R17*P17*Q17 -> 1417500 | T17: =T10 -> 6 | U17: =Q17 -> 3 | V17: =T17*P17 -> 1890 | W17: =V17*R17*U17 -> 8505000 | X17: =X10 -> 24 | Y17: =U17 -> 3 | Z17: =X17*P17*Y17 -> 22680 | AA17: =Z17*R17 -> 34020000 | AB17: =AB10 -> 288 | AC17: =Y17 -> 3 | AD17: =AB17*P17*AC17 -> 272160 | AE17: =AD17*R17 -> 408240000 | AH17: 0.21 | AI17: =AH17*AG$16 -> 840 | AJ17: 0.75 | AK17: =AI17*AJ17 -> 630 | AL17: 1 | AM17: =AK17*AL17 -> 630 | AN17: =AN10 -> 1 | AO17: =AM17*AN17 -> 630 | AP17: 3 | AQ17: =AQ10 -> 1575 | AR17: =AQ17*AO17*AP17 -> 2976750 | AS17: =AS10 -> 6 | AT17: =AP17 -> 3 | AU17: =AS17*AO17 -> 3780 | AV17: =AU17*AQ17*AT17 -> 17860500 | AW17: =AW10 -> 24 | AX17: =AT17 -> 3 | AY17: =AW17*AO17*AX17 -> 45360 | AZ17: =AY17*AQ17 -> 71442000 | BA17: =BA10 -> 288 | BB17: =AX17 -> 3 | BC17: =BA17*AO17*BB17 -> 544320 | BD17: =BC17*AQ17 -> 857304000 | BG17: 0.21 | BH17: =BG17*BF$16 -> 1260 | BI17: 0.75 | BJ17: =BH17*BI17 -> 945 | BK17: 1 | BL17: =BJ17*BK17 -> 945 | BM17: =BM10 -> 1 | BN17: =BL17*BM17 -> 945 | BO17: 3 | BP17: =BP10 -> 1653.75 | BQ17: =BP17*BN17*BO17 -> 4688381.2 | BR17: =BR10 -> 6 | BS17: =BO17 -> 3 | BT17: =BR17*BN17 -> 5670 | BU17: =BT17*BP17*BS17 -> 28130288 | BV17: =BV10 -> 24 | BW17: =BS17 -> 3 | BX17: =BV17*BN17*BW17 -> 68040 | BY17: =BX17*BP17 -> 112521150 | BZ17: =BZ10 -> 288 | CA17: =BW17 -> 3 | CB17: =BZ17*BN17*CA17 -> 816480 | CC17: =CB17*BP17 -> 1350253800 | CF17: 0.21 | CG17: =CF17*CE$16 -> 1680 | CH17: 0.75 | CI17: =CG17*CH17 -> 1260 | CJ17: 1 | CK17: =CI17*CJ17 -> 1260 | CL17: =CL10 -> 1 | CM17: =CK17*CL17 -> 1260 | CN17: 3 | CO17: =CO10 -> 1736.4375 | CP17: =CO17*CM17*CN17 -> 6563733.8 | CQ17: =CQ10 -> 6 | CR17: =CN17 -> 3 | CS17: =CQ17*CM17 -> 7560 | CT17: =CS17*CO17*CR17 -> 39382402 | CU17: =CU10 -> 24 | CV17: =CR17 -> 3 | CW17: =CU17*CM17*CV17 -> 90720 | CX17: =CW17*CO17 -> 157529610 | CY17: =CY10 -> 288 | CZ17: =CV17 -> 3 | DA17: =CY17*CM17*CZ17 -> 1088640 | DB17: =DA17*CO17 -> 1890355320 | DE17: 0.21 | DF17: =DE17*DD$16 -> 2100 | DG17: 0.75 | DH17: =DF17*DG17 -> 1575 | DI17: 1 | DJ17: =DH17*DI17 -> 1575 | DK17: =DK10 -> 1 | DL17: =DJ17*DK17 -> 1575 | DM17: 3 | DN17: =DN10 -> 1823.2594 | DO17: =DN17*DL17*DM17 -> 8614900.5 | DP17: =DP10 -> 6 | DQ17: =DM17 -> 3 | DR17: =DP17*DL17 -> 9450 | DS17: =DR17*DN17*DQ17 -> 51689403 | DT17: =DT10 -> 24 | DU17: =DQ17 -> 3 | DV17: =DT17*DL17*DU17 -> 113400 | DW17: =DV17*DN17 -> 2.0675761e+08 | DX17: =DX10 -> 288 | DY17: =DU17 -> 3 | DZ17: =DX17*DL17*DY17 -> 1360800 | EA17: =DZ17*DN17 -> 2.4810914e+09 | ED17: 0.21 | EE17: =ED17*EC$16 -> 2100 | EF17: 0.75 | EG17: =EE17*EF17 -> 1575 | EH17: 1 | EI17: =EG17*EH17 -> 1575 | EJ17: =EJ10 -> 1 | EK17: =EI17*EJ17 -> 1575 | EL17: 3 | EM17: =EM10 -> 1914.4223 | EN17: =EM17*EK17*EL17 -> 9045645.6 | EO17: =EO10 -> 6 | EP17: =EL17 -> 3 | EQ17: =EO17*EK17 -> 9450 | ER17: =EQ17*EM17*EP17 -> 54273873 | ES17: =ES10 -> 24 | ET17: =EP17 -> 3 | EU17: =ES17*EK17*ET17 -> 113400 | EV17: =EU17*EM17 -> 2.1709549e+08 | EW17: =EW10 -> 288 | EX17: =ET17 -> 3 | EY17: =EW17*EK17*EX17 -> 1360800 | EZ17: =EY17*EM17 -> 2.6051459e+09 | FC17: 0.21 | FD17: =FC17*FB$16 -> 2100 | FE17: 0.75 | FF17: =FD17*FE17 -> 1575 | FG17: 1 | FH17: =FF17*FG17 -> 1575 | FI17: =FI10 -> 1 | FJ17: =FH17*FI17 -> 1575 | FK17: 3 | FL17: =FL10 -> 2010.1435 | FM17: =FL17*FJ17*FK17 -> 9497927.9 | FN17: =FN10 -> 6 | FO17: =FK17 -> 3 | FP17: =FN17*FJ17 -> 9450 | FQ17: =FP17*FL17*FO17 -> 56987567 | FR17: =FR10 -> 24 | FS17: =FO17 -> 3 | FT17: =FR17*FJ17*FS17 -> 113400 | FU17: =FT17*FL17 -> 2.2795027e+08 | FV17: =FV10 -> 288 | FW17: =FS17 -> 3 | FX17: =FV17*FJ17*FW17 -> 1360800 | FY17: =FX17*FL17 -> 2.7354032e+09 | GB17: 0.21 | GC17: =GB17*GA$16 -> 2100 | GD17: 0.75 | GE17: =GC17*GD17 -> 1575 | GF17: 1 | GG17: =GE17*GF17 -> 1575 | GH17: =GH10 -> 1 | GI17: =GG17*GH17 -> 1575 | GJ17: 3 | GK17: =GK10 -> 2110.6506 | GL17: =GK17*GI17*GJ17 -> 9972824.2 | GM17: =GM10 -> 6 | GN17: =GJ17 -> 3 | GO17: =GM17*GI17 -> 9450 | GP17: =GO17*GK17*GN17 -> 59836945 | GQ17: =GQ10 -> 24 | GR17: =GN17 -> 3 | GS17: =GQ17*GI17*GR17 -> 113400 | GT17: =GS17*GK17 -> 2.3934778e+08 | GU17: =GU10 -> 288 | GV17: =GR17 -> 3 | GW17: =GU17*GI17*GV17 -> 1360800 | GX17: =GW17*GK17 -> 2.8721734e+09 | HA17: 0.21 | HB17: =HA17*GZ$16 -> 2100 | HC17: 0.75 | HD17: =HB17*HC17 -> 1575 | HE17: 1 | HF17: =HD17*HE17 -> 1575 | HG17: =HG10 -> 1 | HH17: =HF17*HG17 -> 1575 | HI17: 3 | HJ17: =HJ10 -> 2216.1832 | HK17: =HJ17*HH17*HI17 -> 10471465 | HL17: =HL10 -> 6 | HM17: =HI17 -> 3 | HN17: =HL17*HH17 -> 9450 | HO17: =HN17*HJ17*HM17 -> 62828793 | HP17: =HP10 -> 24 | HQ17: =HM17 -> 3 | HR17: =HP17*HH17*HQ17 -> 113400 | HS17: =HR17*HJ17 -> 2.5131517e+08 | HT17: =HT10 -> 288 | HU17: =HQ17 -> 3 | HV17: =HT17*HH17*HU17 -> 1360800 | HW17: =HV17*HJ17 -> 3.0157821e+09 | HZ17: 0.21 | IA17: =HZ17*HY$16 -> 2100 | IB17: 0.75 | IC17: =IA17*IB17 -> 1575 | ID17: 1 | IE17: =IC17*ID17 -> 1575 | IF17: =IF10 -> 1 | IG17: =IE17*IF17 -> 1575 | IH17: 3 | II17: =II10 -> 2326.9923 | IJ17: =II17*IG17*IH17 -> 10995039 | IK17: =IK10 -> 6 | IL17: =IH17 -> 3 | IM17: =IK17*IG17 -> 9450 | IN17: =IM17*II17*IL17 -> 65970232 | IO17: =IO10 -> 24 | IP17: =IL17 -> 3 | IQ17: =IO17*IG17*IP17 -> 113400 | IR17: =IQ17*II17 -> 2.6388093e+08 | IS17: =IS10 -> 288 | IT17: =IP17 -> 3 | IU17: =IS17*IG17*IT17 -> 1360800 | IV17: =IU17*II17 -> 3.1665712e+09
E18: Supermarket and Pharmacy (+75%) | I18: 0.3 | J18: =I18*H$16 -> 600 | K18: =K17 -> 0.75 | L18: =J18*K18 -> 450 | M18: 1 | N18: =L18*M18 -> 450 | O18: ='Parameters and Summary'!E75 -> 1 | P18: =N18*O18 -> 450 | Q18: =Q17 -> 3 | R18: =R11 -> 1500 | S18: =R18*P18*Q18 -> 2025000 | T18: =T11 -> 6 | U18: =Q18 -> 3 | V18: =T18*P18 -> 2700 | W18: =V18*R18*U18 -> 12150000 | X18: =X11 -> 24 | Y18: =U18 -> 3 | Z18: =X18*P18*Y18 -> 32400 | AA18: =Z18*R18 -> 48600000 | AB18: =AB11 -> 288 | AC18: =Y18 -> 3 | AD18: =AB18*P18*AC18 -> 388800 | AE18: =AD18*R18 -> 583200000 | AH18: 0.3 | AI18: =AH18*AG$16 -> 1200 | AJ18: =AJ17 -> 0.75 | AK18: =AI18*AJ18 -> 900 | AL18: 1 | AM18: =AK18*AL18 -> 900 | AN18: =AN11 -> 1 | AO18: =AM18*AN18 -> 900 | AP18: =AP17 -> 3 | AQ18: =AQ11 -> 1575 | AR18: =AQ18*AO18*AP18 -> 4252500 | AS18: =AS11 -> 6 | AT18: =AP18 -> 3 | AU18: =AS18*AO18 -> 5400 | AV18: =AU18*AQ18*AT18 -> 25515000 | AW18: =AW11 -> 24 | AX18: =AT18 -> 3 | AY18: =AW18*AO18*AX18 -> 64800 | AZ18: =AY18*AQ18 -> 102060000 | BA18: =BA11 -> 288 | BB18: =AX18 -> 3 | BC18: =BA18*AO18*BB18 -> 777600 | BD18: =BC18*AQ18 -> 1224720000 | BG18: 0.3 | BH18: =BG18*BF$16 -> 1800 | BI18: =BI17 -> 0.75 | BJ18: =BH18*BI18 -> 1350 | BK18: 1 | BL18: =BJ18*BK18 -> 1350 | BM18: =BM11 -> 1 | BN18: =BL18*BM18 -> 1350 | BO18: =BO17 -> 3 | BP18: =BP11 -> 1653.75 | BQ18: =BP18*BN18*BO18 -> 6697687.5 | BR18: =BR11 -> 6 | BS18: =BO18 -> 3 | BT18: =BR18*BN18 -> 8100 | BU18: =BT18*BP18*BS18 -> 40186125 | BV18: =BV11 -> 24 | BW18: =BS18 -> 3 | BX18: =BV18*BN18*BW18 -> 97200 | BY18: =BX18*BP18 -> 160744500 | BZ18: =BZ11 -> 288 | CA18: =BW18 -> 3 | CB18: =BZ18*BN18*CA18 -> 1166400 | CC18: =CB18*BP18 -> 1928934000 | CF18: 0.3 | CG18: =CF18*CE$16 -> 2400 | CH18: =CH17 -> 0.75 | CI18: =CG18*CH18 -> 1800 | CJ18: 1 | CK18: =CI18*CJ18 -> 1800 | CL18: =CL11 -> 1 | CM18: =CK18*CL18 -> 1800 | CN18: =CN17 -> 3 | CO18: =CO11 -> 1736.4375 | CP18: =CO18*CM18*CN18 -> 9376762.5 | CQ18: =CQ11 -> 6 | CR18: =CN18 -> 3 | CS18: =CQ18*CM18 -> 10800 | CT18: =CS18*CO18*CR18 -> 56260575 | CU18: =CU11 -> 24 | CV18: =CR18 -> 3 | CW18: =CU18*CM18*CV18 -> 129600 | CX18: =CW18*CO18 -> 225042300 | CY18: =CY11 -> 288 | CZ18: =CV18 -> 3 | DA18: =CY18*CM18*CZ18 -> 1555200 | DB18: =DA18*CO18 -> 2700507600 | DE18: 0.3 | DF18: =DE18*DD$16 -> 3000 | DG18: =DG17 -> 0.75 | DH18: =DF18*DG18 -> 2250 | DI18: 1 | DJ18: =DH18*DI18 -> 2250 | DK18: =DK11 -> 1 | DL18: =DJ18*DK18 -> 2250 | DM18: =DM17 -> 3 | DN18: =DN11 -> 1823.2594 | DO18: =DN18*DL18*DM18 -> 12307001 | DP18: =DP11 -> 6 | DQ18: =DM18 -> 3 | DR18: =DP18*DL18 -> 13500 | DS18: =DR18*DN18*DQ18 -> 73842005 | DT18: =DT11 -> 24 | DU18: =DQ18 -> 3 | DV18: =DT18*DL18*DU18 -> 162000 | DW18: =DV18*DN18 -> 2.9536802e+08 | DX18: =DX11 -> 288 | DY18: =DU18 -> 3 | DZ18: =DX18*DL18*DY18 -> 1944000 | EA18: =DZ18*DN18 -> 3544416225 | ED18: 0.3 | EE18: =ED18*EC$16 -> 3000 | EF18: =EF17 -> 0.75 | EG18: =EE18*EF18 -> 2250 | EH18: 1 | EI18: =EG18*EH18 -> 2250 | EJ18: =EJ11 -> 1 | EK18: =EI18*EJ18 -> 2250 | EL18: =EL17 -> 3 | EM18: =EM11 -> 1914.4223 | EN18: =EM18*EK18*EL18 -> 12922351 | EO18: =EO11 -> 6 | EP18: =EL18 -> 3 | EQ18: =EO18*EK18 -> 13500 | ER18: =EQ18*EM18*EP18 -> 77534105 | ES18: =ES11 -> 24 | ET18: =EP18 -> 3 | EU18: =ES18*EK18*ET18 -> 162000 | EV18: =EU18*EM18 -> 3.1013642e+08 | EW18: =EW11 -> 288 | EX18: =ET18 -> 3 | EY18: =EW18*EK18*EX18 -> 1944000 | EZ18: =EY18*EM18 -> 3.721637e+09 | FC18: 0.3 | FD18: =FC18*FB$16 -> 3000 | FE18: =FE17 -> 0.75 | FF18: =FD18*FE18 -> 2250 | FG18: 1 | FH18: =FF18*FG18 -> 2250 | FI18: =FI11 -> 1 | FJ18: =FH18*FI18 -> 2250 | FK18: =FK17 -> 3 | FL18: =FL11 -> 2010.1435 | FM18: =FL18*FJ18*FK18 -> 13568468 | FN18: =FN11 -> 6 | FO18: =FK18 -> 3 | FP18: =FN18*FJ18 -> 13500 | FQ18: =FP18*FL18*FO18 -> 81410810 | FR18: =FR11 -> 24 | FS18: =FO18 -> 3 | FT18: =FR18*FJ18*FS18 -> 162000 | FU18: =FT18*FL18 -> 3.2564324e+08 | FV18: =FV11 -> 288 | FW18: =FS18 -> 3 | FX18: =FV18*FJ18*FW18 -> 1944000 | FY18: =FX18*FL18 -> 3.9077189e+09 | GB18: 0.3 | GC18: =GB18*GA$16 -> 3000 | GD18: =GD17 -> 0.75 | GE18: =GC18*GD18 -> 2250 | GF18: 1 | GG18: =GE18*GF18 -> 2250 | GH18: =GH11 -> 1 | GI18: =GG18*GH18 -> 2250 | GJ18: =GJ17 -> 3 | GK18: =GK11 -> 2110.6506 | GL18: =GK18*GI18*GJ18 -> 14246892 | GM18: =GM11 -> 6 | GN18: =GJ18 -> 3 | GO18: =GM18*GI18 -> 13500 | GP18: =GO18*GK18*GN18 -> 85481351 | GQ18: =GQ11 -> 24 | GR18: =GN18 -> 3 | GS18: =GQ18*GI18*GR18 -> 162000 | GT18: =GS18*GK18 -> 3.419254e+08 | GU18: =GU11 -> 288 | GV18: =GR18 -> 3 | GW18: =GU18*GI18*GV18 -> 1944000 | GX18: =GW18*GK18 -> 4.1031048e+09 | HA18: 0.3 | HB18: =HA18*GZ$16 -> 3000 | HC18: =HC17 -> 0.75 | HD18: =HB18*HC18 -> 2250 | HE18: 1 | HF18: =HD18*HE18 -> 2250 | HG18: =HG11 -> 1 | HH18: =HF18*HG18 -> 2250 | HI18: =HI17 -> 3 | HJ18: =HJ11 -> 2216.1832 | HK18: =HJ18*HH18*HI18 -> 14959236 | HL18: =HL11 -> 6 | HM18: =HI18 -> 3 | HN18: =HL18*HH18 -> 13500 | HO18: =HN18*HJ18*HM18 -> 89755418 | HP18: =HP11 -> 24 | HQ18: =HM18 -> 3 | HR18: =HP18*HH18*HQ18 -> 162000 | HS18: =HR18*HJ18 -> 3.5902167e+08 | HT18: =HT11 -> 288 | HU18: =HQ18 -> 3 | HV18: =HT18*HH18*HU18 -> 1944000 | HW18: =HV18*HJ18 -> 4.3082601e+09 | HZ18: 0.3 | IA18: =HZ18*HY$16 -> 3000 | IB18: =IB17 -> 0.75 | IC18: =IA18*IB18 -> 2250 | ID18: 1 | IE18: =IC18*ID18 -> 2250 | IF18: =IF11 -> 1 | IG18: =IE18*IF18 -> 2250 | IH18: =IH17 -> 3 | II18: =II11 -> 2326.9923 | IJ18: =II18*IG18*IH18 -> 15707198 | IK18: =IK11 -> 6 | IL18: =IH18 -> 3 | IM18: =IK18*IG18 -> 13500 | IN18: =IM18*II18*IL18 -> 94243189 | IO18: =IO11 -> 24 | IP18: =IL18 -> 3 | IQ18: =IO18*IG18*IP18 -> 162000 | IR18: =IQ18*II18 -> 3.7697276e+08 | IS18: =IS11 -> 288 | IT18: =IP18 -> 3 | IU18: =IS18*IG18*IT18 -> 1944000 | IV18: =IU18*II18 -> 4.5236731e+09
E19: Parks (+43%) | I19: 0.14 | J19: =I19*H$16 -> 280 | K19: =K18 -> 0.75 | L19: =J19*K19 -> 210 | M19: 1 | N19: =L19*M19 -> 210 | O19: ='Parameters and Summary'!E76 -> 1 | P19: =N19*O19 -> 210 | Q19: =Q18 -> 3 | R19: =R12 -> 1500 | S19: =R19*P19*Q19 -> 945000 | T19: =T12 -> 6 | U19: =Q19 -> 3 | V19: =T19*P19 -> 1260 | W19: =V19*R19*U19 -> 5670000 | X19: =X12 -> 24 | Y19: =U19 -> 3 | Z19: =X19*P19*Y19 -> 15120 | AA19: =Z19*R19 -> 22680000 | AB19: =AB12 -> 288 | AC19: =Y19 -> 3 | AD19: =AB19*P19*AC19 -> 181440 | AE19: =AD19*R19 -> 272160000 | AH19: 0.14 | AI19: =AH19*AG$16 -> 560 | AJ19: =AJ18 -> 0.75 | AK19: =AI19*AJ19 -> 420 | AL19: 1 | AM19: =AK19*AL19 -> 420 | AN19: =AN12 -> 1 | AO19: =AM19*AN19 -> 420 | AP19: =AP18 -> 3 | AQ19: =AQ12 -> 1575 | AR19: =AQ19*AO19*AP19 -> 1984500 | AS19: =AS12 -> 6 | AT19: =AP19 -> 3 | AU19: =AS19*AO19 -> 2520 | AV19: =AU19*AQ19*AT19 -> 11907000 | AW19: =AW12 -> 24 | AX19: =AT19 -> 3 | AY19: =AW19*AO19*AX19 -> 30240 | AZ19: =AY19*AQ19 -> 47628000 | BA19: =BA12 -> 288 | BB19: =AX19 -> 3 | BC19: =BA19*AO19*BB19 -> 362880 | BD19: =BC19*AQ19 -> 571536000 | BG19: 0.14 | BH19: =BG19*BF$16 -> 840 | BI19: =BI18 -> 0.75 | BJ19: =BH19*BI19 -> 630 | BK19: 1 | BL19: =BJ19*BK19 -> 630 | BM19: =BM12 -> 1 | BN19: =BL19*BM19 -> 630 | BO19: =BO18 -> 3 | BP19: =BP12 -> 1653.75 | BQ19: =BP19*BN19*BO19 -> 3125587.5 | BR19: =BR12 -> 6 | BS19: =BO19 -> 3 | BT19: =BR19*BN19 -> 3780 | BU19: =BT19*BP19*BS19 -> 18753525 | BV19: =BV12 -> 24 | BW19: =BS19 -> 3 | BX19: =BV19*BN19*BW19 -> 45360 | BY19: =BX19*BP19 -> 75014100 | BZ19: =BZ12 -> 288 | CA19: =BW19 -> 3 | CB19: =BZ19*BN19*CA19 -> 544320 | CC19: =CB19*BP19 -> 9.001692e+08 | CF19: 0.14 | CG19: =CF19*CE$16 -> 1120 | CH19: =CH18 -> 0.75 | CI19: =CG19*CH19 -> 840 | CJ19: 1 | CK19: =CI19*CJ19 -> 840 | CL19: =CL12 -> 1 | CM19: =CK19*CL19 -> 840 | CN19: =CN18 -> 3 | CO19: =CO12 -> 1736.4375 | CP19: =CO19*CM19*CN19 -> 4375822.5 | CQ19: =CQ12 -> 6 | CR19: =CN19 -> 3 | CS19: =CQ19*CM19 -> 5040 | CT19: =CS19*CO19*CR19 -> 26254935 | CU19: =CU12 -> 24 | CV19: =CR19 -> 3 | CW19: =CU19*CM19*CV19 -> 60480 | CX19: =CW19*CO19 -> 105019740 | CY19: =CY12 -> 288 | CZ19: =CV19 -> 3 | DA19: =CY19*CM19*CZ19 -> 725760 | DB19: =DA19*CO19 -> 1260236880 | DE19: 0.14 | DF19: =DE19*DD$16 -> 1400 | DG19: =DG18 -> 0.75 | DH19: =DF19*DG19 -> 1050 | DI19: 1 | DJ19: =DH19*DI19 -> 1050 | DK19: =DK12 -> 1 | DL19: =DJ19*DK19 -> 1050 | DM19: =DM18 -> 3 | DN19: =DN12 -> 1823.2594 | DO19: =DN19*DL19*DM19 -> 5743267 | DP19: =DP12 -> 6 | DQ19: =DM19 -> 3 | DR19: =DP19*DL19 -> 6300 | DS19: =DR19*DN19*DQ19 -> 34459602 | DT19: =DT12 -> 24 | DU19: =DQ19 -> 3 | DV19: =DT19*DL19*DU19 -> 75600 | DW19: =DV19*DN19 -> 1.3783841e+08 | DX19: =DX12 -> 288 | DY19: =DU19 -> 3 | DZ19: =DX19*DL19*DY19 -> 907200 | EA19: =DZ19*DN19 -> 1.6540609e+09 | ED19: 0.14 | EE19: =ED19*EC$16 -> 1400 | EF19: =EF18 -> 0.75 | EG19: =EE19*EF19 -> 1050 | EH19: 1 | EI19: =EG19*EH19 -> 1050 | EJ19: =EJ12 -> 1 | EK19: =EI19*EJ19 -> 1050 | EL19: =EL18 -> 3 | EM19: =EM12 -> 1914.4223 | EN19: =EM19*EK19*EL19 -> 6030430.4 | EO19: =EO12 -> 6 | EP19: =EL19 -> 3 | EQ19: =EO19*EK19 -> 6300 | ER19: =EQ19*EM19*EP19 -> 36182582 | ES19: =ES12 -> 24 | ET19: =EP19 -> 3 | EU19: =ES19*EK19*ET19 -> 75600 | EV19: =EU19*EM19 -> 1.4473033e+08 | EW19: =EW12 -> 288 | EX19: =ET19 -> 3 | EY19: =EW19*EK19*EX19 -> 907200 | EZ19: =EY19*EM19 -> 1.736764e+09 | FC19: 0.14 | FD19: =FC19*FB$16 -> 1400 | FE19: =FE18 -> 0.75 | FF19: =FD19*FE19 -> 1050 | FG19: 1 | FH19: =FF19*FG19 -> 1050 | FI19: =FI12 -> 1 | FJ19: =FH19*FI19 -> 1050 | FK19: =FK18 -> 3 | FL19: =FL12 -> 2010.1435 | FM19: =FL19*FJ19*FK19 -> 6331951.9 | FN19: =FN12 -> 6 | FO19: =FK19 -> 3 | FP19: =FN19*FJ19 -> 6300 | FQ19: =FP19*FL19*FO19 -> 37991711 | FR19: =FR12 -> 24 | FS19: =FO19 -> 3 | FT19: =FR19*FJ19*FS19 -> 75600 | FU19: =FT19*FL19 -> 1.5196685e+08 | FV19: =FV12 -> 288 | FW19: =FS19 -> 3 | FX19: =FV19*FJ19*FW19 -> 907200 | FY19: =FX19*FL19 -> 1.8236021e+09 | GB19: 0.14 | GC19: =GB19*GA$16 -> 1400 | GD19: =GD18 -> 0.75 | GE19: =GC19*GD19 -> 1050 | GF19: 1 | GG19: =GE19*GF19 -> 1050 | GH19: =GH12 -> 1 | GI19: =GG19*GH19 -> 1050 | GJ19: =GJ18 -> 3 | GK19: =GK12 -> 2110.6506 | GL19: =GK19*GI19*GJ19 -> 6648549.5 | GM19: =GM12 -> 6 | GN19: =GJ19 -> 3 | GO19: =GM19*GI19 -> 6300 | GP19: =GO19*GK19*GN19 -> 39891297 | GQ19: =GQ12 -> 24 | GR19: =GN19 -> 3 | GS19: =GQ19*GI19*GR19 -> 75600 | GT19: =GS19*GK19 -> 1.5956519e+08 | GU19: =GU12 -> 288 | GV19: =GR19 -> 3 | GW19: =GU19*GI19*GV19 -> 907200 | GX19: =GW19*GK19 -> 1.9147823e+09 | HA19: 0.14 | HB19: =HA19*GZ$16 -> 1400 | HC19: =HC18 -> 0.75 | HD19: =HB19*HC19 -> 1050 | HE19: 1 | HF19: =HD19*HE19 -> 1050 | HG19: =HG12 -> 1 | HH19: =HF19*HG19 -> 1050 | HI19: =HI18 -> 3 | HJ19: =HJ12 -> 2216.1832 | HK19: =HJ19*HH19*HI19 -> 6980977 | HL19: =HL12 -> 6 | HM19: =HI19 -> 3 | HN19: =HL19*HH19 -> 6300 | HO19: =HN19*HJ19*HM19 -> 41885862 | HP19: =HP12 -> 24 | HQ19: =HM19 -> 3 | HR19: =HP19*HH19*HQ19 -> 75600 | HS19: =HR19*HJ19 -> 1.6754345e+08 | HT19: =HT12 -> 288 | HU19: =HQ19 -> 3 | HV19: =HT19*HH19*HU19 -> 907200 | HW19: =HV19*HJ19 -> 2.0105214e+09 | HZ19: 0.14 | IA19: =HZ19*HY$16 -> 1400 | IB19: =IB18 -> 0.75 | IC19: =IA19*IB19 -> 1050 | ID19: 1 | IE19: =IC19*ID19 -> 1050 | IF19: =IF12 -> 1 | IG19: =IE19*IF19 -> 1050 | IH19: =IH18 -> 3 | II19: =II12 -> 2326.9923 | IJ19: =II19*IG19*IH19 -> 7330025.8 | IK19: =IK12 -> 6 | IL19: =IH19 -> 3 | IM19: =IK19*IG19 -> 6300 | IN19: =IM19*II19*IL19 -> 43980155 | IO19: =IO12 -> 24 | IP19: =IL19 -> 3 | IQ19: =IO19*IG19*IP19 -> 75600 | IR19: =IQ19*II19 -> 1.7592062e+08 | IS19: =IS12 -> 288 | IT19: =IP19 -> 3 | IU19: =IS19*IG19*IT19 -> 907200 | IV19: =IU19*II19 -> 2.1110474e+09
E20: Workplaces (+73%) | I20: 0.175 | J20: =I20*H$16 -> 350 | K20: =K19 -> 0.75 | L20: =J20*K20 -> 262.5 | M20: 1 | N20: =L20*M20 -> 262.5 | O20: ='Parameters and Summary'!E77 -> 1 | P20: =N20*O20 -> 262.5 | Q20: =Q19 -> 3 | R20: =R13 -> 1500 | S20: =R20*P20*Q20 -> 1181250 | T20: =T13 -> 6 | U20: =Q20 -> 3 | V20: =T20*P20 -> 1575 | W20: =V20*R20*U20 -> 7087500 | X20: =X13 -> 24 | Y20: =U20 -> 3 | Z20: =X20*P20*Y20 -> 18900 | AA20: =Z20*R20 -> 28350000 | AB20: =AB13 -> 288 | AC20: =Y20 -> 3 | AD20: =AB20*P20*AC20 -> 226800 | AE20: =AD20*R20 -> 340200000 | AH20: 0.175 | AI20: =AH20*AG$16 -> 700 | AJ20: =AJ19 -> 0.75 | AK20: =AI20*AJ20 -> 525 | AL20: 1 | AM20: =AK20*AL20 -> 525 | AN20: =AN13 -> 1 | AO20: =AM20*AN20 -> 525 | AP20: =AP19 -> 3 | AQ20: =AQ13 -> 1575 | AR20: =AQ20*AO20*AP20 -> 2480625 | AS20: =AS13 -> 6 | AT20: =AP20 -> 3 | AU20: =AS20*AO20 -> 3150 | AV20: =AU20*AQ20*AT20 -> 14883750 | AW20: =AW13 -> 24 | AX20: =AT20 -> 3 | AY20: =AW20*AO20*AX20 -> 37800 | AZ20: =AY20*AQ20 -> 59535000 | BA20: =BA13 -> 288 | BB20: =AX20 -> 3 | BC20: =BA20*AO20*BB20 -> 453600 | BD20: =BC20*AQ20 -> 714420000 | BG20: 0.175 | BH20: =BG20*BF$16 -> 1050 | BI20: =BI19 -> 0.75 | BJ20: =BH20*BI20 -> 787.5 | BK20: 1 | BL20: =BJ20*BK20 -> 787.5 | BM20: =BM13 -> 1 | BN20: =BL20*BM20 -> 787.5 | BO20: =BO19 -> 3 | BP20: =BP13 -> 1653.75 | BQ20: =BP20*BN20*BO20 -> 3906984.4 | BR20: =BR13 -> 6 | BS20: =BO20 -> 3 | BT20: =BR20*BN20 -> 4725 | BU20: =BT20*BP20*BS20 -> 23441906 | BV20: =BV13 -> 24 | BW20: =BS20 -> 3 | BX20: =BV20*BN20*BW20 -> 56700 | BY20: =BX20*BP20 -> 93767625 | BZ20: =BZ13 -> 288 | CA20: =BW20 -> 3 | CB20: =BZ20*BN20*CA20 -> 680400 | CC20: =CB20*BP20 -> 1125211500 | CF20: 0.175 | CG20: =CF20*CE$16 -> 1400 | CH20: =CH19 -> 0.75 | CI20: =CG20*CH20 -> 1050 | CJ20: 1 | CK20: =CI20*CJ20 -> 1050 | CL20: =CL13 -> 1 | CM20: =CK20*CL20 -> 1050 | CN20: =CN19 -> 3 | CO20: =CO13 -> 1736.4375 | CP20: =CO20*CM20*CN20 -> 5469778.1 | CQ20: =CQ13 -> 6 | CR20: =CN20 -> 3 | CS20: =CQ20*CM20 -> 6300 | CT20: =CS20*CO20*CR20 -> 32818669 | CU20: =CU13 -> 24 | CV20: =CR20 -> 3 | CW20: =CU20*CM20*CV20 -> 75600 | CX20: =CW20*CO20 -> 131274675 | CY20: =CY13 -> 288 | CZ20: =CV20 -> 3 | DA20: =CY20*CM20*CZ20 -> 907200 | DB20: =DA20*CO20 -> 1575296100 | DE20: 0.175 | DF20: =DE20*DD$16 -> 1750 | DG20: =DG19 -> 0.75 | DH20: =DF20*DG20 -> 1312.5 | DI20: 1 | DJ20: =DH20*DI20 -> 1312.5 | DK20: =DK13 -> 1 | DL20: =DJ20*DK20 -> 1312.5 | DM20: =DM19 -> 3 | DN20: =DN13 -> 1823.2594 | DO20: =DN20*DL20*DM20 -> 7179083.8 | DP20: =DP13 -> 6 | DQ20: =DM20 -> 3 | DR20: =DP20*DL20 -> 7875 | DS20: =DR20*DN20*DQ20 -> 43074503 | DT20: =DT13 -> 24 | DU20: =DQ20 -> 3 | DV20: =DT20*DL20*DU20 -> 94500 | DW20: =DV20*DN20 -> 1.7229801e+08 | DX20: =DX13 -> 288 | DY20: =DU20 -> 3 | DZ20: =DX20*DL20*DY20 -> 1134000 | EA20: =DZ20*DN20 -> 2.0675761e+09 | ED20: 0.175 | EE20: =ED20*EC$16 -> 1750 | EF20: =EF19 -> 0.75 | EG20: =EE20*EF20 -> 1312.5 | EH20: 1 | EI20: =EG20*EH20 -> 1312.5 | EJ20: =EJ13 -> 1 | EK20: =EI20*EJ20 -> 1312.5 | EL20: =EL19 -> 3 | EM20: =EM13 -> 1914.4223 | EN20: =EM20*EK20*EL20 -> 7538038 | EO20: =EO13 -> 6 | EP20: =EL20 -> 3 | EQ20: =EO20*EK20 -> 7875 | ER20: =EQ20*EM20*EP20 -> 45228228 | ES20: =ES13 -> 24 | ET20: =EP20 -> 3 | EU20: =ES20*EK20*ET20 -> 94500 | EV20: =EU20*EM20 -> 1.8091291e+08 | EW20: =EW13 -> 288 | EX20: =ET20 -> 3 | EY20: =EW20*EK20*EX20 -> 1134000 | EZ20: =EY20*EM20 -> 2.1709549e+09 | FC20: 0.175 | FD20: =FC20*FB$16 -> 1750 | FE20: =FE19 -> 0.75 | FF20: =FD20*FE20 -> 1312.5 | FG20: 1 | FH20: =FF20*FG20 -> 1312.5 | FI20: =FI13 -> 1 | FJ20: =FH20*FI20 -> 1312.5 | FK20: =FK19 -> 3 | FL20: =FL13 -> 2010.1435 | FM20: =FL20*FJ20*FK20 -> 7914939.9 | FN20: =FN13 -> 6 | FO20: =FK20 -> 3 | FP20: =FN20*FJ20 -> 7875 | FQ20: =FP20*FL20*FO20 -> 47489639 | FR20: =FR13 -> 24 | FS20: =FO20 -> 3 | FT20: =FR20*FJ20*FS20 -> 94500 | FU20: =FT20*FL20 -> 1.8995856e+08 | FV20: =FV13 -> 288 | FW20: =FS20 -> 3 | FX20: =FV20*FJ20*FW20 -> 1134000 | FY20: =FX20*FL20 -> 2.2795027e+09 | GB20: 0.175 | GC20: =GB20*GA$16 -> 1750 | GD20: =GD19 -> 0.75 | GE20: =GC20*GD20 -> 1312.5 | GF20: 1 | GG20: =GE20*GF20 -> 1312.5 | GH20: =GH13 -> 1 | GI20: =GG20*GH20 -> 1312.5 | GJ20: =GJ19 -> 3 | GK20: =GK13 -> 2110.6506 | GL20: =GK20*GI20*GJ20 -> 8310686.9 | GM20: =GM13 -> 6 | GN20: =GJ20 -> 3 | GO20: =GM20*GI20 -> 7875 | GP20: =GO20*GK20*GN20 -> 49864121 | GQ20: =GQ13 -> 24 | GR20: =GN20 -> 3 | GS20: =GQ20*GI20*GR20 -> 94500 | GT20: =GS20*GK20 -> 1.9945648e+08 | GU20: =GU13 -> 288 | GV20: =GR20 -> 3 | GW20: =GU20*GI20*GV20 -> 1134000 | GX20: =GW20*GK20 -> 2.3934778e+09 | HA20: 0.175 | HB20: =HA20*GZ$16 -> 1750 | HC20: =HC19 -> 0.75 | HD20: =HB20*HC20 -> 1312.5 | HE20: 1 | HF20: =HD20*HE20 -> 1312.5 | HG20: =HG13 -> 1 | HH20: =HF20*HG20 -> 1312.5 | HI20: =HI19 -> 3 | HJ20: =HJ13 -> 2216.1832 | HK20: =HJ20*HH20*HI20 -> 8726221.2 | HL20: =HL13 -> 6 | HM20: =HI20 -> 3 | HN20: =HL20*HH20 -> 7875 | HO20: =HN20*HJ20*HM20 -> 52357327 | HP20: =HP13 -> 24 | HQ20: =HM20 -> 3 | HR20: =HP20*HH20*HQ20 -> 94500 | HS20: =HR20*HJ20 -> 2.0942931e+08 | HT20: =HT13 -> 288 | HU20: =HQ20 -> 3 | HV20: =HT20*HH20*HU20 -> 1134000 | HW20: =HV20*HJ20 -> 2.5131517e+09 | HZ20: 0.175 | IA20: =HZ20*HY$16 -> 1750 | IB20: =IB19 -> 0.75 | IC20: =IA20*IB20 -> 1312.5 | ID20: 1 | IE20: =IC20*ID20 -> 1312.5 | IF20: =IF13 -> 1 | IG20: =IE20*IF20 -> 1312.5 | IH20: =IH19 -> 3 | II20: =II13 -> 2326.9923 | IJ20: =II20*IG20*IH20 -> 9162532.3 | IK20: =IK13 -> 6 | IL20: =IH20 -> 3 | IM20: =IK20*IG20 -> 7875 | IN20: =IM20*II20*IL20 -> 54975194 | IO20: =IO13 -> 24 | IP20: =IL20 -> 3 | IQ20: =IO20*IG20*IP20 -> 94500 | IR20: =IQ20*II20 -> 2.1990077e+08 | IS20: =IS13 -> 288 | IT20: =IP20 -> 3 | IU20: =IS20*IG20*IT20 -> 1134000 | IV20: =IU20*II20 -> 2.6388093e+09
E21: Residential Areas (+19%) | I21: 0.105 | J21: =I21*H$16 -> 210 | K21: =K20 -> 0.75 | L21: =J21*K21 -> 157.5 | M21: 1 | N21: =L21*M21 -> 157.5 | O21: ='Parameters and Summary'!E78 -> 1 | P21: =N21*O21 -> 157.5 | Q21: =Q20 -> 3 | R21: =R14 -> 1500 | S21: =R21*P21*Q21 -> 708750 | T21: =T14 -> 6 | U21: =Q21 -> 3 | V21: =T21*P21 -> 945 | W21: =V21*R21*U21 -> 4252500 | X21: =X14 -> 24 | Y21: =U21 -> 3 | Z21: =X21*P21*Y21 -> 11340 | AA21: =Z21*R21 -> 17010000 | AB21: =AB14 -> 288 | AC21: =Y21 -> 3 | AD21: =AB21*P21*AC21 -> 136080 | AE21: =AD21*R21 -> 204120000 | AH21: 0.105 | AI21: =AH21*AG$16 -> 420 | AJ21: =AJ20 -> 0.75 | AK21: =AI21*AJ21 -> 315 | AL21: 1 | AM21: =AK21*AL21 -> 315 | AN21: =AN14 -> 1 | AO21: =AM21*AN21 -> 315 | AP21: =AP20 -> 3 | AQ21: =AQ14 -> 1575 | AR21: =AQ21*AO21*AP21 -> 1488375 | AS21: =AS14 -> 6 | AT21: =AP21 -> 3 | AU21: =AS21*AO21 -> 1890 | AV21: =AU21*AQ21*AT21 -> 8930250 | AW21: =AW14 -> 24 | AX21: =AT21 -> 3 | AY21: =AW21*AO21*AX21 -> 22680 | AZ21: =AY21*AQ21 -> 35721000 | BA21: =BA14 -> 288 | BB21: =AX21 -> 3 | BC21: =BA21*AO21*BB21 -> 272160 | BD21: =BC21*AQ21 -> 428652000 | BG21: 0.105 | BH21: =BG21*BF$16 -> 630 | BI21: =BI20 -> 0.75 | BJ21: =BH21*BI21 -> 472.5 | BK21: 1 | BL21: =BJ21*BK21 -> 472.5 | BM21: =BM14 -> 1 | BN21: =BL21*BM21 -> 472.5 | BO21: =BO20 -> 3 | BP21: =BP14 -> 1653.75 | BQ21: =BP21*BN21*BO21 -> 2344190.6 | BR21: =BR14 -> 6 | BS21: =BO21 -> 3 | BT21: =BR21*BN21 -> 2835 | BU21: =BT21*BP21*BS21 -> 14065144 | BV21: =BV14 -> 24 | BW21: =BS21 -> 3 | BX21: =BV21*BN21*BW21 -> 34020 | BY21: =BX21*BP21 -> 56260575 | BZ21: =BZ14 -> 288 | CA21: =BW21 -> 3 | CB21: =BZ21*BN21*CA21 -> 408240 | CC21: =CB21*BP21 -> 675126900 | CF21: 0.105 | CG21: =CF21*CE$16 -> 840 | CH21: =CH20 -> 0.75 | CI21: =CG21*CH21 -> 630 | CJ21: 1 | CK21: =CI21*CJ21 -> 630 | CL21: =CL14 -> 1 | CM21: =CK21*CL21 -> 630 | CN21: =CN20 -> 3 | CO21: =CO14 -> 1736.4375 | CP21: =CO21*CM21*CN21 -> 3281866.9 | CQ21: =CQ14 -> 6 | CR21: =CN21 -> 3 | CS21: =CQ21*CM21 -> 3780 | CT21: =CS21*CO21*CR21 -> 19691201 | CU21: =CU14 -> 24 | CV21: =CR21 -> 3 | CW21: =CU21*CM21*CV21 -> 45360 | CX21: =CW21*CO21 -> 78764805 | CY21: =CY14 -> 288 | CZ21: =CV21 -> 3 | DA21: =CY21*CM21*CZ21 -> 544320 | DB21: =DA21*CO21 -> 945177660 | DE21: 0.105 | DF21: =DE21*DD$16 -> 1050 | DG21: =DG20 -> 0.75 | DH21: =DF21*DG21 -> 787.5 | DI21: 1 | DJ21: =DH21*DI21 -> 787.5 | DK21: =DK14 -> 1 | DL21: =DJ21*DK21 -> 787.5 | DM21: =DM20 -> 3 | DN21: =DN14 -> 1823.2594 | DO21: =DN21*DL21*DM21 -> 4307450.3 | DP21: =DP14 -> 6 | DQ21: =DM21 -> 3 | DR21: =DP21*DL21 -> 4725 | DS21: =DR21*DN21*DQ21 -> 25844702 | DT21: =DT14 -> 24 | DU21: =DQ21 -> 3 | DV21: =DT21*DL21*DU21 -> 56700 | DW21: =DV21*DN21 -> 1.0337881e+08 | DX21: =DX14 -> 288 | DY21: =DU21 -> 3 | DZ21: =DX21*DL21*DY21 -> 680400 | EA21: =DZ21*DN21 -> 1.2405457e+09 | ED21: 0.105 | EE21: =ED21*EC$16 -> 1050 | EF21: =EF20 -> 0.75 | EG21: =EE21*EF21 -> 787.5 | EH21: 1 | EI21: =EG21*EH21 -> 787.5 | EJ21: =EJ14 -> 1 | EK21: =EI21*EJ21 -> 787.5 | EL21: =EL20 -> 3 | EM21: =EM14 -> 1914.4223 | EN21: =EM21*EK21*EL21 -> 4522822.8 | EO21: =EO14 -> 6 | EP21: =EL21 -> 3 | EQ21: =EO21*EK21 -> 4725 | ER21: =EQ21*EM21*EP21 -> 27136937 | ES21: =ES14 -> 24 | ET21: =EP21 -> 3 | EU21: =ES21*EK21*ET21 -> 56700 | EV21: =EU21*EM21 -> 1.0854775e+08 | EW21: =EW14 -> 288 | EX21: =ET21 -> 3 | EY21: =EW21*EK21*EX21 -> 680400 | EZ21: =EY21*EM21 -> 1.302573e+09 | FC21: 0.105 | FD21: =FC21*FB$16 -> 1050 | FE21: =FE20 -> 0.75 | FF21: =FD21*FE21 -> 787.5 | FG21: 1 | FH21: =FF21*FG21 -> 787.5 | FI21: =FI14 -> 1 | FJ21: =FH21*FI21 -> 787.5 | FK21: =FK20 -> 3 | FL21: =FL14 -> 2010.1435 | FM21: =FL21*FJ21*FK21 -> 4748963.9 | FN21: =FN14 -> 6 | FO21: =FK21 -> 3 | FP21: =FN21*FJ21 -> 4725 | FQ21: =FP21*FL21*FO21 -> 28493784 | FR21: =FR14 -> 24 | FS21: =FO21 -> 3 | FT21: =FR21*FJ21*FS21 -> 56700 | FU21: =FT21*FL21 -> 1.1397513e+08 | FV21: =FV14 -> 288 | FW21: =FS21 -> 3 | FX21: =FV21*FJ21*FW21 -> 680400 | FY21: =FX21*FL21 -> 1.3677016e+09 | GB21: 0.105 | GC21: =GB21*GA$16 -> 1050 | GD21: =GD20 -> 0.75 | GE21: =GC21*GD21 -> 787.5 | GF21: 1 | GG21: =GE21*GF21 -> 787.5 | GH21: =GH14 -> 1 | GI21: =GG21*GH21 -> 787.5 | GJ21: =GJ20 -> 3 | GK21: =GK14 -> 2110.6506 | GL21: =GK21*GI21*GJ21 -> 4986412.1 | GM21: =GM14 -> 6 | GN21: =GJ21 -> 3 | GO21: =GM21*GI21 -> 4725 | GP21: =GO21*GK21*GN21 -> 29918473 | GQ21: =GQ14 -> 24 | GR21: =GN21 -> 3 | GS21: =GQ21*GI21*GR21 -> 56700 | GT21: =GS21*GK21 -> 1.1967389e+08 | GU21: =GU14 -> 288 | GV21: =GR21 -> 3 | GW21: =GU21*GI21*GV21 -> 680400 | GX21: =GW21*GK21 -> 1.4360867e+09 | HA21: 0.105 | HB21: =HA21*GZ$16 -> 1050 | HC21: =HC20 -> 0.75 | HD21: =HB21*HC21 -> 787.5 | HE21: 1 | HF21: =HD21*HE21 -> 787.5 | HG21: =HG14 -> 1 | HH21: =HF21*HG21 -> 787.5 | HI21: =HI20 -> 3 | HJ21: =HJ14 -> 2216.1832 | HK21: =HJ21*HH21*HI21 -> 5235732.7 | HL21: =HL14 -> 6 | HM21: =HI21 -> 3 | HN21: =HL21*HH21 -> 4725 | HO21: =HN21*HJ21*HM21 -> 31414396 | HP21: =HP14 -> 24 | HQ21: =HM21 -> 3 | HR21: =HP21*HH21*HQ21 -> 56700 | HS21: =HR21*HJ21 -> 1.2565759e+08 | HT21: =HT14 -> 288 | HU21: =HQ21 -> 3 | HV21: =HT21*HH21*HU21 -> 680400 | HW21: =HV21*HJ21 -> 1.507891e+09 | HZ21: 0.105 | IA21: =HZ21*HY$16 -> 1050 | IB21: =IB20 -> 0.75 | IC21: =IA21*IB21 -> 787.5 | ID21: 1 | IE21: =IC21*ID21 -> 787.5 | IF21: =IF14 -> 1 | IG21: =IE21*IF21 -> 787.5 | IH21: =IH20 -> 3 | II21: =II14 -> 2326.9923 | IJ21: =II21*IG21*IH21 -> 5497519.4 | IK21: =IK14 -> 6 | IL21: =IH21 -> 3 | IM21: =IK21*IG21 -> 4725 | IN21: =IM21*II21*IL21 -> 32985116 | IO21: =IO14 -> 24 | IP21: =IL21 -> 3 | IQ21: =IO21*IG21*IP21 -> 56700 | IR21: =IQ21*II21 -> 1.3194046e+08 | IS21: =IS14 -> 288 | IT21: =IP21 -> 3 | IU21: =IS21*IG21*IT21 -> 680400 | IV21: =IU21*II21 -> 1.5832856e+09
